Workbook
Name BICSFI: 'Overview of Revisions'!#REF!
Name BICSGOVT: 'Overview of Revisions'!#REF!
Name EQUITY: 'Overview of Revisions'!#REF!
Name GOVSECTOR: 'Overview of Revisions'!$B$159
Name LANG: 'How To Download'!$C$4
Name LANG4MAP: 'Mapping for Fixed Income'!$B$2
Name LANG4MAP: 'Mapping for Equity'!$B$2
Name OVERTOP: 'Overview of Revisions'!$A$1:$A$1
Name TICKER: 'BICS Fixed Income'!$A$5
Name TICKER: 'How To Download'!$B$5
Name TOP: 'Table of Contents'!$A$3

Sheet Table of Contents
B3: Table of Contents
B4: 1 | C4: Overview of Revisions | D4: - | E4: Overview of Revisions to BICS Equity 2024 Hierarchy
B5: 2 | C5: BICS Equity 2024 Hierarchy | D5: - | E5: BICS Equity 2024 Hierarchy (Level 1 ~ 7) with Codes, Names, and Definitions
B6: 3 | C6: BICS Fixed Income Hierarchy | D6: - | E6: BICS Fixed Income 2014 Hierarchy (Level 1 ~ 2) with Codes and Names
B7: 4 | C7: How To Download | D7: - | E7: Tutorial on How To Download BICS Data Through API
B8: 5 | C8: Mapping for Equity | D8: - | E8: Mapping Between BICS Equity 2020 Hierarchy and BICS Equity 2024 Hierarchy
B9: 6 | C9: Mapping for Fixed Income | D9: - | E9: Mapping Between BICS Equity 2024 Hierarchy and BICS Fixed Income 2014 Hierarchy
B10: 8 | C10: Comparison Template | D10: - | E10: API Template that provide BICS Equity 2024 Classification Data For a List of Entities
B12: Notes:
B13: * | C13: The BICS hierarchy revision is implemented only for Equity. Legacy BICS (DS199, DS201, DS202) remains the same.
B14: ** | C14: BICS fixed income hierarchy remains the same until further notice.

Sheet Overview of Revisions
O1: Back to Table of Contents
B3: Overview of BICS 2024 Revisions (Effective Date: June 7, 2024)
B6: Sector Moves for previous BICS Classifications - These classifications moved from one sector to another sector in the BICS hierarchy
B7: BICS Code | C7: Level | D7: BICS Name | E7: BICS Sector | F7: Prior BICS Code | G7: Prior BICS Sector
B8: 1411111311 | C8: 5 | D8: Financial Transaction Processors | E8: Financials | F8: 1911111210 | G8: Technology
B9: 1411111312 | C9: 5 | D9: Financial Info Services | E9: Financials | F9: 1911111110 | G9: Technology
B10: 141111131210 | C10: 6 | D10: Credit Agencies | E10: Financials | F10: 191111111010 | G10: Technology
B11: 141111131211 | C11: 6 | D11: Data & Analytics | E11: Financials | F11: 191111111011 | G11: Technology
B13: Dropped BICS Classifications - These are BICS Equity 2020 classifications that were removed from the BICS hierarchy
B14: BICS Code | C14: Level | D14: BICS Name | E14: BICS Sector
B15: 171113101310 | C15: 6 | D15: Environ Consulting Services | E15: Industrials
B16: 171113101311 | C16: 6 | D16: Environ Engineering Services | E16: Industrials
B17: 19111111 | C17: 4 | D17: Information Services | E17: Technology
B18: 1911111111 | C18: 5 | D18: Non-Financial Info Services | E18: Technology
B19: 191111111110 | C19: 6 | D19: Health Care Information | E19: Technology
B20: 191111111111 | C20: 6 | D20: Legal Information | E20: Technology
B21: 191111111112 | C21: 6 | D21: Real Estate Information | E21: Technology
B22: 191111111113 | C22: 6 | D22: Scientific Information | E22: Technology
B23: 191111111114 | C23: 6 | D23: Technology Information | E23: Technology
B24: 19111112 | C24: 4 | D24: Data & Transaction Processors | E24: Technology
B25: 1911111211 | C25: 5 | D25: Non-Financial Data Processors | E25: Technology
B27: New BICS Classifications for Entity assignment - These classifications already existed for Segment assignment only
B28: BICS Code | C28: Level | D28: BICS Name | E28: BICS Sector
B29: 111011101010 | C29: 6 | D29: Cars - Electric | E29: Consumer Discretionary
B30: 111011101011 | C30: 6 | D30: Cars - Fossil Fuels | E30: Consumer Discretionary
B31: 111011101110 | C31: 6 | D31: Light Trucks - Electric | E31: Consumer Discretionary
B32: 111011101111 | C32: 6 | D32: Light Trucks - Fossil Fuels | E32: Consumer Discretionary
B33: 111011101210 | C33: 6 | D33: Motorcycles - Electric | E33: Consumer Discretionary
B34: 111011101211 | C34: 6 | D34: Motorcycles - Fossil Fuels | E34: Consumer Discretionary
B35: 11121110131010 | C35: 7 | D35: Passenger Veh Leasing - Electric | E35: Consumer Discretionary
B36: 11121110131011 | C36: 7 | D36: Passenger Veh Leasing - Fossil Fuels | E36: Consumer Discretionary
B37: 11121110131110 | C37: 7 | D37: Passenger Veh Rental - Electric | E37: Consumer Discretionary
B38: 11121110131111 | C38: 7 | D38: Passenger Veh Rental - Fossil Fuels | E38: Consumer Discretionary
B39: 14111110111110 | C39: 7 | D39: Comml Veh Fin & Leasing - Electric | E39: Financials
B40: 14111110111111 | C40: 7 | D40: Comml Veh Fin & Leasing - Fossil Fuels | E40: Financials
... B89: 201011101013 | C89: 6 | D89: CO2 Transmission & Storage | E89: Utilities
B91: New BICS Classifications - These classifications were added in the BICS Equity 2024 hierarchy
B92: BICS Code | C92: Level | D92: BICS Name | E92: BICS Sector
B93: 101012101013 | C93: 6 | D93: Online Film & TV Streaming | E93: Communications
B94: 1010141024 | C94: 5 | D94: Online Transport & Delivery Svcs | E94: Communications
B95: 101014102410 | C95: 6 | D95: Online Food Delivery Svcs | E95: Communications
B96: 101014102411 | C96: 6 | D96: Ridesharing Svcs | E96: Communications
B97: 111011112510 | C97: 6 | D97: Electric Vehicle Batteries | E97: Consumer Discretionary
B98: 111011112511 | C98: 6 | D98: Starter Batteries | E98: Consumer Discretionary
B99: 1112111825 | C99: 5 | D99: Electric Vehicle Charging Stations | E99: Consumer Discretionary
B100: 121010101319 | C100: 6 | D100: Coffee Farming | E100: Consumer Staples
B101: 121010101412 | C101: 6 | D101: Cocoa & Coffee Processing | E101: Consumer Staples
B102: 12101010141210 | C102: 7 | D102: Cocoa Processing | E102: Consumer Staples
B103: 12101010141211 | C103: 7 | D103: Coffee Processing | E103: Consumer Staples
B104: 1210101120 | C104: 5 | D104: Protein, Dairy & Other Food Alt | E104: Consumer Staples
... B111: 1710121014 | C111: 5 | D111: Electric Vehicle Supply Equip | E111: Industrials
B113: Name Changes to Existing BICS Classifications
B114: BICS Code | C114: Level | D114: BICS Name | E114: Prior BICS Name
B115: 1110111010 | C115: 5 | D115: Cars | E115: Passenger Vehicles
B116: 1110131310 | C116: 5 | D116: Stationery | E116: Stationary
B117: 1210101014 | C117: 5 | D117: Food Crop Processing | E117: Sugar, Grain & Oilseed Mill
B118: 1210101118 | C118: 5 | D118: Snack Food & Confectionery | E118: Snack Food & Confectionary
B119: 12101011181011 | C119: 7 | D119: Sugar & Other Confectionery | E119: Sugar & Other Confectionary
B120: 131010 | C120: 3 | D120: Oil & Gas Supply Chain | E120: Oil & Gas Producers
B121: 1411101012 | C121: 5 | D121: Blank Check | E121: SPAC
B122: 1710121012 | C122: 5 | D122: Lighting Fixtures | E122: Lighting Fixture
B123: 171012101210 | C123: 6 | D123: Commercial Light Fixtures | E123: Commercial Light Fixture
B124: 171012101211 | C124: 6 | D124: Residential Light Fixtures | E124: Residential Light Fixture
B125: 171111161010 | C125: 6 | D125: Law Firms | E125: Lawyer Offices
B126: 1711131013 | C126: 5 | D126: Environmental Engineering Svcs | E126: Environ Engineer & Consulting
... B135: 20101011121511 | C135: 7 | D135: Biomass & Waste - Deregulated | E135: Biomass & Waste - Unregulated
L139: =HYPERLINK("bbg://screens/ICS BICS","Click Here To See The Full Revised Hierarchy On Terminal") -> Click Here To See The Full Revised Hierarchy On Terminal
B140: Back to Top

Sheet BICS Equity Hierarchy 2024
H2: Back to Table of Contents
G3: =HYPERLINK("bbg://screens/ICS BICS","Click HERE to see the BICS hierarchy on terminal") -> Click HERE to see the BICS hierarchy on terminal
B4: Changes | C4: BICS Code | D4: Level | E4: BICS Name | F4: BICS Name (Long Name) | G4: Definitions | H4: 日本語 DX616=2 | I4: Français DX616=3 | J4: Deutsch DX616=4 | K4: Español DX616=5 | L4: Português DX616=6 | M4: Italiano DX616=7 | N4: 繁體中文 DX616=8 | O4: 한국어 DX616=9 | P4: 简体中文 DX616=10 | Q4: Русский DX616=16
C5: 10 | D5: 1 | E5: Communications | F5: Communications | G5: This sector includes companies facilitating communication or creating and distributing content. | H5: 通信 | I5: Communications | J5: Kommunikation | K5: Comunicaciones | L5: Comunicações | M5: Comunicazioni | N5: 通訊 | O5: 통신 | P5: 通讯 | Q5: Коммуникации
C6: 1010 | D6: 2 | E6: Media | F6: Media | G6: This industry group includes companies that create, distribute, or publish media content. Media content includes many formats, such as print, advertisements, motion pictures, television, music, radio, and Internet websites. Also included are cable and satellite providers. | H6: ﾒﾃﾞｨｱ | I6: Médias | J6: Medien | K6: Prensa | L6: Mídia | M6: Media | N6: 媒體 | O6: 미디어 | P6: 媒体 | Q6: СМИ
C7: 101010 | D7: 3 | E7: Advertising & Marketing | F7: Advertising & Marketing | G7: This industry includes companies that provide advertising and marketing services. Includes the creation of advertising campaigns for use in media, display, or direct mail advertising and other related services. | H7: 広告･ﾏｰｹﾃｨﾝｸﾞ | I7: Publicité et marketing | J7: Werbung & Marketing | K7: Publicidad y mercadeo | L7: Publicidade e Marketing | M7: Pubblicità e marketing | N7: 廣告及行銷 | O7: 광고 & 마케팅 | P7: 广告与营销 | Q7: Реклама и маркетинг
C8: 10101010 | D8: 4 | E8: Advertising & Marketing | F8: Advertising & Marketing | G8: This industry subgroup includes companies that provide advertising and marketing services. Includes the creation of advertising campaigns for use in media, display, or direct mail advertising and other related services. | H8: 広告･ﾏｰｹﾃｨﾝｸﾞ | I8: Publicité et marketing | J8: Werbung & Marketing | K8: Publicidad y mercadeo | L8: Publicidade e Marketing | M8: Pubblicità e marketing | N8: 廣告及行銷 | O8: 광고 & 마케팅 | P8: 广告营销 | Q8: Реклама и маркетинг
C9: 1010101010 | D9: 5 | E9: Advertising Agencies & Svcs | F9: Advertising Agencies & Related Service | G9: This segment includes companies that create advertising campaigns for media use, provide market research or marketing consulting services, or act as public relations or media representatives. | H9: 広告代理店･関連ｻｰﾋﾞｽ | I9: Agences/serv de publicité | J9: Werbeagenturen & -dienste | K9: Servicios y agencias de publicidad | L9: Agências de publicidade e serv | M9: Agenzie e serv pubblicitari | N9: 廣告代理及服務 | O9: 광고 대행사 & 관련 서비스 | P9: 广告代理商及相关服务 | Q9: Рекламн. агентства и услг
C10: 101010101010 | D10: 6 | E10: Advertising Agencies | F10: Advertising Agencies | G10: This segment includes companies that create advertising campaigns for use in newspapers, magazines, radio, television or other media. | H10: 広告代理店 | I10: Agences de pub | J10: Werbeagenturen | K10: Agencias publicidad | L10: Agências de propaganda | M10: Soctà pubblicitarie | N10: 廣告代理業 | O10: 광고대행사 | P10: 广告代理 | Q10: Рекламные агентства
C11: 101010101011 | D11: 6 | E11: E-Marketing | F11: E-Marketing | G11: This segment includes companies that specialize in creating advertising campaigns via Internet media. Includes email marketing, mobile and website advertising, search engine optimization, and social media marketing. | H11: eﾏｰｹﾃｨﾝｸﾞ | I11: E-Marketing | J11: E-Marketing | K11: E-Marketing | L11: Marketing online | M11: E-Marketing | N11: 電子行銷 | O11: E-마케팅 | P11: 网络营销 | Q11: Эл. маркетинг
C12: 101010101012 | D12: 6 | E12: Market Research & Consulting | F12: Market Research & Consulting | G12: This segment includes companies that provide market research, opinion polling or marketing consulting services. | H12: 市場調査･ｺﾝｻﾙﾃｨﾝｸﾞ | I12: Etude de marché et conseil | J12: Marktforschung & Beratung | K12: Estudios y consultoría de mercado | L12: Consultoria e pesquisa de mercado | M12: Consulenza e ricerca di mercato | N12: 市場研究及顧問 | O12: 시장 리서치 & 컨설팅 | P12: 市场研究和顾问 | Q12: Исследования рынка и консалтинг
C13: 10101010101210 | D13: 7 | E13: Marketing Consulting Services | F13: Marketing Consulting Services | G13: This segment includes companies that provide marketing consulting services. | H13: ﾏｰｹﾃｨﾝｸﾞｺﾝｻﾙﾃｨﾝｸﾞｻｰﾋﾞｽ | I13: Services de conseils en marketing | J13: Marketing-Consulting-Dienste | K13: Servicios de consultoría de mercadotecnia | L13: Serviços de consultoria de marketing | M13: Servizi consulenza marketing | N13: 行銷顧問服務 | O13: 시장 컨설팅 서비스 | P13: 营销咨询服务 | Q13: Консультационные услуги по маркетингу
C14: 10101010101211 | D14: 7 | E14: Market Research | F14: Market Research | G14: This segment includes companies that provide market research and opinion polling. | H14: 市場調査 | I14: Etudes de marché | J14: Marktforschung | K14: Estudios del mercado | L14: Pesquisas de mercado | M14: Ricerche di mercato | N14: 市場研究及意見調查 | O14: 시장 리서치 | P14: 市场研究 | Q14: Исследования рынка
C15: 101010101013 | D15: 6 | E15: Media Representatives | F15: Media Representatives | G15: This segment includes companies that sell media time or space on behalf of media owners. | H15: ﾒﾃﾞｨｱﾚｯﾌﾟ | I15: Représentants de médias | J15: Medienvertreter | K15: Agencias de representación de medios | L15: Representantes mídia | M15: Rappresentanti dei media | N15: 媒體代表 | O15: 광고매체판매업 | P15: 媒体代表 | Q15: Представитель средств рекламы
C16: 101010101014 | D16: 6 | E16: Public Relations Agencies | F16: Public Relations Agencies | G16: This segment includes companies that provide public relations services. Public relations services manage the communication and spread of information between their clients and the public. | H16: 広報代理店 | I16: Services de relations publiques | J16: Public-Relations-Agenturen | K16: Agencias de relaciones públicas | L16: Agências de relações públicas | M16: Agenzie di pubbliche relazioni | N16: 公共關係代理 | O16: 홍보기관 | P16: 公关代理 | Q16: Агентства по связьм с общественностью
... C34: 101012101012 | D34: 6 | E34: Teleprod & Postprod Services | F34: Teleproduction & Postproduction Services | G34: This segment includes companies that provide postproduction services for film and TV. Includes editing film, titling, subtitling, credits, and closed captioning. | H34: 番組制作･編集ｻｰﾋﾞｽ | I34: Services de téléprod et postproduction | J34: Fernsehprod. & Nachbearbeitungsdienste | K34: Servicios de tele producción y post producción | L34: Serviços de teleprodução pós prod | M34: Servizi teleprod e postprod | N34: 影像製作及後製服務 | O34: 영상제작 & 영상물 편집 서비스업 | P34: 影像制作及后期制作服务 | Q34: Телепроизв. и проч. монтажн. услуги
B35: New | C35: 101012101013 | D35: 6 | E35: Online Film & TV Streaming | F35: Online Film & TV Streaming | G35: This segment includes companies that create, acquire distribution rights, and distribute film and television shows directly to consumers online via websites or mobile applications. Excludes companies that do not produce content. | H35: ｵﾝﾗｲﾝ映画&TVｽﾄﾘｰﾐﾝｸﾞ | I35: Streaming de films/TV en ligne | J35: Streaming von Filmen & TV online | K35: Películas online y TV por streaming | L35: Streaming de filmes e TV on-line | M35: Film e TV in streaming online | N35: 線上影片及電視串流 | O35: 온라인 영화 & TV 스트리밍 | P35: 在线影视流媒体 | Q35: Онлайн вещание - фильмы и ТВ
C36: 1010121011 | D36: 5 | E36: TV Media Networks | F36: TV Media Networks | G36: This segment includes companies that aggregate, market, and distribute television programs to TV broadcasting stations, cable companies, satellite companies, and wireline telecommunications companies. Programming may be produced in-house or acquired from external sources. | H36: ﾃﾚﾋﾞﾒﾃﾞｨｱﾈｯﾄﾜｰｸ | I36: TV, médias, réseaux | J36: TV Mediennetzwerke | K36: Estaciones de medios p/tv | L36: Redes mídia televisiva | M36: Reti media TV | N36: 電視媒體網路 | O36: TV 미디어 네트워크 | P36: 电视媒体网络 | Q36: Сети ТВ-СМИ
C37: 101012101110 | D37: 6 | E37: Cable Networks | F37: Cable Networks | G37: This segment includes companies that aggregate, market, and distribute television programs to cable companies, satellite companies, and wireline telecommunications companies. These networks negotiate with local and international distributors to broadcast programming on a subscription or fee basis. | H37: ｹｰﾌﾞﾙﾈｯﾄﾜｰｸ | I37: Réseaux de câble | J37: Kabelnetze | K37: Redes de cable | L37: Redes a cabo | M37: Canali TV via cavo | N37: 有線網路 | O37: 케이블 네트워크 | P37: 有线网络 | Q37: Кабельные сети
C38: 10101210111010 | D38: 7 | E38: Adv Rev - Cable Networks | F38: Advertising Revenue - Cable Networks | G38: This segment includes revenue that cable networks generate from advertising. | H38: 広告売上高-ｹｰﾌﾞﾙﾈｯﾄﾜｰｸ | I38: Rev pub-réseaux de câble | J38: Werbeerlös - Kabelnetze | K38: Ingreso de publicidad-redes de cable | L38: Rec prop - Redes a cabo | M38: Ric pubb - Reti via cavo | N38: 廣告收入-有線網路 | O38: 광고 수익 - 케이블 네트워크 | P38: 广告收入-有线网络 | Q38: Рекл. врчк - кабельные сети
C39: 10101210111011 | D39: 7 | E39: Other Rev - Cable Networks | F39: Other Revenue - Cable Networks | G39: This segment includes revenue that cable networks generate from sources other than advertising. | H39: その他売上高-ｹｰﾌﾞﾙﾈｯﾄﾜｰｸ | I39: Autres rev- Réseaux de câble | J39: Sonstiger Erlös - Kabelnetze | K39: Otro ing-redes de cable | L39: Out rec- Redes a cabo | M39: Altri ric - Reti via cavo | N39: 其他收入-有線網路 | O39: 기타 수익 - 케이블 네트워크 | P39: 其他收入-有线网络 | Q39: Пр. выручка - кабельные сети
C40: 101012101111 | D40: 6 | E40: TV Broadcast Networks | F40: TV Broadcast Networks | G40: This segment includes companies that aggregate, market, and distribute television programs to affiliate TV broadcasting stations. These stations then transmit the programming to viewers over public airways. | H40: ﾃﾚﾋﾞ放送ﾈｯﾄﾜｰｸ | I40: Réseaux de diffusion TV | J40: TV Rundfunknetzwerke | K40: Estaciones de tv | L40: Redes transmissão televisiva | M40: Reti trasmissione TV | N40: 電視播放網路 | O40: TV 방송국 네트워크 | P40: 电视广播网络 | Q40: Сети телевещания
C41: 10101210111110 | D41: 7 | E41: Adv Rev - TV Broadcast Netw | F41: Advertising Revenue - TV Broadcast Networks | G41: This segment includes revenue that TV broadcast networks generates from advertising. | H41: 広告売上高-ﾃﾚﾋﾞ放送ﾈｯﾄﾜｰｸ | I41: Rev de pub - Réseau de diffusion télé | J41: Werbeerlös - TV Rundfunknetzwerke | K41: Ing an - estación de tv | L41: Rec prop - Redes transm televisiva | M41: Ric pub-rete TV | N41: 廣告收入-電視播放網路 | O41: 광고수익-TV 방송국 네트워크 | P41: 广告收入-电视广播网络 | Q41: Рекл. выручка - Сети телевещания
C42: 10101210111111 | D42: 7 | E42: Other Rev - TV Broadcast Netw | F42: Other Revenue - TV Broadcast Networks | G42: This segment includes revenue that TV broadcast networks generate from sources other than advertising. | H42: その他売上高-ﾃﾚﾋﾞ放送ﾈｯﾄﾜｰｸ | I42: Autres rev - Rés diffusion TV | J42: Sonst. Erlös - Fernsehübertragungsnetze | K42: Otro ingreso - retransmisión de televisión | L42: Outras rec - Redes transmissão TV | M42: Altri ric - Reti teletrasmissione | N42: 其他收入-電視播放網路 | O42: 기타 수익 - TV 방송국 네트워크 | P42: 其他收入-电视广播网络 | Q42: Пр. выручка -сети телевещ.
C43: 1010121012 | D43: 5 | E43: Royalty Income - Film & TV | F43: Royalty Income - Film & TV | G43: This segment includes companies that generate revenue from their film and television assets (such as trademarks, brand names and/or agreements) for which a royalty payment or licensing fee is paid by others. | H43: ﾛｲﾔﾙﾃｨ収入-映画･ﾃﾚﾋﾞ | I43: Royalties - film et TV | J43: Lizenzerlös - Film & TV | K43: Ing de regalías - películas y TV | L43: Receita de royalty - Filme e TV | M43: Reddito concessioni-Film e TV | N43: 權利金收入-媒體 | O43: 로열티 수익- 영화 & TV | P43: 版权收入-电影与电视 | Q43: Лиценз. сборы - кино- и ТВ
C44: 10101211 | D44: 4 | E44: Music | F44: Music | G44: This industry subgroup includes companies that acquire, produce, and distribute music content. | H44: 音楽 | I44: Musique | J44: Musik | K44: Música | L44: Música | M44: Musica | N44: 音樂製作及發行 | O44: 음악 | P44: 音乐 | Q44: Музыка
C45: 1010121110 | D45: 5 | E45: Integrated Record Prod & Distr | F45: Integrated Record Production & Distribution | G45: This segment includes companies that release, promote, and distribute sound recordings. These companies manufacture, or arrange for the manufacture of recordings, such as audio tapes/cassettes and compact discs, and promote and distribute these products to wholesalers, retailers, or directly to the public. Companies in this segment produce master recordings themselves or obtain reproduction and distribution rights to master recordings produced by record production companies or other integrated record companies. | H45: 総合ﾚｺｰﾄﾞ制作･配給 | I45: Prod int d'enregistrements et distrib | J45: Integrierte Musikprod. & -vertrieb | K45: Produc y distr grabación integr | L45: Prod e dist de gravação integrada | M45: Prod e distrib registrazioni integrate | N45: 整合唱片製作及發行 | O45: 통합 음반 제작 & 배급 | P45: 综合录音制品制作与发行 | Q45: Объед. запись и распрост. пластинок
C46: 1010121111 | D46: 5 | E46: Music Publishers | F46: Music Publishers | G46: This segment includes companies that acquire and register copyrights for musical compositions, and promote and authorize the use of these compositions in recordings, radio, television, motion pictures, live performances, print or other media. Companies in this segment represent the interests of the songwriter or other owners of musical compositions to produce revenues from the use of such works, generally through licensing agreements. These companies may own the copyright or act as administrator of the music copyrights on behalf of copyright owners. Publishers of music books and sheet music are included in this segment. | H46: 音楽出版 | I46: Editeurs de musique | J46: Musikverleger | K46: Editoras de música | L46: Editoras de música | M46: Editori di musica | N46: 音樂出版 | O46: 음반 제작업 | P46: 音乐出版商 | Q46: Издатели муз. произведений
C47: 1010121112 | D47: 5 | E47: Record Production | F47: Record Production | G47: This segment includes companies that produce records, tapes, and compact discs. These companies contract with artists and arrange and finance the production of original master recordings. These companies also hold the copyright to the master recording and derive most of their revenues from the sales, leasing, and licensing of master recordings. Such companies do not have their own duplication or distribution capabilities. | H47: ﾚｺｰﾄﾞ制作 | I47: Prod. enreg. sonore | J47: Musikproduktion | K47: Producción de discos | L47: Produção de disco | M47: Produzione di dischi | N47: 唱片製作 | O47: 음반 제작업 | P47: 录制产品制作 | Q47: Запись пластинок
... C117: 101014102311 | D117: 6 | E117: Other Rev - Social Networking Web | F117: Other Revenue - Social Networking Websites | G117: This segment includes revenue that social networking websites generate from sources other than advertising. | H117: その他売上高-ｿｰｼｬﾙﾈｯﾄﾜｰｷﾝｸﾞWebｻｲﾄ | I117: Autrs rev - Sites Web rés soc | J117: Sonst. Erl. - Social-Networking-Web. | K117: Otro ing - redes sociales | L117: Out rec - Sites da rede social | M117: Altri ric - Web rete sociale | N117: 其他收入-社交網站 | O117: 기타 수익 - 소셜 네트워킹 웹 | P117: 其他收入-社交网络 | Q117: Пр. врчк - Веб-сайты Интернет-сообществ
B118: New | C118: 1010141024 | D118: 5 | E118: Online Transport & Delivery Svcs | F118: Online Transport & Delivery Svcs | G118: This segment includes companies that offer transportation or delivery services online or via applications. These companies do not own the mode of transportation. | H118: ｵﾝﾗｲﾝ輸送･配送ｻｰﾋﾞｽ | I118: Svcs transp/livraison en ligne | J118: Online-Transport- & Lieferdienste | K118: Servicios de transporte y entrega en línea | L118: Serv online de transporte e entrega | M118: Serv di Trasporto e consegna online | N118: 線上運輸及外送服務 | O118: 온라인 운송 및 배달 서비스 | P118: 在线快递物流服务 | Q118: Онлайн услуги транспортировки и доставки
B119: New | C119: 101014102410 | D119: 6 | E119: Online Food Delivery Svcs | F119: Online Food Delivery Svcs | G119: This segment includes companies that offer food delivery services online or via applications. These companies do not own the mode of transportation. | H119: ｵﾝﾗｲﾝ食品配達ｻｰﾋﾞｽ | I119: Svcs de livraison de repas en ligne | J119: Online-Lebensmittellieferungen | K119: Serv en línea de entrega de comida | L119: Serv online para entrega de alimentos | M119: Serv consegna cibo online | N119: 線上食品外送服務 | O119: 온라인 식품 배달 서비스 | P119: 在线外卖服务 | Q119: Онлайн услуги по доставки продуктов питания
B120: New | C120: 101014102411 | D120: 6 | E120: Ridesharing Svcs | F120: Ridesharing Svcs | G120: This segment includes companies that offer ridesharing or other services for the transportation of individuals online or via applications. These companies do not own the mode of transportation. | H120: ﾗｲﾄﾞｼｪｱｻｰﾋﾞｽ | I120: Svcs covoiturage | J120: Mitfahrservice | K120: Serv transporte compartido | L120: Serv de transporte compartilhado | M120: Serv de transporte compartilhado | N120: 共乘服務 | O120: 차량공유 서비스 | P120: 拼车服务 | Q120: Услуги райдшеринга
C121: 1011 | D121: 2 | E121: Telecommunications | F121: Telecommunications | G121: This industry group includes companies that provide telecommunication services. Excludes cable companies that offer telecommunication services. | H121: 電気通信 | I121: Télécommunications | J121: Telekommunikation | K121: Telecomunicaciones | L121: Telecomunicações | M121: Telecomunicazioni | N121: 電信 | O121: 정보통신 | P121: 电信 | Q121: Связь
C122: 101110 | D122: 3 | E122: Telecommunications | F122: Telecommunications | G122: This industry includes companies that provide a broad range of telecommunications services including wireless and wireline services and satellite services including voice, video and/or data. Also includes companies that sell wholesale access to other service providers. Excludes cable multiple system operators (MSOs). (See Cable Cable & Satellite) | H122: 電気通信 | I122: Télécommunications | J122: Telekommunikation | K122: Telecomunicaciones | L122: Telecomunicações | M122: Telecomunicazioni | N122: 電信 | O122: 정보통신 | P122: 电信 | Q122: Связь
C123: 10111010 | D123: 4 | E123: Wireless Telecommunications | F123: Wireless Telecommunications Services | G123: This industry subgroup includes companies that use a wireless infrastructure to provide a variety of services, such as wireless telephony services, wireless data services, text messaging/short messaging services (SMS), roaming, wireless Internet services, and satellite telecommunications. These companies have spectrum licenses and provide services using that spectrum. | H123: 無線通信 | I123: Télécommunications sans fil | J123: Drahtlose Telekommunikation | K123: Telecomunicación inalámbrica | L123: Telecomunicações rede s/fio | M123: Telecomunicazione senza fili | N123: 無線通訊服務 | O123: 무선 정보통신 | P123: 无线电信 | Q123: Беспроводная связь
C124: 1011101010 | D124: 5 | E124: Wireless Service Providers | F124: Wireless Service Providers | G124: This segment includes companies that provide mobile phone services, such as telephone voice services, data services, text messaging services, and roaming services. | H124: ﾜｲﾔﾚｽｻｰﾋﾞｽﾌﾟﾛﾊﾞｲﾀﾞｰ | I124: Fournisseurs services sans fil | J124: Drahtlose Service-Anbieter | K124: Proveedores de servicios inhalámbricos | L124: Provedores de serviços sem fios | M124: Fornitori servizi wireless | N124: 無線服務供應商 | O124: 이동통신서비스 제공업체 | P124: 无线服务供应商 | Q124: Провайдеры беспроводной связи
C125: 101110101010 | D125: 6 | E125: Mobile Phone Services | F125: Mobile Phone Services | G125: This segment includes wireless carriers that offer mobile voice services. | H125: 携帯電話ｻｰﾋﾞｽ | I125: Services téléphoniques mobiles | J125: Mobilfunkdienste | K125: Servicios de teléfono móvil | L125: Serviços de telefone celular | M125: Servizi telefonia mobile | N125: 行動語音服務 | O125: 휴대전화 서비스 | P125: 移动电话服务 | Q125: Услуги мобильных телефонов
C126: 101110101011 | D126: 6 | E126: Mobile Data Services | F126: Mobile Data Services | G126: This segment includes wireless carriers that provide a broad range of mobile data services, such as wireless Internet access, video, games, ring tones, and music. | H126: 携帯通信ﾃﾞｰﾀｻｰﾋﾞｽ | I126: Services données mobiles | J126: Mobile Datendienste | K126: Servicios móviles de datos | L126: Serviços dados móvel | M126: Servizi dati Mobili | N126: 行動數據服務 | O126: 모바일 데이터 서비스 | P126: 移动数据服务 | Q126: Мобильн. усл. данных
C127: 101110101012 | D127: 6 | E127: Mobile Text Messaging (SMS) | F127: Mobile Text Messaging (SMS) | G127: This segment includes wireless carriers that offer mobile short message service (SMS), also known as text messaging. | H127: 携帯ﾃｷｽﾄﾒｯｾｰｼﾞ(SMS) | I127: Message texte (SMS) par mobile | J127: Textnachrichten (SMS) | K127: Mensajes de texto en celulares (SMS) | L127: Mensagem de texto de telefone móvel | M127: Messaggi (SMS) | N127: 行動簡訊(SMS) | O127: 모바일 문자 메시지 (SMS) | P127: 手机短信 (SMS) | Q127: Мобильные текстовые сообщения (SMS)
C128: 101110101013 | D128: 6 | E128: Mobile Roaming Services | F128: Mobile Roaming Services | G128: This segment includes wireless carriers that provide mobile roaming services. Such services allow subscribers from other carriers' networks to make and receive calls over its network. | H128: 携帯ﾛｰﾐﾝｸﾞｻｰﾋﾞｽ | I128: Services d'itinérance de mobiles | J128: Mobile Roaming-Dienste | K128: Servicios móviles de itinerancia | L128: Serviços roaming móvel | M128: Servizi roaming Mobile | N128: 行動漫遊服務 | O128: 모바일 로밍 서비스 | P128: 移动漫游服务 | Q128: Мобильные услуги роуминга
C129: 101110101014 | D129: 6 | E129: Wireless Infra Access Revenue | F129: Wireless Infrastructure Access Revenue | G129: This segment includes carriers that sell wireless network capacity on a wholesale basis to other wireless service providers who, in turn, use this network capacity to market branded mobile services to their customers. | H129: 無線ｲﾝﾌﾗ接続収入 | I129: Revenus d'accès infra sans fil | J129: Erlös kabelloser Infrastrukturzugang | K129: Ingreso de acceso al infraestructura inalámbrica | L129: Receita de acesso infra sem fio | M129: Ricavi accesso infrastruttura senza fili | N129: 無線基礎建設使用收入 | O129: 무선인프라 접속 수익 | P129: 无线基础设施使用收入 | Q129: Врчк от предост. доступа к инфрастр-ре буспроводн. сети
C130: 1011101011 | D130: 5 | E130: Satellite Operators | F130: Satellite Operators | G130: This segment includes companies that own and operate satellites. Typically, these satellite operators offer satellite capacity for telecommunication networks or provide geospatial data for their clients. | H130: 衛星運営 | I130: Opérateurs de satellite | J130: Satellitenbetreiber | K130: Operadores de satélite | L130: Operadores de satélite | M130: Operatori satellitari | N130: 衛星電信(除電視) | O130: 위성 운영업체 | P130: 卫星运营商 | Q130: Спутниковые операторы
C131: 1011101012 | D131: 5 | E131: Mobile Comm Device Revenue | F131: Mobile Communications Device Revenue | G131: This segment includes revenue that telecom carriers generate from the sale of mobile handsets and other wireless devices. These devices are frequently sold along with a prepaid or postpaid wireless subscription. | H131: 移動体通信機器売上高 | I131: Revenu d'appareils de communication mobile | J131: Erlös aus mobilen Kommunikationsgeräten | K131: Ingreso de dispositivos móviles de comunicaciones | L131: Receita de aparelhos de comunicações móveis | M131: Ricavi apparati comunicazione mobile | N131: 行動通信裝置收入 | O131: 이동통신기기 매출액 | P131: 移动通信设备收入 | Q131: Выручка от устройств мобильной связи
C132: 10111011 | D132: 4 | E132: Wireline Telecommunications | F132: Wireline Telecommunications Services | G132: This industry subgroup includes companies that operate facilities and infrastructure that supplies voice, data, text, and sound using wired switching and transmission networks. | H132: 有線通信 | I132: Télécommunications filaires | J132: Kabelgebundene Telekommunikation | K132: Telecomunicación de línea fija | L132: Telecomunicações rede fixa | M132: Telecomunicazione linea fissa | N132: 固網電信 | O132: 유선 정보통신 | P132: 有线电信 | Q132: Проводная связь
... C191: 11101110 | D191: 4 | E191: Automobiles | F191: Automobiles Manufacturing | G191: This industry subgroup includes companies that manufacture automobiles (passenger cars), light trucks, motorcycles and sport utility vehicles. Excludes passenger vehicles manufactured for commercial use, medium duty trucks and heavy duty trucks. | H191: 自動車 | I191: Automobiles | J191: Autos | K191: Automóviles | L191: Automóveis | M191: Automobili | N191: 汽車 | O191: 자동차 | P191: 汽车 | Q191: Автомобили
B192: Name Changed | C192: 1110111010 | D192: 5 | E192: Cars | F192: Cars Manufacturing | G192: This segment includes companies that manufacture passenger cars. Such cars include sports cars, sedans, station wagons, hatchbacks, and microcars. | H192: 自動車 | I192: Voitures | J192: Autos | K192: Autos | L192: Carros | M192: Automobili | N192: 車輛 | O192: 자동차 | P192: 汽车 | Q192: Автомобили
B193: New | C193: 111011101010 | D193: 6 | E193: Cars - Electric | F193: Cars Manufacturing - Electric | G193: This segment includes companies that manufacture electric passenger cars. | H193: 自動車-電気 | I193: Voitures - électriques | J193: Autos - Elektrisch | K193: Autos - eléctricos | L193: Carros - elétricos | M193: Automobili - elettriche | N193: 車輛-電力 | O193: 자동차 - 전기 | P193: 汽车-电动 | Q193: Автомобили - электрические
B194: New | C194: 111011101011 | D194: 6 | E194: Cars - Fossil Fuels | F194: Cars Manufacturing - Fossil Fuels | G194: This segment includes companies that manufacture fossil fuel passenger cars. | H194: 自動車-化石燃料 | I194: Voitures - combustibles fossiles | J194: Autos - Fossile Brennstoffe | K194: Autos - combustibles fósiles | L194: Carros - combustíveis fósseis | M194: Automobili - combustibili fossili | N194: 車輛-化石燃料 | O194: 자동차 - 화석연료 | P194: 汽车-化石燃料 | Q194: Автомобили - ископаемое топливо
C195: 1110111011 | D195: 5 | E195: Light Trucks | F195: Light Trucks Manufacturing | G195: This segment includes companies that manufacture light duty trucks and utility vehicles, including light trucks, pickup trucks, cabs, light duty vans, minivans, crossovers, and sport utility vehicles. | H195: ﾗｲﾄﾄﾗｯｸ | I195: Camions légers | J195: Kleinlaster | K195: Camiones ligeros | L195: Caminhões leves | M195: Autocarri leggeri | N195: 輕型卡車 | O195: 소형트럭 | P195: 轻型卡车 | Q195: Грузовики малой грузоподъемн.
B196: New | C196: 111011101110 | D196: 6 | E196: Light Trucks - Electric | F196: Light Trucks - Electric | G196: This segment includes companies that manufacture electric light duty trucks and utility vehicles. | H196: 軽ﾄﾗｯｸ-電気 | I196: Camions légers - électricité | J196: Leichte Lkws - Elektrisch | K196: Camiones ligeros - eléctricos | L196: Caminhões leves - eletricidade | M196: Autocarri leggeri - Elettrici | N196: 輕型卡車-電力 | O196: 경트럭 - 전기 | P196: 轻型卡车-电动 | Q196: Легкие грузовые автомобили - на электричестве
B197: New | C197: 111011101111 | D197: 6 | E197: Light Trucks - Fossil Fuels | F197: Light Trucks - Fossil Fuels | G197: This segment includes companies that manufacture fossil fuel light duty trucks and utility vehicles. | H197: 軽ﾄﾗｯｸ-化石燃料 | I197: Camions légers - combustibles fossiles | J197: Leichte Lkws - Fossile Brennstoffe | K197: Camiones ligeros - combustibles fósiles | L197: Caminhões leves - combustíveis fósseis | M197: Autocarri leggeri - Combustibili fossili | N197: 輕型卡車-化石燃料 | O197: 경트럭 - 화석 연료 | P197: 轻型卡车-化石燃料 | Q197: Легкие грузовые автомобили - ископаемое топливо
C198: 1110111012 | D198: 5 | E198: Motorcycles | F198: Motorcycles Manufacturing | G198: This segment includes companies that manufacture motorcycles and scooters as well as parts specifically designed for motorcycles and scooters. | H198: 自動二輪車 | I198: Motos | J198: Motorräder | K198: Motocicletas | L198: Motocicletas | M198: Motociclette | N198: 摩托車及零件製造 | O198: 모터사이클 | P198: 摩托车 | Q198: Мотоциклы
B199: New | C199: 111011101210 | D199: 6 | E199: Motorcycles - Electric | F199: Motorcycles - Electric | G199: This segment includes companies that manufacture electric motorcycles and scooters as well as parts specifically designed for electric motorcycles and scooters. | H199: 自動二輪車-電気 | I199: Motos - électricité | J199: Motorräder - Elektrisch | K199: Motocicletas - eléctricas | L199: Motocicletas - eletricidade | M199: Motociclette - Elettriche | N199: 機車-電力 | O199: 오토바이 - 전기 | P199: 摩托车-电动 | Q199: Мотоциклы - электрические
B200: New | C200: 111011101211 | D200: 6 | E200: Motorcycles - Fossil Fuels | F200: Motorcycles - Fossil Fuels | G200: This segment includes companies that manufacture fossil fuel motorcycles and scooters as well as parts specifically designed for fossil fuel motorcycles and scooters. | H200: 自動二輪車-化石燃料 | I200: Motos - combustibles fossiles | J200: Motorräder - Fossile Brennstoffe | K200: Motocicletas - combustibles fósiles | L200: Motocicletas - combustíveis fósseis | M200: Motociclette - Combustibili fossili | N200: 機車-化石燃料 | O200: 오토바이 - 화석 연료 | P200: 摩托车-化石燃料 | Q200: Мотоциклы - ископаемое топливо
C201: 11101111 | D201: 4 | E201: Auto Parts | F201: Auto Parts Manufacturing | G201: This industry subgroup includes companies that manufacture various types of automotive parts. Excludes companies that manufacture parts for commercial vehicles (see Commercial Vehicles) and motorcycles (see Motorcycles). | H201: 自動車部品 | I201: Pièces automobiles | J201: Autoteile | K201: Autopartes | L201: Auto-peças | M201: Parti automobilistiche | N201: 汽車零件 | O201: 자동차 부품 | P201: 汽车配件 | Q201: Автозапчасти
C202: 1110111110 | D202: 5 | E202: Alternative Vehicle Parts | F202: Alternative Drivetrain Vehicle Parts Manufacturing | G202: This segment includes companies that manufacture alternative drivetrain and hybrid systems and parts for automobiles. Includes motors and other components specifically for alternative energy systems. | H202: 代替燃料車部品 | I202: Pièces de véhicules alternatifs | J202: Alternative Fahrzeugteile | K202: Partes alternativas de vehículos | L202: Peças para veículos alternativo | M202: Parti veicoli alternativi | N202: 另類車輛零件 | O202: 대체 차량 부품 | P202: 替代汽车零部件 | Q202: Запчасти для пр. альтерн. автомобилей
C203: 1110111111 | D203: 5 | E203: Auto Electrical & Electronics | F203: Auto Electrical & Electronics Manufacturing | G203: This segment includes companies that manufacture onboard electrical and electronic equipment for the automobile industry. | H203: 自動車用電装品･電子製品 | I203: Electrique/électro. automobile | J203: Autoelektrik & -elektronik | K203: Eléctricos y electrónicos de autos | L203: Elétricos e eletrônicos auto | M203: Auto comp elett, elettronici | N203: 汽車電機 | O203: 자동차 전기 & 전자 제품 | P203: 汽车电气电子 | Q203: Электр. для автомобилей
C204: 111011111110 | D204: 6 | E204: Auto Light Equipment | F204: Auto Light Equipment Manufacturing | G204: This segment includes companies that manufacture onboard electrical lighting products. | H204: 自動車用照明 | I204: Equipements d'éclairage automobile | J204: Beleuchtungsvorrichtung für Autos | K204: Equipo ligero de autos | L204: Equipamentos para carros leves | M204: Equip illuminazione auto | N204: 汽車照明設備 | O204: 자동차 경량 장비 | P204: 汽车照明设备 | Q204: Автомоб. свет. оборудование
C205: 111011111111 | D205: 6 | E205: Auto Electronics | F205: Auto Electronics Manufacturing | G205: This segment includes companies that manufacture electrical and electronic equipment. Includes automotive systems, cruise control systems, power window systems, alternators, starters, engine control units, sensors, and wiper systems. Excludes car audio equipment (see Home & Car Audio Equipment). | H205: 自動車用電子製品 | I205: Electronique automobile | J205: Autoelektronik | K205: Dispositivos electrónicos de autos | L205: Eletrônicos auto | M205: Elettronica auto | N205: 其他電機設備製造 | O205: 자동차 전자제품 | P205: 汽车电子 | Q205: Авто-электроника
C206: 1110111112 | D206: 5 | E206: Auto Glass | F206: Auto Glass Manufacturing | G206: This segment includes companies that manufacture automobile glass. Includes tinted and tintless windshields, windows, and sun and moon roofs. | H206: 自動車用ガラス | I206: Verre pour automobiles | J206: Autoglas | K206: Ventanas automotrices | L206: Vidros automotivos | M206: Vetri auto | N206: 汽車玻璃 | O206: 자동차 유리 | P206: 汽车玻璃 | Q206: Автомобильное стекло
C207: 1110111113 | D207: 5 | E207: Auto HVAC Systems | F207: Auto Heating, Ventilation & Air Conditioning (HVAC) Systems Manufacturing | G207: This segment includes companies that manufacture heating, ventilation, and air conditioning (HVAC) systems and their components. | H207: 自動車用冷暖房空調ｼｽﾃﾑ | I207: Systèmes CVCA auto | J207: Auto HVAC-Systeme | K207: Sistemas HVAC de autos | L207: Sistemas HVAC automóveis | M207: Sistemi HVAC auto | N207: 汽車冷暖氣系統 | O207: 자동차 HVAC 시스템 | P207: 汽车暖通空调系统 | Q207: Оборуд. для обогрева и кондиционирования
C208: 1110111114 | D208: 5 | E208: Auto Metal Stamping | F208: Auto Metal Stamping Manufacturing | G208: This segment includes companies that manufacture auto parts primarily produced by the metal stamping fabrication process. Includes body parts, fenders, hubcaps, and tops. | H208: 自動車金属ﾌﾟﾚｽ | I208: Estampage de métal pour automobiles | J208: Autometallstanzen | K208: Estampas de metal de autos | L208: Estampa metal para automóveis | M208: Stampaggio metalli auto | N208: 汽車金屬沖壓 | O208: 자동차 금속 스탬핑 | P208: 汽车金属冲压 | Q208: Металлочеканные автодетали
C209: 1110111115 | D209: 5 | E209: Auto Safety Equipment | F209: Auto Safety Equipment Manufacturing | G209: This segment includes companies that manufacture automotive safety equipment. Includes airbags and seatbelts. | H209: 自動車用安全機器 | I209: Equipements de sécurité pour automobiles | J209: Autosicherheitsgeräte | K209: Equipo de seguridad automotriz | L209: Equipamento de segurança automotiva | M209: Equipagg sicurezza auto | N209: 汽車安全設備 | O209: 자동차 안전 장비 | P209: 汽车安全设备 | Q209: Оборудование автомобильной безопасности
C210: 1110111116 | D210: 5 | E210: Automotive Engineering & Tech | F210: Automotive Engineering & Technology | G210: This segment includes companies that develop, license, or sell technology applied in the automobile industry but are not involved in the manufacturing process. | H210: 自動車ｴﾝｼﾞﾆｱﾘﾝｸﾞ･ﾃｸﾉﾛｼﾞｰ | I210: Tech et ingénierie automobile | J210: Automobiltechnologie | K210: Ingeniería y tec automotriz | L210: Engenharia automotiva e tecn | M210: Ingegneria e tec automobilistica | N210: 汽車工程及技術 | O210: 자동차공학 & 기술 | P210: 汽车工程与技术 | Q210: Автомобильное машиностр. и технологии
C211: 1110111117 | D211: 5 | E211: Body & Chassis | F211: Body & Chassis Manufacturing | G211: This segment includes companies that manufacture body and chassis structures, such as frames, roll cages, and joints. | H211: 車体･ｼｬｰｼ | I211: Carrosseries et châssis | J211: Karosserie & Fahrgestell | K211: Carrocerías | L211: Carroceria e chassi | M211: Telaio e carrozzeria | N211: 車體及底盤 | O211: 본체 & 섀시 | P211: 车身与底盘 | Q211: Шасси и кузова автомобилей
C212: 1110111118 | D212: 5 | E212: Brake Systems | F212: Brake Systems Manufacturing | G212: This segment includes companies that manufacture automobile braking systems and related components. | H212: ﾌﾞﾚｰｷｼｽﾃﾑ | I212: Systèmes de freinage | J212: Bremssysteme | K212: Sistemas de frenos | L212: Sistema de freios | M212: Sistemi frenanti | N212: 煞車系統 | O212: 브레이크 시스템 | P212: 制动系统 | Q212: Тормозные системы
... C221: 1110111125 | D221: 5 | E221: Vehicle Batteries | F221: Vehicle Batteries Manufacturing | G221: This segment includes companies that manufacture batteries for automobiles. | H221: 車両ﾊﾞｯﾃﾘｰ | I221: Batteries de véhicules | J221: Fahrzeugbatterien | K221: Baterías de vehículos | L221: Veículos a bateria | M221: Batterie veicoli | N221: 車用電池 | O221: 자동차 배터리 | P221: 汽车电池 | Q221: Аккумулят. батари д/автомобилей
B222: New | C222: 111011112510 | D222: 6 | E222: Electric Vehicle Batteries | F222: Electric Vehicle Batteries Manufacturing | G222: This segment includes companies that manufacture batteries which power the motors of electric vehicles. Excludes batteries for hybrid electric vehicles (HEV). | H222: 電気自動車用電池 | I222: Batteries pr véhicules électriques | J222: Batterien für Elektrofahrzeuge | K222: Baterías de vehículos eléctricos | L222: Baterias para veículos elétricos | M222: Batterie per veicoli elettrici | N222: 電機車電池 | O222: 전기차 배터리 | P222: 电动汽车电池 | Q222: Аккумуляторные батареи для электромобиля
B223: New | C223: 111011112511 | D223: 6 | E223: Starter Batteries | F223: Starter Batteries Manufacturing | G223: This segment includes companies that manufacture batteries which are used to start the motors of internal combustion engine vehicles (ICEV). | H223: 始動用蓄電池 | I223: Batteries de démarrage | J223: Starterbatterien | K223: Baterías de arranque | L223: Baterias de arranque | M223: Batterie di avviamento | N223: 起動式電池 | O223: 시동용 배터리 | P223: 启动用蓄电池 | Q223: Стартерные аккумуляторные батареи
C224: 1110111126 | D224: 5 | E224: Vehicle Wheels | F224: Vehicle Wheels Manufacturing | G224: This segment includes companies that manufacture automobile wheels and rims. Products include steel, aluminum, and alloy wheels. | H224: 自動車用車輪 | I224: Roues de véhicules | J224: Fahrzeugräder | K224: Ruedas de vehículos | L224: Roda de veículo | M224: Ruote veicoli | N224: 車輪 | O224: 자동차 휠 | P224: 车辆轮圈 | Q224: Колеса автомобиля
C225: 111012 | D225: 3 | E225: Home Construction | F225: Home Construction | G225: This industry includes companies involved in the construction and building of homes. | H225: 住宅建設 | I225: Construction résid | J225: Hausbau | K225: Construcción de viviendas | L225: Construção de casas | M225: Costruzione residenziale | N225: 住宅營建 | O225: 주택건설 | P225: 房屋建设 | Q225: Строительство домов
C226: 11101210 | D226: 4 | E226: Homebuilding | F226: Homebuilding | G226: This industry subgroup includes companies that build and sell single family homes, townhouses, and other similar residential homes. Excludes companies that rent properties. | H226: 戸建住宅建設 | I226: Construction de maisons | J226: Wohnungsbau | K226: Construcción de viviendas | L226: Construção de casa | M226: Edilizia residenziale | N226: 住宅營建 | O226: 주택건설 | P226: 住宅建筑 | Q226: Жилищное строит-во
C227: 1110121010 | D227: 5 | E227: Single Family Homebuilding | F227: Single Family Homebuilding | G227: This segment includes companies that build and sell single family homes. | H227: 一戸建住宅建設 | I227: Construc maisons individuelles | J227: Bau von Einfamilienhäusern | K227: Construcción de viv unifamiliares | L227: Construção de casas unifamiliares | M227: Edilizia case monofamiliari | N227: 單戶住宅建築 | O227: 단일가구 주택건설 | P227: 独栋住宅建造 | Q227: Стр-во жилья на одну семью
C228: 1110121011 | D228: 5 | E228: Multifamily Homebuilding | F228: Multifamily Homebuilding | G228: This segment includes companies that build and sell multifamily homes. Includes townhouses, condominiums, and duplexes. | H228: 多世帯住宅建設 | I228: Construc résid multi-famille | J228: Bau von Mehrfamilienhäusern | K228: Construcción de viv multifamiliares | L228: Construção de casas multifamiliares | M228: Edilizia case multifamiliari | N228: 多戶住宅建築 | O228: 다가구 주택건설 | P228: 多户房屋建筑 | Q228: Многокв. жилищное строит-во
C229: 1110121012 | D229: 5 | E229: Manufactured Home (Mobile) | F229: Manufactured Home (Mobile) | G229: This segment includes companies that build and sell manufactured or mobile homes and other buildings. | H229: 移動住宅(ﾄﾚｰﾗｰ) | I229: Maisons préfab. (mobiles) | J229: Fertighäuser (Mobil) | K229: Viviendas fabricadas (móviles) | L229: Casas fabricadas (móveis) | M229: Case prefabbricate (mobili) | N229: 組合房屋(移動式) | O229: 조립식 주택 (이동식) | P229: 预制房屋(移动) | Q229: Готовые (передвижные) дома
C230: 1110121013 | D230: 5 | E230: Land Sales | F230: Land Sales | G230: This segment includes revenue derived from land sales by homebuilders. | H230: 土地売却 | I230: Ventes de terrains | J230: Grundstücksverkäufe | K230: Ventas de tierra | L230: Vendas de terras | M230: Vendite di terreno | N230: 土地銷售 | O230: 토지 매매 | P230: 土地出售 | Q230: Продажа земли
C231: 11101211 | D231: 4 | E231: Building Products | F231: Building Products Manufacturing | G231: This industry subgroup includes companies that manufacture building products, appliances, tools, and lawn and garden supplies. Excludes all raw materials classified under Materials. | H231: 建築用品 | I231: Produits de construction | J231: Baumaterialien | K231: Productos de construcción | L231: Produtos para construção | M231: Prodotti edili | N231: 居家修繕 | O231: 건축 제품 | P231: 建筑产品 | Q231: Строительные изделия
C232: 1110121110 | D232: 5 | E232: Flooring | F232: Flooring Products Manufacturing | G232: This segment includes companies that manufacture flooring products. Includes carpet, hardwood, tile, vinyl, and laminate flooring. | H232: 床材 | I232: Revêtements | J232: Bodenbeläge | K232: Pisos | L232: Pisos | M232: Pavimentazione | N232: 地板鋪設 | O232: 바닥재 | P232: 地板 | Q232: Настил полов
C233: 111012111010 | D233: 6 | E233: Carpet Flooring | F233: Carpet Flooring Products Manufacturing | G233: This segment includes companies that mill carpets and rugs. | H233: 床用絨毯 | I233: Moquettes | J233: Teppichbodenbelag | K233: Pisos de alfombras | L233: Piso de carpete | M233: Moquette | N233: 地毯及踏墊 | O233: 카펫 바닥재 | P233: 地毯地面材料 | Q233: Ковровое покрытие
C234: 111012111011 | D234: 6 | E234: Tile Flooring | F234: Tile Flooring Products Manufacturing | G234: This segment includes companies that manufacture wall and floor tiles. | H234: 床ﾀｲﾙ | I234: Carrelage | J234: Fliesenbodenbelag | K234: Pisos de baldosa | L234: Piso de azulejo | M234: Piastrelle per pavimenti | N234: 陶瓷牆及地板磁磚 | O234: 타일 바닥재 | P234: 地砖地面材料 | Q234: Плитка для пола
C235: 111012111012 | D235: 6 | E235: Laminate & Wood Flooring | F235: Laminate & Wood Flooring Products Manufacturing | G235: This segment includes companies that plane and finish wood strips for unassembled wood flooring. | H235: ﾗﾐﾈｰﾄﾌﾛｱ･木床 | I235: Parquets et laminés | J235: Laminat & Holzfußboden | K235: Pisos de laminado y madera | L235: Piso de madeira sólida e laminados | M235: Pavimenti in legno e laminato | N235: 層板及木質地板 | O235: 라미네이트 & 원목 바닥재 | P235: 层压板和木地板 | Q235: Ламинат и древесное покр.
... C260: 11101313 | D260: 4 | E260: Office Supplies | F260: Office Supplies Manufacturing | G260: This industry subgroup includes companies that manufacture office supplies such as envelopes, notebooks, writing instruments, folders, and carbon paper. | H260: 事務用品 | I260: Fournitures de bureau | J260: Bürobedarf | K260: Artículos oficina | L260: Mater escritório | M260: Articoli per ufficio | N260: 辦公用品 | O260: 사무용품 | P260: 办公用品 | Q260: Канцтовары
B261: Name Changed | C261: 1110131310 | D261: 5 | E261: Stationery | F261: Stationery Manufacturing | G261: This segment includes companies that manufacture stationery and related office supplies, such as pads and notebooks. | H261: 文具 | I261: Articles de papeterie | J261: Schreibwaren | K261: Artículos de papelería | L261: Papelaria | M261: Cancelleria | N261: 文具 | O261: 사무용품 | P261: 文具 | Q261: Канцелярские товары
C262: 1110131311 | D262: 5 | E262: Writing Instruments | F262: Writing Instruments Manufacturing | G262: This segment includes companies that manufacture writing instruments, such as pens, pencils, markers, chalk, and rubber stamps. | H262: 筆記具 | I262: Articles d'écriture | J262: Schreibgeräte | K262: Instrum de escritura | L262: Instrumentos de escrita | M262: Strumenti scrittura | N262: 書寫工具 | O262: 필기도구 | P262: 书写工具 | Q262: Пишущие инструменты
C263: 111014 | D263: 3 | E263: Leisure Products | F263: Leisure Products Manufacturing | G263: This industry includes companies that manufacture consumer products used for leisure, recreation, or hobbies. | H263: ﾚｼﾞｬｰ用品 | I263: Produits de loisir | J263: Freizeitartikel | K263: Productos de tiempo libre | L263: Produtos de lazer | M263: Articoli tempo libero | N263: 休閒產品 | O263: 레저 상품 | P263: 休闲产品 | Q263: Товары д/отдыха
C264: 11101410 | D264: 4 | E264: Toys & Games | F264: Toys & Games Manufacturing | G264: This industry subgroup includes companies that manufacture physical products used for leisure such as dolls, toys, board games, playing cards, puzzles, hobby items, and crafts. Excludes video game consoles (see Video Game Equipment), and their games (see Video Game Software). | H264: 玩具･ｹﾞｰﾑ | I264: Jeux et jouets | J264: Spielzeug & Spiele | K264: Juguetes y juegos | L264: Brinquedos e jogos | M264: Giochi e giocattoli | N264: 玩具及遊戲 | O264: 완구 및 게임 | P264: 玩具与游戏 | Q264: Игрушки и игры
C265: 11101411 | D265: 4 | E265: Music Instruments | F265: Music Instruments Manufacturing | G265: This industry subgroup includes companies that manufacture stringed, keyboard, woodwind, brass, and percussion instruments used to perform music. | H265: 楽器 | I265: Instruments de musique | J265: Musikinstrumente | K265: Instrumentos musicales | L265: Instrumentos musicais | M265: Strumenti musicali | N265: 樂器 | O265: 악기 | P265: 乐器 | Q265: Музыкальные инструменты
C266: 11101412 | D266: 4 | E266: Recreational Vehicles | F266: Recreational Vehicles Manufacturing | G266: This industry subgroup includes companies that manufacture motor homes, travel trailers, campers, and recreational vehicle equipment. | H266: 娯楽用品 | I266: Véhicules de plaisance | J266: Wohnmobile | K266: Vehículos recreativos | L266: Veículos recreativos | M266: Veicoli ricreativi | N266: 休旅車 | O266: 레크레이션용 자동차 | P266: 休闲车 | Q266: Транспорт для отдыха
C267: 1110141210 | D267: 5 | E267: Leisure Boats & Yachts Building | F267: Leisure Boats & Yachts Building | G267: This segment includes companies that manufacture recreational watercraft, such as yachts, motorboats, sailboats, canoes, kayaks, rowboats, and inflatable rafts. | H267: ﾚｼﾞｬｰ用小型船･ﾖｯﾄ | I267: Construction de bateaux et yachts de plaisance | J267: Bau von Freizeitbooten & Yachten | K267: Construc botes de ocio/yates | L267: Construção de barcos para lazer e iates | M267: Costruzione imbarcazioni da diporto e yacht | N267: 遊船遊艇建造 | O267: 레저 보트 & 요트 건조 | P267: 休闲艇与游艇 | Q267: Лодки/яхты
C268: 1110141211 | D268: 5 | E268: Motorhomes, Trailers & Campers | F268: Motorhomes, Trailers & Campers Manufacturing | G268: This segment includes companies that manufacture motor homes, travel trailers, and campers. | H268: ﾓｰﾀｰﾎｰﾑ･ﾄﾚｰﾗｰ･ｷｬﾝﾋﾟﾝｸﾞｶｰ | I268: Mobile-homes, caravanes et camping cars | J268: Wohnmobile, Anhänger & Campingbusse | K268: Autocaravanas, remolques y campers | L268: Motorhomes, trailers e caravanas | M268: Camper e roulotte | N268: 車屋、露營拖車及露營車 | O268: 이동식 주택, 트레일러 & 캠핑카 | P268: 房车、拖车及露营车 | Q268: Дома на колесах, прицепы и автофургоны
C269: 111014121110 | D269: 6 | E269: Motorhomes | F269: Motorhomes Manufacturing | G269: This segment includes companies that manufacture motorhomes, which are vehicles equipped with living quarters. | H269: ﾓｰﾀｰﾎｰﾑ | I269: Mobile-homes | J269: Wohnmobile | K269: Autocaravanas | L269: Motorhomes | M269: Camper | N269: 車屋 | O269: 이동식 주택 | P269: 房车 | Q269: Дома на колесах
C270: 111014121111 | D270: 6 | E270: Travel Trailers & Campers | F270: Travel Trailers & Campers Manufacturing | G270: This segment includes companies that manufacture travel and camper trailers, which are towed behind a vehicle. | H270: 旅行用ﾄﾚｰﾗｰ･ｷｬﾝﾋﾟﾝｸﾞｶｰ | I270: Caravanes et camping cars | J270: Wohnwagen & Campingbusse | K270: Caravanas de viajes y de campamento | L270: Trailers e caravanas | M270: Roulotte e camper | N270: 旅行車及露營車 | O270: 여행용 트레일러 & 캠핑카 | P270: 旅行拖车及露营车 | Q270: Туристические прицепы и автофургоны
C271: 11101413 | D271: 4 | E271: Sporting Goods | F271: Sporting Goods Manufacturing | G271: This industry subgroup includes companies that manufacture sporting equipment. | H271: ｽﾎﾟｰﾂ用品 | I271: Articles de sport | J271: Sportartikel | K271: Bienes deportivos | L271: Materiais esportivos | M271: Articoli sportivi | N271: 體育用品 | O271: 스포츠 용품 | P271: 体育用品 | Q271: Спортивные товары
C272: 1110141310 | D272: 5 | E272: Bicycles & Parts | F272: Bicycles & Parts Manufacturing | G272: This segment includes companies that manufacture bicycles and bicycle parts. | H272: 自転車･部品 | I272: Bicyclettes et leurs pièces | J272: Fahrräder & Teile | K272: Bicicletas y partes | L272: Bicicleta e peças | M272: Biciclette e parti | N272: 腳踏車及零件 | O272: 자전거 & 부품 | P272: 自行车及零件 | Q272: Велосипеды и з/части
C273: 111014131010 | D273: 6 | E273: Bicycles | F273: Bicycles Manufacturing | G273: This segment includes companies that manufacture bicycles. | H273: 自転車 | I273: Bicyclettes | J273: Fahrräder | K273: Bicicletas | L273: Bicicletas | M273: Biciclette | N273: 腳踏車 | O273: 자전거 | P273: 自行车 | Q273: Велосипеды
... C407: 111211101310 | D407: 6 | E407: Passenger Vehicle Leasing | F407: Passenger Vehicle Leasing | G407: This segment includes companies that lease passenger cars. Excludes companies that provide a driver for the vehicle (see Taxi Services). | H407: 乗用車ﾘｰｽ | I407: Crédit-bail de voitures particulières | J407: Pkw-Leasing | K407: Arrendamiento de carros de pasajero | L407: Arrendamento de veículos de passageiros | M407: Leasing autoveicoli | N407: 客車租賃 | O407: 승용차 리스 | P407: 客运车辆租赁 | Q407: Лизинг легковых автомобилей
B408: New | C408: 11121110131010 | D408: 7 | E408: Passenger Veh Leasing - Electric | F408: Passenger Vehicle Leasing - Electric | G408: This segment includes companies that lease electric passenger vehicles. | H408: 乗用車ﾘｰｽ-電気 | I408: Location à bail de véh de passagers - électricité | J408: Pkw-Leasing - Elektrisch | K408: Arrendamiento veh de pasajeros - eléctricos | L408: Leasing veíc passageiros - eletricidade | M408: Leasing veicoli passeggeri - Elettrici | N408: 客車租賃-電力 | O408: 승용차 리스 - 전기 | P408: 乘用车辆租赁-电动 | Q408: Лизинг легковых автомобилей - на электрич.
B409: New | C409: 11121110131011 | D409: 7 | E409: Passenger Veh Leasing - Fossil Fuels | F409: Passenger Vehicle Leasing - Fossil Fuels | G409: This segment includes companies that lease fossil fuel passenger vehicles. | H409: 乗用車ﾘｰｽ-化石燃料 | I409: Location à bail de véh de passagers - combustibles fossiles | J409: Pkw-Leasing - Fossile Brennstoffe | K409: Arrendamiento veh de pasajero - combustibles fósiles | L409: Leasing veíc passageiros - combustíveis fósseis | M409: Leasing veicoli passeggeri - Combustibili fossili | N409: 客車租賃-化石燃料 | O409: 승용차 리스 - 화석 연료 | P409: 乘用车辆租赁-化石燃料 | Q409: Лизинг легковых автомобилей - ископ. топливо
C410: 111211101311 | D410: 6 | E410: Passenger Vehicle Rental | F410: Passenger Vehicle Rental | G410: This segment includes companies that rent passenger cars. Excludes companies that provide a driver for the vehicle (see Taxi Services). | H410: 乗用車ﾚﾝﾀﾙ | I410: Location de voitures particulières | J410: Pkw-Vermietung | K410: Alquiler de carros de pasajero | L410: Aluguel de veículos de passageiros | M410: Affitto autoveicoli | N410: 客車出租 | O410: 승용차 렌트 | P410: 客运车辆租赁 | Q410: Аренда легковых автомобилей
...

Sheet BICS Fixed Income
H2: =INDEX('How To Download'!$F$70:$F$80,MATCH('BICS Fixed Income'!C4,'How To Download'!$D$70:$D$80,FALSE)) -> 3
C3: LANGUAGE:
C4: English | E4: Back to Table of Contents
B6: No Change To BICS Fixed Income Hierarchy Until Further Notice
B7: ID | C7: Classification Fields
B8: BI011 | C8: BICS_LEVEL_1_SECTOR_CODE
B9: BI012 | C9: BICS_LEVEL_2_INDUSTRY_GROUP_CODE
B10: BI001 | C10: BICS_LEVEL_1_SECTOR_NAME
B11: BI002 | C11: BICS_LEVEL_2_INDUSTRY_GROUP_NAME
B13: LEVEL 1 - SECTOR | D13: LEVEL 2 - INDUSTRY GROUP
B14: 30 | C14: =VLOOKUP(B14,'Current BICS Fixed Income'!$B$5:$P$94,'BICS Fixed Income'!$H$2,FALSE) -> Materials | D14: 3010 | E14: =TRIM(VLOOKUP(D14,'Current BICS Fixed Income'!$B$5:$P$94,'BICS Fixed Income'!$H$2,FALSE)) -> Forest & Paper Products Manufacturing
D15: 3011 | E15: =TRIM(VLOOKUP(D15,'Current BICS Fixed Income'!$B$5:$P$94,'BICS Fixed Income'!$H$2,FALSE)) -> Metals & Mining
D16: 3012 | E16: =TRIM(VLOOKUP(D16,'Current BICS Fixed Income'!$B$5:$P$94,'BICS Fixed Income'!$H$2,FALSE)) -> Construction Materials Manufacturing
D17: 3013 | E17: =TRIM(VLOOKUP(D17,'Current BICS Fixed Income'!$B$5:$P$94,'BICS Fixed Income'!$H$2,FALSE)) -> Chemicals
D18: 3014 | E18: =TRIM(VLOOKUP(D18,'Current BICS Fixed Income'!$B$5:$P$94,'BICS Fixed Income'!$H$2,FALSE)) -> Containers & Packaging
B20: LEVEL 1 - SECTOR | D20: LEVEL 2 - INDUSTRY GROUP
B21: 31 | C21: =TRIM(VLOOKUP(B21,'Current BICS Fixed Income'!$B$5:$P$94,'BICS Fixed Income'!$H$2,FALSE)) -> Communications | D21: 3110 | E21: =TRIM(VLOOKUP(D21,'Current BICS Fixed Income'!$B$5:$P$94,'BICS Fixed Income'!$H$2,FALSE)) -> Cable & Satellite
D22: 3111 | E22: =TRIM(VLOOKUP(D22,'Current BICS Fixed Income'!$B$5:$P$94,'BICS Fixed Income'!$H$2,FALSE)) -> Wireline Telecommunications Services
D23: 3112 | E23: =TRIM(VLOOKUP(D23,'Current BICS Fixed Income'!$B$5:$P$94,'BICS Fixed Income'!$H$2,FALSE)) -> Internet Media
D24: 3113 | E24: =TRIM(VLOOKUP(D24,'Current BICS Fixed Income'!$B$5:$P$94,'BICS Fixed Income'!$H$2,FALSE)) -> Wireless Telecommunications Services
D25: 3114 | E25: =TRIM(VLOOKUP(D25,'Current BICS Fixed Income'!$B$5:$P$94,'BICS Fixed Income'!$H$2,FALSE)) -> Entertainment Content
D26: 3115 | E26: =TRIM(VLOOKUP(D26,'Current BICS Fixed Income'!$B$5:$P$94,'BICS Fixed Income'!$H$2,FALSE)) -> Publishing & Broadcasting
D27: 3116 | E27: =TRIM(VLOOKUP(D27,'Current BICS Fixed Income'!$B$5:$P$94,'BICS Fixed Income'!$H$2,FALSE)) -> Advertising & Marketing
B29: LEVEL 1 - SECTOR | D29: LEVEL 2 - INDUSTRY GROUP
B30: 32 | C30: =TRIM(VLOOKUP(B30,'Current BICS Fixed Income'!$B$5:$P$94,'BICS Fixed Income'!$H$2,FALSE)) -> Consumer Discretionary | D30: 3210 | E30: =TRIM(VLOOKUP(D30,'Current BICS Fixed Income'!$B$5:$P$94,'BICS Fixed Income'!$H$2,FALSE)) -> Leisure Products Manufacturing
D31: 3211 | E31: =TRIM(VLOOKUP(D31,'Current BICS Fixed Income'!$B$5:$P$94,'BICS Fixed Income'!$H$2,FALSE)) -> Automobiles Manufacturing
D32: 3212 | E32: =TRIM(VLOOKUP(D32,'Current BICS Fixed Income'!$B$5:$P$94,'BICS Fixed Income'!$H$2,FALSE)) -> Retail - Consumer Discretionary
D33: 3213 | E33: =TRIM(VLOOKUP(D33,'Current BICS Fixed Income'!$B$5:$P$94,'BICS Fixed Income'!$H$2,FALSE)) -> Airlines
D34: 3214 | E34: =TRIM(VLOOKUP(D34,'Current BICS Fixed Income'!$B$5:$P$94,'BICS Fixed Income'!$H$2,FALSE)) -> Casinos & Gaming
D35: 3215 | E35: =TRIM(VLOOKUP(D35,'Current BICS Fixed Income'!$B$5:$P$94,'BICS Fixed Income'!$H$2,FALSE)) -> Restaurants
D36: 3216 | E36: =TRIM(VLOOKUP(D36,'Current BICS Fixed Income'!$B$5:$P$94,'BICS Fixed Income'!$H$2,FALSE)) -> Travel & Lodging
D37: 3217 | E37: =TRIM(VLOOKUP(D37,'Current BICS Fixed Income'!$B$5:$P$94,'BICS Fixed Income'!$H$2,FALSE)) -> Homebuilders
D38: 3218 | E38: =TRIM(VLOOKUP(D38,'Current BICS Fixed Income'!$B$5:$P$94,'BICS Fixed Income'!$H$2,FALSE)) -> Home Improvement
D39: 3219 | E39: =TRIM(VLOOKUP(D39,'Current BICS Fixed Income'!$B$5:$P$94,'BICS Fixed Income'!$H$2,FALSE)) -> Apparel & Textile Products
D40: 3225 | E40: =TRIM(VLOOKUP(D40,'Current BICS Fixed Income'!$B$5:$P$94,'BICS Fixed Income'!$H$2,FALSE)) -> Home & Office Products Manufacturing
D41: 3226 | E41: =TRIM(VLOOKUP(D41,'Current BICS Fixed Income'!$B$5:$P$94,'BICS Fixed Income'!$H$2,FALSE)) -> Educational Services
D42: 3227 | E42: =TRIM(VLOOKUP(D42,'Current BICS Fixed Income'!$B$5:$P$94,'BICS Fixed Income'!$H$2,FALSE)) -> Entertainment Resources
... D46: 3231 | E46: =TRIM(VLOOKUP(D46,'Current BICS Fixed Income'!$B$5:$P$94,'BICS Fixed Income'!$H$2,FALSE)) -> Department Stores
B48: LEVEL 1 - SECTOR | D48: LEVEL 2 - INDUSTRY GROUP
B49: 33 | C49: =TRIM(VLOOKUP(B49,'Current BICS Fixed Income'!$B$5:$P$94,'BICS Fixed Income'!$H$2,FALSE)) -> Consumer Staples | D49: 3310 | E49: =TRIM(VLOOKUP(D49,'Current BICS Fixed Income'!$B$5:$P$94,'BICS Fixed Income'!$H$2,FALSE)) -> Tobacco
D50: 3311 | E50: =TRIM(VLOOKUP(D50,'Current BICS Fixed Income'!$B$5:$P$94,'BICS Fixed Income'!$H$2,FALSE)) -> Retail - Consumer Staples
D51: 3312 | E51: =TRIM(VLOOKUP(D51,'Current BICS Fixed Income'!$B$5:$P$94,'BICS Fixed Income'!$H$2,FALSE)) -> Supermarkets & Pharmacies
D52: 3313 | E52: =TRIM(VLOOKUP(D52,'Current BICS Fixed Income'!$B$5:$P$94,'BICS Fixed Income'!$H$2,FALSE)) -> Consumer Products
D53: 3314 | E53: =TRIM(VLOOKUP(D53,'Current BICS Fixed Income'!$B$5:$P$94,'BICS Fixed Income'!$H$2,FALSE)) -> Food & Beverage
D54: 3315 | E54: =TRIM(VLOOKUP(D54,'Current BICS Fixed Income'!$B$5:$P$94,'BICS Fixed Income'!$H$2,FALSE)) -> Mass Merchants
B56: LEVEL 1 - SECTOR | D56: LEVEL 2 - INDUSTRY GROUP
B57: 34 | C57: =TRIM(VLOOKUP(B57,'Current BICS Fixed Income'!$B$5:$P$94,'BICS Fixed Income'!$H$2,FALSE)) -> Energy | D57: 3410 | E57: =TRIM(VLOOKUP(D57,'Current BICS Fixed Income'!$B$5:$P$94,'BICS Fixed Income'!$H$2,FALSE)) -> Integrated Oils
D58: 3411 | E58: =TRIM(VLOOKUP(D58,'Current BICS Fixed Income'!$B$5:$P$94,'BICS Fixed Income'!$H$2,FALSE)) -> Renewable Energy
D59: 3412 | E59: =TRIM(VLOOKUP(D59,'Current BICS Fixed Income'!$B$5:$P$94,'BICS Fixed Income'!$H$2,FALSE)) -> Exploration & Production
D60: 3413 | E60: =TRIM(VLOOKUP(D60,'Current BICS Fixed Income'!$B$5:$P$94,'BICS Fixed Income'!$H$2,FALSE)) -> Oil & Gas Services & Equipment
D61: 3414 | E61: =TRIM(VLOOKUP(D61,'Current BICS Fixed Income'!$B$5:$P$94,'BICS Fixed Income'!$H$2,FALSE)) -> Refining & Marketing
D62: 3415 | E62: =TRIM(VLOOKUP(D62,'Current BICS Fixed Income'!$B$5:$P$94,'BICS Fixed Income'!$H$2,FALSE)) -> Pipeline
D63: 3416 | E63: =TRIM(VLOOKUP(D63,'Current BICS Fixed Income'!$B$5:$P$94,'BICS Fixed Income'!$H$2,FALSE)) -> Coal Operations
B65: LEVEL 1 - SECTOR | D65: LEVEL 2 - INDUSTRY GROUP
B66: 35 | C66: =TRIM(VLOOKUP(B66,'Current BICS Fixed Income'!$B$5:$P$94,'BICS Fixed Income'!$H$2,FALSE)) -> Financials | D66: 3510 | E66: =TRIM(VLOOKUP(D66,'Current BICS Fixed Income'!$B$5:$P$94,'BICS Fixed Income'!$H$2,FALSE)) -> Banks
D67: 3511 | E67: =TRIM(VLOOKUP(D67,'Current BICS Fixed Income'!$B$5:$P$94,'BICS Fixed Income'!$H$2,FALSE)) -> Commercial Finance
D68: 3512 | E68: =TRIM(VLOOKUP(D68,'Current BICS Fixed Income'!$B$5:$P$94,'BICS Fixed Income'!$H$2,FALSE)) -> Consumer Finance
D69: 3513 | E69: =TRIM(VLOOKUP(D69,'Current BICS Fixed Income'!$B$5:$P$94,'BICS Fixed Income'!$H$2,FALSE)) -> Life Insurance
D70: 3514 | E70: =TRIM(VLOOKUP(D70,'Current BICS Fixed Income'!$B$5:$P$94,'BICS Fixed Income'!$H$2,FALSE)) -> Property & Casualty Insurance
D71: 3515 | E71: =TRIM(VLOOKUP(D71,'Current BICS Fixed Income'!$B$5:$P$94,'BICS Fixed Income'!$H$2,FALSE)) -> Real Estate
D72: 3516 | E72: =TRIM(VLOOKUP(D72,'Current BICS Fixed Income'!$B$5:$P$94,'BICS Fixed Income'!$H$2,FALSE)) -> Financial Services
D73: 3517 | E73: =TRIM(VLOOKUP(D73,'Current BICS Fixed Income'!$B$5:$P$94,'BICS Fixed Income'!$H$2,FALSE)) -> Funds & Trusts
D74: 3518 | E74: =TRIM(VLOOKUP(D74,'Current BICS Fixed Income'!$B$5:$P$94,'BICS Fixed Income'!$H$2,FALSE)) -> Diversified Banks
B76: LEVEL 1 - SECTOR | D76: LEVEL 2 - INDUSTRY GROUP
B77: 36 | C77: =TRIM(VLOOKUP(B77,'Current BICS Fixed Income'!$B$5:$P$94,'BICS Fixed Income'!$H$2,FALSE)) -> Health Care | D77: 3610 | E77: =TRIM(VLOOKUP(D77,'Current BICS Fixed Income'!$B$5:$P$94,'BICS Fixed Income'!$H$2,FALSE)) -> Biotechnology
D78: 3611 | E78: =TRIM(VLOOKUP(D78,'Current BICS Fixed Income'!$B$5:$P$94,'BICS Fixed Income'!$H$2,FALSE)) -> Medical Equipment & Devices Manufacturing
D79: 3612 | E79: =TRIM(VLOOKUP(D79,'Current BICS Fixed Income'!$B$5:$P$94,'BICS Fixed Income'!$H$2,FALSE)) -> Health Care Facilities & Services
D80: 3613 | E80: =TRIM(VLOOKUP(D80,'Current BICS Fixed Income'!$B$5:$P$94,'BICS Fixed Income'!$H$2,FALSE)) -> Pharmaceuticals
D81: 3615 | E81: =TRIM(VLOOKUP(D81,'Current BICS Fixed Income'!$B$5:$P$94,'BICS Fixed Income'!$H$2,FALSE)) -> Managed Care
B83: LEVEL 1 - SECTOR | D83: LEVEL 2 - INDUSTRY GROUP
B84: 37 | C84: =TRIM(VLOOKUP(B84,'Current BICS Fixed Income'!$B$5:$P$94,'BICS Fixed Income'!$H$2,FALSE)) -> Industrials | D84: 3710 | E84: =TRIM(VLOOKUP(D84,'Current BICS Fixed Income'!$B$5:$P$94,'BICS Fixed Income'!$H$2,FALSE)) -> Manufactured Goods
D85: 3711 | E85: =TRIM(VLOOKUP(D85,'Current BICS Fixed Income'!$B$5:$P$94,'BICS Fixed Income'!$H$2,FALSE)) -> Aerospace & Defense
D86: 3712 | E86: =TRIM(VLOOKUP(D86,'Current BICS Fixed Income'!$B$5:$P$94,'BICS Fixed Income'!$H$2,FALSE)) -> Transportation & Logistics
D87: 3713 | E87: =TRIM(VLOOKUP(D87,'Current BICS Fixed Income'!$B$5:$P$94,'BICS Fixed Income'!$H$2,FALSE)) -> Waste & Environment Services & Equipment
D88: 3714 | E88: =TRIM(VLOOKUP(D88,'Current BICS Fixed Income'!$B$5:$P$94,'BICS Fixed Income'!$H$2,FALSE)) -> Machinery Manufacturing
D89: 3715 | E89: =TRIM(VLOOKUP(D89,'Current BICS Fixed Income'!$B$5:$P$94,'BICS Fixed Income'!$H$2,FALSE)) -> Railroad
D90: 3716 | E90: =TRIM(VLOOKUP(D90,'Current BICS Fixed Income'!$B$5:$P$94,'BICS Fixed Income'!$H$2,FALSE)) -> Industrial Other
D91: 3718 | E91: =TRIM(VLOOKUP(D91,'Current BICS Fixed Income'!$B$5:$P$94,'BICS Fixed Income'!$H$2,FALSE)) -> Electrical Equipment Manufacturing
B93: LEVEL 1 - SECTOR | D93: LEVEL 2 - INDUSTRY GROUP
B94: 38 | C94: =TRIM(VLOOKUP(B94,'Current BICS Fixed Income'!$B$5:$P$94,'BICS Fixed Income'!$H$2,FALSE)) -> Technology | D94: 3810 | E94: =TRIM(VLOOKUP(D94,'Current BICS Fixed Income'!$B$5:$P$94,'BICS Fixed Income'!$H$2,FALSE)) -> Hardware
D95: 3811 | E95: =TRIM(VLOOKUP(D95,'Current BICS Fixed Income'!$B$5:$P$94,'BICS Fixed Income'!$H$2,FALSE)) -> Communications Equipment
D96: 3812 | E96: =TRIM(VLOOKUP(D96,'Current BICS Fixed Income'!$B$5:$P$94,'BICS Fixed Income'!$H$2,FALSE)) -> Software & Services
D97: 3813 | E97: =TRIM(VLOOKUP(D97,'Current BICS Fixed Income'!$B$5:$P$94,'BICS Fixed Income'!$H$2,FALSE)) -> Semiconductors
D98: 3814 | E98: =TRIM(VLOOKUP(D98,'Current BICS Fixed Income'!$B$5:$P$94,'BICS Fixed Income'!$H$2,FALSE)) -> Design, Manufacturing & Distribution
B100: LEVEL 1 - SECTOR | D100: LEVEL 2 - INDUSTRY GROUP
B101: 39 | C101: =TRIM(VLOOKUP(B101,'Current BICS Fixed Income'!$B$5:$P$94,'BICS Fixed Income'!$H$2,FALSE)) -> Utilities | D101: 3910 | E101: =TRIM(VLOOKUP(D101,'Current BICS Fixed Income'!$B$5:$P$94,'BICS Fixed Income'!$H$2,FALSE)) -> Utilities
D102: 3911 | E102: =TRIM(VLOOKUP(D102,'Current BICS Fixed Income'!$B$5:$P$94,'BICS Fixed Income'!$H$2,FALSE)) -> Power Generation
B104: No Change To BICS Government Hierarchy For Fixed Income Securities
B105: LEVEL 1 - SECTOR | D105: LEVEL 2 - INDUSTRY GROUP
B106: 50 | C106: =TRIM(VLOOKUP(B106,'Current BICS Fixed Income'!$B$5:$P$94,'BICS Fixed Income'!$H$2,FALSE)) -> Government | D106: 5010 | E106: =TRIM(VLOOKUP(D106,'Current BICS Fixed Income'!$B$5:$P$94,'BICS Fixed Income'!$H$2,FALSE)) -> Sovereigns
D107: 5011 | E107: =TRIM(VLOOKUP(D107,'Current BICS Fixed Income'!$B$5:$P$94,'BICS Fixed Income'!$H$2,FALSE)) -> Government Agencies
D108: 5012 | E108: =TRIM(VLOOKUP(D108,'Current BICS Fixed Income'!$B$5:$P$94,'BICS Fixed Income'!$H$2,FALSE)) -> Government Regional
D109: 5013 | E109: =TRIM(VLOOKUP(D109,'Current BICS Fixed Income'!$B$5:$P$94,'BICS Fixed Income'!$H$2,FALSE)) -> Supranationals
D110: 5014 | E110: =TRIM(VLOOKUP(D110,'Current BICS Fixed Income'!$B$5:$P$94,'BICS Fixed Income'!$H$2,FALSE)) -> Government Development Banks
D111: 5015 | E111: =TRIM(VLOOKUP(D111,'Current BICS Fixed Income'!$B$5:$P$94,'BICS Fixed Income'!$H$2,FALSE)) -> Winding Up Agencies
D112: 5016 | E112: =TRIM(VLOOKUP(D112,'Current BICS Fixed Income'!$B$5:$P$94,'BICS Fixed Income'!$H$2,FALSE)) -> Central Banks
D113: 5017 | E113: =TRIM(VLOOKUP(D113,'Current BICS Fixed Income'!$B$5:$P$94,'BICS Fixed Income'!$H$2,FALSE)) -> Government Local

Sheet How To Download
B4: Ticker | C4: SECURITY_NAME_LANG | D4: LONG_COMP_NAME
B5: EA US equity | C5: English | D5: {=IF(TICKER="","",_xll.BDP(TICKER,$D$4,LANG,INDEX($E$70:$E$80,MATCH($C$5,$D$70:$D$80,FALSE))))} -> Electronic Arts Inc | H5: Back to Table of Contents
B7: How To view BICS Equity 2024 on Terminal
B9: =HYPERLINK("bbg://screens/ICS BICS","ICS BICS <GO>") -> ICS BICS <GO>
B10: Type ICS BICS<GO> to see revised hierarchy on terminal
B12: =HYPERLINK("bbg://screens/"&TICKER&" CCB BICS",TICKER&" CCB BICS"&"<GO>") -> EA US equity CCB BICS<GO>
B13: Type CCB BICS<GO> to see Company Classification Browser based on BICS hierarchy
B15: How To Download BICS Equity 2024 (Default)
B17: BICS Fields (Returns BICS 2024) | D17: Example: | E17: =BDP(Ticker,"BICS_LEVEL_1_SECTOR_CODE") | I17: *BICS (Level 1~4 with optional level 5~7)
B18: Following classification fields return BICS 2024 codes and names.
B19: ID | C19: Classification Code Field | D19: Level | E19: Classification Code | G19: ID | H19: Classification Name Field | I19: Classification Name
B20: BI011 | C20: BICS_LEVEL_1_SECTOR_CODE | D20: 1 | E20: {=IF(TICKER="","",IF(_xlfn.SINGLE(_xll.BDP(TICKER,C20))="#N/A N/A","",_xll.BDP(TICKER,C20)))} -> 10 | G20: BI001 | H20: BICS_LEVEL_1_SECTOR_NAME | I20: {=IF(TICKER="","",IF(_xlfn.SINGLE(_xll.BDP(TICKER,H20,LANG,INDEX($E$70:$E$80,MATCH($C$5,$D$70:$D$80,FALSE))))="#N/A N/A","",_xll.BDP(TICKER,H20,LANG,INDEX($E$70:$E$80,MATCH($C$5,$D$70:$D$80,FALSE)))))} -> Communications
B21: BI012 | C21: BICS_LEVEL_2_INDUSTRY_GROUP_CODE | D21: 2 | E21: {=IF(TICKER="","",IF(_xlfn.SINGLE(_xll.BDP(TICKER,C21))="#N/A N/A","",_xll.BDP(TICKER,C21)))} -> 1010 | G21: BI002 | H21: BICS_LEVEL_2_INDUSTRY_GROUP_NAME | I21: {=IF(TICKER="","",IF(_xlfn.SINGLE(_xll.BDP(TICKER,H21,LANG,INDEX($E$70:$E$80,MATCH($C$5,$D$70:$D$80,FALSE))))="#N/A N/A","",_xll.BDP(TICKER,H21,LANG,INDEX($E$70:$E$80,MATCH($C$5,$D$70:$D$80,FALSE)))))} -> Media
B22: BI013 | C22: BICS_LEVEL_3_INDUSTRY_CODE | D22: 3 | E22: {=IF(TICKER="","",IF(_xlfn.SINGLE(_xll.BDP(TICKER,C22))="#N/A N/A","",_xll.BDP(TICKER,C22)))} -> 101012 | G22: BI003 | H22: BICS_LEVEL_3_INDUSTRY_NAME | I22: {=IF(TICKER="","",IF(_xlfn.SINGLE(_xll.BDP(TICKER,H22,LANG,INDEX($E$70:$E$80,MATCH($C$5,$D$70:$D$80,FALSE))))="#N/A N/A","",_xll.BDP(TICKER,H22,LANG,INDEX($E$70:$E$80,MATCH($C$5,$D$70:$D$80,FALSE)))))} -> Entertainment Content
B23: BI014 | C23: BICS_LEVEL_4_SUB_INDUSTRY_CODE | D23: 4 | E23: {=IF(TICKER="","",IF(_xlfn.SINGLE(_xll.BDP(TICKER,C23))="#N/A N/A","",_xll.BDP(TICKER,C23)))} -> 10101212 | G23: BI004 | H23: BICS_LEVEL_4_SUB_INDUSTRY_NAME | I23: {=IF(TICKER="","",IF(_xlfn.SINGLE(_xll.BDP(TICKER,H23,LANG,INDEX($E$70:$E$80,MATCH($C$5,$D$70:$D$80,FALSE))))="#N/A N/A","",_xll.BDP(TICKER,H23,LANG,INDEX($E$70:$E$80,MATCH($C$5,$D$70:$D$80,FALSE)))))} -> Video Games
B24: BI015 | C24: BICS_LEVEL_5_SEGMENT_CODE | D24: 5 | E24: {=IF(TICKER="","",IF(_xlfn.SINGLE(_xll.BDP(TICKER,C24))="#N/A N/A","",_xll.BDP(TICKER,C24)))} -> 1010121211 | G24: BI005 | H24: BICS_LEVEL_5_SEGMENT_NAME | I24: {=IF(TICKER="","",IF(_xlfn.SINGLE(_xll.BDP(TICKER,H24,LANG,INDEX($E$70:$E$80,MATCH($C$5,$D$70:$D$80,FALSE))))="#N/A N/A","",_xll.BDP(TICKER,H24,LANG,INDEX($E$70:$E$80,MATCH($C$5,$D$70:$D$80,FALSE)))))} -> Console & PC Games
B25: BI016 | C25: BICS_LEVEL_6_SEGMENT_CODE | D25: 6 | E25: {=IF(TICKER="","",IF(_xlfn.SINGLE(_xll.BDP(TICKER,C25))="#N/A N/A","",_xll.BDP(TICKER,C25)))} | G25: BI006 | H25: BICS_LEVEL_6_SEGMENT_NAME | I25: {=IF(TICKER="","",IF(_xlfn.SINGLE(_xll.BDP(TICKER,H25,LANG,INDEX($E$70:$E$80,MATCH($C$5,$D$70:$D$80,FALSE))))="#N/A N/A","",_xll.BDP(TICKER,H25,LANG,INDEX($E$70:$E$80,MATCH($C$5,$D$70:$D$80,FALSE)))))}
B26: BI017 | C26: BICS_LEVEL_7_SEGMENT_CODE | D26: 7 | E26: {=IF(TICKER="","",IF(_xlfn.SINGLE(_xll.BDP(TICKER,C26))="#N/A N/A","",_xll.BDP(TICKER,C26)))} | G26: BI007 | H26: BICS_LEVEL_7_SEGMENT_NAME | I26: {=IF(TICKER="","",IF(_xlfn.SINGLE(_xll.BDP(TICKER,H26,LANG,INDEX($E$70:$E$80,MATCH($C$5,$D$70:$D$80,FALSE))))="#N/A N/A","",_xll.BDP(TICKER,H26,LANG,INDEX($E$70:$E$80,MATCH($C$5,$D$70:$D$80,FALSE)))))}
B29: How To Download BICS Equity 2024 (Alternative Method 1)
B30: Level Specific Generic Classification Fields
B31: Classification Scheme Override
B32: CLASSIFICATION_SCHEME=BICS | D32: Example: | E32: =BDP(Ticker,"CLASSIFICATION_LEVEL_1_CODE","CLASSIFICATION_SCHEME=BICS")
I33: *BICS (Level 1~4 with optional level 5~7)
B34: Following level specific classification fields can return any available classification codes and names when classification scheme is specified. Use "CLASSIFICATION_SCHEME=BICS" to view BICS 2024 classification
B35: ID | C35: Classification Code Field | D35: Level | E35: Classification Code | G35: ID | H35: Classification Name Field | I35: Classification Name
B36: BI061 | C36: CLASSIFICATION_LEVEL_1_CODE | D36: 1 | E36: =IF(TICKER="","",IF(_xll.BDP(TICKER,C36,"CLASSIFICATION_SCHEME=BICS")="#N/A N/A","",_xll.BDP(TICKER,C36,"CLASSIFICATION_SCHEME=BICS"))) -> 10 | G36: BI071 | H36: CLASSIFICATION_LEVEL_1_NAME | I36: =IF(TICKER="","",IF(_xll.BDP(TICKER,H36,"CLASSIFICATION_SCHEME=BICS",LANG,INDEX($E$70:$E$80,MATCH($C$5,$D$70:$D$80,FALSE)))="#N/A N/A","",_xll.BDP(TICKER,H36,"CLASSIFICATION_SCHEME=BICS",LANG,INDEX($E$70:$E$80,MATCH($C$5,$D$70:$D$80,FALSE))))) -> Communications
B37: BI062 | C37: CLASSIFICATION_LEVEL_2_CODE | D37: 2 | E37: =IF(TICKER="","",IF(_xll.BDP(TICKER,C37,"CLASSIFICATION_SCHEME=BICS")="#N/A N/A","",_xll.BDP(TICKER,C37,"CLASSIFICATION_SCHEME=BICS"))) -> 1010 | G37: BI072 | H37: CLASSIFICATION_LEVEL_2_NAME | I37: =IF(TICKER="","",IF(_xll.BDP(TICKER,H37,"CLASSIFICATION_SCHEME=BICS",LANG,INDEX($E$70:$E$80,MATCH($C$5,$D$70:$D$80,FALSE)))="#N/A N/A","",_xll.BDP(TICKER,H37,"CLASSIFICATION_SCHEME=BICS",LANG,INDEX($E$70:$E$80,MATCH($C$5,$D$70:$D$80,FALSE))))) -> Media
B38: BI063 | C38: CLASSIFICATION_LEVEL_3_CODE | D38: 3 | E38: =IF(TICKER="","",IF(_xll.BDP(TICKER,C38,"CLASSIFICATION_SCHEME=BICS")="#N/A N/A","",_xll.BDP(TICKER,C38,"CLASSIFICATION_SCHEME=BICS"))) -> 101012 | G38: BI073 | H38: CLASSIFICATION_LEVEL_3_NAME | I38: =IF(TICKER="","",IF(_xll.BDP(TICKER,H38,"CLASSIFICATION_SCHEME=BICS",LANG,INDEX($E$70:$E$80,MATCH($C$5,$D$70:$D$80,FALSE)))="#N/A N/A","",_xll.BDP(TICKER,H38,"CLASSIFICATION_SCHEME=BICS",LANG,INDEX($E$70:$E$80,MATCH($C$5,$D$70:$D$80,FALSE))))) -> Entertainment Content
B39: BI064 | C39: CLASSIFICATION_LEVEL_4_CODE | D39: 4 | E39: =IF(TICKER="","",IF(_xll.BDP(TICKER,C39,"CLASSIFICATION_SCHEME=BICS")="#N/A N/A","",_xll.BDP(TICKER,C39,"CLASSIFICATION_SCHEME=BICS"))) -> 10101212 | G39: BI074 | H39: CLASSIFICATION_LEVEL_4_NAME | I39: =IF(TICKER="","",IF(_xll.BDP(TICKER,H39,"CLASSIFICATION_SCHEME=BICS",LANG,INDEX($E$70:$E$80,MATCH($C$5,$D$70:$D$80,FALSE)))="#N/A N/A","",_xll.BDP(TICKER,H39,"CLASSIFICATION_SCHEME=BICS",LANG,INDEX($E$70:$E$80,MATCH($C$5,$D$70:$D$80,FALSE))))) -> Video Games
B40: BI065 | C40: CLASSIFICATION_LEVEL_5_CODE | D40: 5 | E40: =IF(TICKER="","",IF(_xll.BDP(TICKER,C40,"CLASSIFICATION_SCHEME=BICS")="#N/A N/A","",_xll.BDP(TICKER,C40,"CLASSIFICATION_SCHEME=BICS"))) -> 1010121211 | G40: BI075 | H40: CLASSIFICATION_LEVEL_5_NAME | I40: =IF(TICKER="","",IF(_xll.BDP(TICKER,H40,"CLASSIFICATION_SCHEME=BICS",LANG,INDEX($E$70:$E$80,MATCH($C$5,$D$70:$D$80,FALSE)))="#N/A N/A","",_xll.BDP(TICKER,H40,"CLASSIFICATION_SCHEME=BICS",LANG,INDEX($E$70:$E$80,MATCH($C$5,$D$70:$D$80,FALSE))))) -> Console & PC Games
B41: BI066 | C41: CLASSIFICATION_LEVEL_6_CODE | D41: 6 | E41: =IF(TICKER="","",IF(_xll.BDP(TICKER,C41,"CLASSIFICATION_SCHEME=BICS")="#N/A N/A","",_xll.BDP(TICKER,C41,"CLASSIFICATION_SCHEME=BICS"))) | G41: BI076 | H41: CLASSIFICATION_LEVEL_6_NAME | I41: =IF(TICKER="","",IF(_xll.BDP(TICKER,H41,"CLASSIFICATION_SCHEME=BICS",LANG,INDEX($E$70:$E$80,MATCH($C$5,$D$70:$D$80,FALSE)))="#N/A N/A","",_xll.BDP(TICKER,H41,"CLASSIFICATION_SCHEME=BICS",LANG,INDEX($E$70:$E$80,MATCH($C$5,$D$70:$D$80,FALSE)))))
B42: BI067 | C42: CLASSIFICATION_LEVEL_7_CODE | D42: 7 | E42: =IF(TICKER="","",IF(_xll.BDP(TICKER,C42,"CLASSIFICATION_SCHEME=BICS")="#N/A N/A","",_xll.BDP(TICKER,C42,"CLASSIFICATION_SCHEME=BICS"))) | G42: BI077 | H42: CLASSIFICATION_LEVEL_7_NAME | I42: =IF(TICKER="","",IF(_xll.BDP(TICKER,H42,"CLASSIFICATION_SCHEME=BICS",LANG,INDEX($E$70:$E$80,MATCH($C$5,$D$70:$D$80,FALSE)))="#N/A N/A","",_xll.BDP(TICKER,H42,"CLASSIFICATION_SCHEME=BICS",LANG,INDEX($E$70:$E$80,MATCH($C$5,$D$70:$D$80,FALSE)))))
B45: How To Download BICS Equity 2024 (Alternative Method 2)
B46: Generic Classification Fields With Level Override
B47: Classification Scheme and Level Override
B48: CLASSIFICATION_SCHEME=BICS | D48: Example: | E48: =BDP(Ticker,"CLASSIFICATION_CODE","CLASSIFICATION_SCHEME=BICS","CLASSIFICATION_LEVEL=1")
B49: CLASSIFICATION_LEVEL=1
B51: Following classification fields can return any available classification codes and names when classification scheme and classification level are specified. In case of BICS level 4, use "CLASSIFICATION_SCHEME=BICS" and "CLASSIFICATION_LEVEL=4"
B52: ID | C52: Classification Code Field | D52: Level | E52: Classification Code | G52: ID | H52: Classification Name Field | I52: Classification Name
B53: DY843 | C53: CLASSIFICATION_CODE | D53: 1 | E53: =IF(TICKER="","",IF(_xll.BDP(TICKER,"CLASSIFICATION_CODE","CLASSIFICATION_LEVEL",D53,"CLASSIFICATION_SCHEME=BICS")="#N/A N/A","",_xll.BDP(TICKER,"CLASSIFICATION_CODE","CLASSIFICATION_LEVEL",D53,"CLASSIFICATION_SCHEME=BICS"))) -> 10 | G53: DY844 | H53: CLASSIFICATION_DESCRIPTION | I53: =IF(TICKER="","",IF(_xll.BDP(TICKER,"CLASSIFICATION_DESCRIPTION","CLASSIFICATION_LEVEL",D53,"CLASSIFICATION_SCHEME=BICS",LANG,INDEX($E$70:$E$80,MATCH($C$5,$D$70:$D$80,FALSE)))="#N/A N/A","",_xll.BDP(TICKER,"CLASSIFICATION_DESCRIPTION","CLASSIFICATION_LEVEL",D53,"CLASSIFICATION_SCHEME=BICS",LANG,INDEX($E$70:$E$80,MATCH($C$5,$D$70:$D$80,FALSE))))) -> Communications
D54: 2 | E54: =IF(TICKER="","",IF(_xll.BDP(TICKER,"CLASSIFICATION_CODE","CLASSIFICATION_LEVEL",D54,"CLASSIFICATION_SCHEME=BICS")="#N/A N/A","",_xll.BDP(TICKER,"CLASSIFICATION_CODE","CLASSIFICATION_LEVEL",D54,"CLASSIFICATION_SCHEME=BICS"))) -> 1010 | I54: =IF(TICKER="","",IF(_xll.BDP(TICKER,"CLASSIFICATION_DESCRIPTION","CLASSIFICATION_LEVEL",D54,"CLASSIFICATION_SCHEME=BICS",LANG,INDEX($E$70:$E$80,MATCH($C$5,$D$70:$D$80,FALSE)))="#N/A N/A","",_xll.BDP(TICKER,"CLASSIFICATION_DESCRIPTION","CLASSIFICATION_LEVEL",D54,"CLASSIFICATION_SCHEME=BICS",LANG,INDEX($E$70:$E$80,MATCH($C$5,$D$70:$D$80,FALSE))))) -> Media
D55: 3 | E55: =IF(TICKER="","",IF(_xll.BDP(TICKER,"CLASSIFICATION_CODE","CLASSIFICATION_LEVEL",D55,"CLASSIFICATION_SCHEME=BICS")="#N/A N/A","",_xll.BDP(TICKER,"CLASSIFICATION_CODE","CLASSIFICATION_LEVEL",D55,"CLASSIFICATION_SCHEME=BICS"))) -> 101012 | I55: =IF(TICKER="","",IF(_xll.BDP(TICKER,"CLASSIFICATION_DESCRIPTION","CLASSIFICATION_LEVEL",D55,"CLASSIFICATION_SCHEME=BICS",LANG,INDEX($E$70:$E$80,MATCH($C$5,$D$70:$D$80,FALSE)))="#N/A N/A","",_xll.BDP(TICKER,"CLASSIFICATION_DESCRIPTION","CLASSIFICATION_LEVEL",D55,"CLASSIFICATION_SCHEME=BICS",LANG,INDEX($E$70:$E$80,MATCH($C$5,$D$70:$D$80,FALSE))))) -> Entertainment Content
D56: 4 | E56: =IF(TICKER="","",IF(_xll.BDP(TICKER,"CLASSIFICATION_CODE","CLASSIFICATION_LEVEL",D56,"CLASSIFICATION_SCHEME=BICS")="#N/A N/A","",_xll.BDP(TICKER,"CLASSIFICATION_CODE","CLASSIFICATION_LEVEL",D56,"CLASSIFICATION_SCHEME=BICS"))) -> 10101212 | I56: =IF(TICKER="","",IF(_xll.BDP(TICKER,"CLASSIFICATION_DESCRIPTION","CLASSIFICATION_LEVEL",D56,"CLASSIFICATION_SCHEME=BICS",LANG,INDEX($E$70:$E$80,MATCH($C$5,$D$70:$D$80,FALSE)))="#N/A N/A","",_xll.BDP(TICKER,"CLASSIFICATION_DESCRIPTION","CLASSIFICATION_LEVEL",D56,"CLASSIFICATION_SCHEME=BICS",LANG,INDEX($E$70:$E$80,MATCH($C$5,$D$70:$D$80,FALSE))))) -> Video Games
D57: 5 | E57: =IF(TICKER="","",IF(_xll.BDP(TICKER,"CLASSIFICATION_CODE","CLASSIFICATION_LEVEL",D57,"CLASSIFICATION_SCHEME=BICS")="#N/A N/A","",_xll.BDP(TICKER,"CLASSIFICATION_CODE","CLASSIFICATION_LEVEL",D57,"CLASSIFICATION_SCHEME=BICS"))) -> 1010121211 | I57: =IF(TICKER="","",IF(_xll.BDP(TICKER,"CLASSIFICATION_DESCRIPTION","CLASSIFICATION_LEVEL",D57,"CLASSIFICATION_SCHEME=BICS",LANG,INDEX($E$70:$E$80,MATCH($C$5,$D$70:$D$80,FALSE)))="#N/A N/A","",_xll.BDP(TICKER,"CLASSIFICATION_DESCRIPTION","CLASSIFICATION_LEVEL",D57,"CLASSIFICATION_SCHEME=BICS",LANG,INDEX($E$70:$E$80,MATCH($C$5,$D$70:$D$80,FALSE))))) -> Console & PC Games
D58: 6 | E58: =IF(TICKER="","",IF(_xll.BDP(TICKER,"CLASSIFICATION_CODE","CLASSIFICATION_LEVEL",D58,"CLASSIFICATION_SCHEME=BICS")="#N/A N/A","",_xll.BDP(TICKER,"CLASSIFICATION_CODE","CLASSIFICATION_LEVEL",D58,"CLASSIFICATION_SCHEME=BICS"))) | I58: =IF(TICKER="","",IF(_xll.BDP(TICKER,"CLASSIFICATION_DESCRIPTION","CLASSIFICATION_LEVEL",D58,"CLASSIFICATION_SCHEME=BICS",LANG,INDEX($E$70:$E$80,MATCH($C$5,$D$70:$D$80,FALSE)))="#N/A N/A","",_xll.BDP(TICKER,"CLASSIFICATION_DESCRIPTION","CLASSIFICATION_LEVEL",D58,"CLASSIFICATION_SCHEME=BICS",LANG,INDEX($E$70:$E$80,MATCH($C$5,$D$70:$D$80,FALSE)))))
D59: 7 | E59: =IF(TICKER="","",IF(_xll.BDP(TICKER,"CLASSIFICATION_CODE","CLASSIFICATION_LEVEL",D59,"CLASSIFICATION_SCHEME=BICS")="#N/A N/A","",_xll.BDP(TICKER,"CLASSIFICATION_CODE","CLASSIFICATION_LEVEL",D59,"CLASSIFICATION_SCHEME=BICS"))) | I59: =IF(TICKER="","",IF(_xll.BDP(TICKER,"CLASSIFICATION_DESCRIPTION","CLASSIFICATION_LEVEL",D59,"CLASSIFICATION_SCHEME=BICS",LANG,INDEX($E$70:$E$80,MATCH($C$5,$D$70:$D$80,FALSE)))="#N/A N/A","",_xll.BDP(TICKER,"CLASSIFICATION_DESCRIPTION","CLASSIFICATION_LEVEL",D59,"CLASSIFICATION_SCHEME=BICS",LANG,INDEX($E$70:$E$80,MATCH($C$5,$D$70:$D$80,FALSE)))))
B62: Override Fields
B63: Use following override field to specify classification system and level
B64: ID | C64: Override Fields | D64: Classification Scheme | E64: Instruction
B65: DY841 | C65: CLASSIFICATION_SCHEME | D65: BICS | E65: Specify classification system "BICS" with "CLASSIFICATION_SCHEME"
B66: DY842 | C66: CLASSIFICATION_LEVEL | D66: 1, 2, 3, 4 | E66: Specify classification level with "CLASSIFICATION_LEVEL". In order to download level 4 data, use "CLASSIFICATION_LEVEL=4". This field is applicable for DY843 CLASSIFICATION_CODE and DY844 CLASSIFICATION_DESCRIPTION
B68: (Optional Override) Language can be specified with "SECURITY_NAME_LANG". ("SECURITY_NAME_LANG=2" for Japanese)
B69: ID | C69: Language Override Field | D69: Language Description | E69: Language Override Code | F69: Vlookup#
B70: DX616 | C70: SECURITY_NAME_LANG | D70: English | E70: 1 | F70: 3
D71: Japanese | E71: 2 | F71: 6
D72: Français | E72: 3 | F72: 7
D73: Deutsch | E73: 4 | F73: 8
D74: Español | E74: 5 | F74: 9
D75: Português | E75: 6 | F75: 10
D76: Italiano | E76: 7 | F76: 11
D77: Traditional Chinese | E77: 8 | F77: 12
D78: Korean | E78: 9 | F78: 13
D79: Simplified Chinese | E79: 10 | F79: 14
D80: Russian | E80: 16 | F80: 15

Sheet Mapping for Equity
B1: LANGUAGE: | K1: =INDEX('How To Download'!F70:F80,MATCH(LANG4MAP,'How To Download'!$D$70:$D$80,FALSE)) -> 3
B2: English | J2: Back to Table of Contents
B3: BICS Equity Hierarchy 2020 | H3: Equivalent BICS Equity 2024 Classification
B4: BICS Code | C4: Level | D4: BICS Name | F4: Changes | H4: BICS Code | I4: BICS Name | J4: BICS Code | K4: BICS Name | L4: BICS Code | M4: BICS Name | N4: BICS Code | O4: BICS Name
B5: 10 | C5: 1 | D5: =VLOOKUP(B5,'Current BICS'!$B$4:$P$1837,'Mapping for Equity'!$K$1,FALSE) -> Communications | E5: ⇒ | G5: ⇒ | H5: 10 | I5: =VLOOKUP(H5,'BICS Equity Hierarchy 2024'!$C$5:$Q$1846,'Mapping for Equity'!$K$1,FALSE) -> Communications | K5: =IF(J5="","",VLOOKUP(J5,'BICS Equity Hierarchy 2024'!$C$5:$Q$1783,'Mapping for Equity'!$K$1))
B6: 1010 | C6: 2 | D6: =VLOOKUP(B6,'Current BICS'!$B$4:$P$1837,'Mapping for Equity'!$K$1,FALSE) -> Media | E6: ⇒ | G6: ⇒ | H6: 1010 | I6: =VLOOKUP(H6,'BICS Equity Hierarchy 2024'!$C$5:$Q$1846,'Mapping for Equity'!$K$1,FALSE) -> Media | K6: =IF(J6="","",VLOOKUP(J6,'BICS Equity Hierarchy 2024'!$C$5:$Q$1783,'Mapping for Equity'!$K$1))
B7: 101010 | C7: 3 | D7: =VLOOKUP(B7,'Current BICS'!$B$4:$P$1837,'Mapping for Equity'!$K$1,FALSE) -> Advertising & Marketing | E7: ⇒ | G7: ⇒ | H7: 101010 | I7: =VLOOKUP(H7,'BICS Equity Hierarchy 2024'!$C$5:$Q$1846,'Mapping for Equity'!$K$1,FALSE) -> Advertising & Marketing | K7: =IF(J7="","",VLOOKUP(J7,'BICS Equity Hierarchy 2024'!$C$5:$Q$1783,'Mapping for Equity'!$K$1))
B8: 10101010 | C8: 4 | D8: =VLOOKUP(B8,'Current BICS'!$B$4:$P$1837,'Mapping for Equity'!$K$1,FALSE) -> Advertising & Marketing | E8: ⇒ | G8: ⇒ | H8: 10101010 | I8: =VLOOKUP(H8,'BICS Equity Hierarchy 2024'!$C$5:$Q$1846,'Mapping for Equity'!$K$1,FALSE) -> Advertising & Marketing | K8: =IF(J8="","",VLOOKUP(J8,'BICS Equity Hierarchy 2024'!$C$5:$Q$1783,'Mapping for Equity'!$K$1))
B9: 1010101010 | C9: 5 | D9: =VLOOKUP(B9,'Current BICS'!$B$4:$P$1837,'Mapping for Equity'!$K$1,FALSE) -> Advertising Agencies & Svcs | E9: ⇒ | G9: ⇒ | H9: 1010101010 | I9: =VLOOKUP(H9,'BICS Equity Hierarchy 2024'!$C$5:$Q$1846,'Mapping for Equity'!$K$1,FALSE) -> Advertising Agencies & Svcs | K9: =IF(J9="","",VLOOKUP(J9,'BICS Equity Hierarchy 2024'!$C$5:$Q$1783,'Mapping for Equity'!$K$1))
B10: 101010101010 | C10: 6 | D10: =VLOOKUP(B10,'Current BICS'!$B$4:$P$1837,'Mapping for Equity'!$K$1,FALSE) -> Advertising Agencies | E10: ⇒ | G10: ⇒ | H10: 101010101010 | I10: =VLOOKUP(H10,'BICS Equity Hierarchy 2024'!$C$5:$Q$1846,'Mapping for Equity'!$K$1,FALSE) -> Advertising Agencies | K10: =IF(J10="","",VLOOKUP(J10,'BICS Equity Hierarchy 2024'!$C$5:$Q$1783,'Mapping for Equity'!$K$1))
B11: 101010101011 | C11: 6 | D11: =VLOOKUP(B11,'Current BICS'!$B$4:$P$1837,'Mapping for Equity'!$K$1,FALSE) -> E-Marketing | E11: ⇒ | G11: ⇒ | H11: 101010101011 | I11: =VLOOKUP(H11,'BICS Equity Hierarchy 2024'!$C$5:$Q$1846,'Mapping for Equity'!$K$1,FALSE) -> E-Marketing | K11: =IF(J11="","",VLOOKUP(J11,'BICS Equity Hierarchy 2024'!$C$5:$Q$1783,'Mapping for Equity'!$K$1))
B12: 101010101012 | C12: 6 | D12: =VLOOKUP(B12,'Current BICS'!$B$4:$P$1837,'Mapping for Equity'!$K$1,FALSE) -> Market Research & Consulting | E12: ⇒ | G12: ⇒ | H12: 101010101012 | I12: =VLOOKUP(H12,'BICS Equity Hierarchy 2024'!$C$5:$Q$1846,'Mapping for Equity'!$K$1,FALSE) -> Market Research & Consulting | K12: =IF(J12="","",VLOOKUP(J12,'BICS Equity Hierarchy 2024'!$C$5:$Q$1783,'Mapping for Equity'!$K$1))
B13: 10101010101210 | C13: 7 | D13: =VLOOKUP(B13,'Current BICS'!$B$4:$P$1837,'Mapping for Equity'!$K$1,FALSE) -> Marketing Consulting Services | E13: ⇒ | G13: ⇒ | H13: 10101010101210 | I13: =VLOOKUP(H13,'BICS Equity Hierarchy 2024'!$C$5:$Q$1846,'Mapping for Equity'!$K$1,FALSE) -> Marketing Consulting Services | K13: =IF(J13="","",VLOOKUP(J13,'BICS Equity Hierarchy 2024'!$C$5:$Q$1783,'Mapping for Equity'!$K$1))
B14: 10101010101211 | C14: 7 | D14: =VLOOKUP(B14,'Current BICS'!$B$4:$P$1837,'Mapping for Equity'!$K$1,FALSE) -> Market Research | E14: ⇒ | G14: ⇒ | H14: 10101010101211 | I14: =VLOOKUP(H14,'BICS Equity Hierarchy 2024'!$C$5:$Q$1846,'Mapping for Equity'!$K$1,FALSE) -> Market Research | K14: =IF(J14="","",VLOOKUP(J14,'BICS Equity Hierarchy 2024'!$C$5:$Q$1783,'Mapping for Equity'!$K$1))
B15: 101010101013 | C15: 6 | D15: =VLOOKUP(B15,'Current BICS'!$B$4:$P$1837,'Mapping for Equity'!$K$1,FALSE) -> Media Representatives | E15: ⇒ | G15: ⇒ | H15: 101010101013 | I15: =VLOOKUP(H15,'BICS Equity Hierarchy 2024'!$C$5:$Q$1846,'Mapping for Equity'!$K$1,FALSE) -> Media Representatives | K15: =IF(J15="","",VLOOKUP(J15,'BICS Equity Hierarchy 2024'!$C$5:$Q$1783,'Mapping for Equity'!$K$1))
B16: 101010101014 | C16: 6 | D16: =VLOOKUP(B16,'Current BICS'!$B$4:$P$1837,'Mapping for Equity'!$K$1,FALSE) -> Public Relations Agencies | E16: ⇒ | G16: ⇒ | H16: 101010101014 | I16: =VLOOKUP(H16,'BICS Equity Hierarchy 2024'!$C$5:$Q$1846,'Mapping for Equity'!$K$1,FALSE) -> Public Relations Agencies | K16: =IF(J16="","",VLOOKUP(J16,'BICS Equity Hierarchy 2024'!$C$5:$Q$1783,'Mapping for Equity'!$K$1))
... B187: 11101110 | C187: 4 | D187: =VLOOKUP(B187,'Current BICS'!$B$4:$P$1837,'Mapping for Equity'!$K$1,FALSE) -> Automobiles | E187: ⇒ | G187: ⇒ | H187: 11101110 | I187: =VLOOKUP(H187,'BICS Equity Hierarchy 2024'!$C$5:$Q$1846,'Mapping for Equity'!$K$1,FALSE) -> Automobiles | K187: =IF(J187="","",VLOOKUP(J187,'BICS Equity Hierarchy 2024'!$C$5:$Q$1783,'Mapping for Equity'!$K$1))
B188: 1110111010 | C188: 5 | D188: =VLOOKUP(B188,'Current BICS'!$B$4:$P$1837,'Mapping for Equity'!$K$1,FALSE) -> Passenger Vehicles | E188: ⇒ | F188: Name Changed | G188: ⇒ | H188: 1110111010 | I188: =VLOOKUP(H188,'BICS Equity Hierarchy 2024'!$C$5:$Q$1846,'Mapping for Equity'!$K$1,FALSE) -> Cars | K188: =IF(J188="","",VLOOKUP(J188,'BICS Equity Hierarchy 2024'!$C$5:$Q$1783,'Mapping for Equity'!$K$1))
B189: 111011101010 | C189: 6 | D189: =VLOOKUP(B189,'Current BICS'!$B$4:$P$1837,'Mapping for Equity'!$K$1,FALSE) -> Passenger Vehicles - Electric | E189: ⇒ | F189: Name Changed | G189: ⇒ | H189: 111011101010 | I189: =VLOOKUP(H189,'BICS Equity Hierarchy 2024'!$C$5:$Q$1846,'Mapping for Equity'!$K$1,FALSE) -> Cars - Electric | K189: =IF(J189="","",VLOOKUP(J189,'BICS Equity Hierarchy 2024'!$C$5:$Q$1783,'Mapping for Equity'!$K$1))
B190: 111011101011 | C190: 6 | D190: =VLOOKUP(B190,'Current BICS'!$B$4:$P$1837,'Mapping for Equity'!$K$1,FALSE) -> Passenger Vehicles - Fossil Fuels | E190: ⇒ | F190: Name Changed | G190: ⇒ | H190: 111011101011 | I190: =VLOOKUP(H190,'BICS Equity Hierarchy 2024'!$C$5:$Q$1846,'Mapping for Equity'!$K$1,FALSE) -> Cars - Fossil Fuels | K190: =IF(J190="","",VLOOKUP(J190,'BICS Equity Hierarchy 2024'!$C$5:$Q$1783,'Mapping for Equity'!$K$1))
B191: 1110111011 | C191: 5 | D191: =VLOOKUP(B191,'Current BICS'!$B$4:$P$1837,'Mapping for Equity'!$K$1,FALSE) -> Light Trucks | E191: ⇒ | G191: ⇒ | H191: 1110111011 | I191: =VLOOKUP(H191,'BICS Equity Hierarchy 2024'!$C$5:$Q$1846,'Mapping for Equity'!$K$1,FALSE) -> Light Trucks | K191: =IF(J191="","",VLOOKUP(J191,'BICS Equity Hierarchy 2024'!$C$5:$Q$1783,'Mapping for Equity'!$K$1))
B192: 111011101110 | C192: 6 | D192: =VLOOKUP(B192,'Current BICS'!$B$4:$P$1837,'Mapping for Equity'!$K$1,FALSE) -> Light Trucks - Electric | E192: ⇒ | G192: ⇒ | H192: 111011101110 | I192: =VLOOKUP(H192,'BICS Equity Hierarchy 2024'!$C$5:$Q$1846,'Mapping for Equity'!$K$1,FALSE) -> Light Trucks - Electric | K192: =IF(J192="","",VLOOKUP(J192,'BICS Equity Hierarchy 2024'!$C$5:$Q$1783,'Mapping for Equity'!$K$1))
B193: 111011101111 | C193: 6 | D193: =VLOOKUP(B193,'Current BICS'!$B$4:$P$1837,'Mapping for Equity'!$K$1,FALSE) -> Light Trucks - Fossil Fuels | E193: ⇒ | G193: ⇒ | H193: 111011101111 | I193: =VLOOKUP(H193,'BICS Equity Hierarchy 2024'!$C$5:$Q$1846,'Mapping for Equity'!$K$1,FALSE) -> Light Trucks - Fossil Fuels | K193: =IF(J193="","",VLOOKUP(J193,'BICS Equity Hierarchy 2024'!$C$5:$Q$1783,'Mapping for Equity'!$K$1))
B194: 1110111012 | C194: 5 | D194: =VLOOKUP(B194,'Current BICS'!$B$4:$P$1837,'Mapping for Equity'!$K$1,FALSE) -> Motorcycles | E194: ⇒ | G194: ⇒ | H194: 1110111012 | I194: =VLOOKUP(H194,'BICS Equity Hierarchy 2024'!$C$5:$Q$1846,'Mapping for Equity'!$K$1,FALSE) -> Motorcycles | K194: =IF(J194="","",VLOOKUP(J194,'BICS Equity Hierarchy 2024'!$C$5:$Q$1783,'Mapping for Equity'!$K$1))
B195: 111011101210 | C195: 6 | D195: =VLOOKUP(B195,'Current BICS'!$B$4:$P$1837,'Mapping for Equity'!$K$1,FALSE) -> Motorcycles - Electric | E195: ⇒ | G195: ⇒ | H195: 111011101210 | I195: =VLOOKUP(H195,'BICS Equity Hierarchy 2024'!$C$5:$Q$1846,'Mapping for Equity'!$K$1,FALSE) -> Motorcycles - Electric | K195: =IF(J195="","",VLOOKUP(J195,'BICS Equity Hierarchy 2024'!$C$5:$Q$1783,'Mapping for Equity'!$K$1))
B196: 111011101211 | C196: 6 | D196: =VLOOKUP(B196,'Current BICS'!$B$4:$P$1837,'Mapping for Equity'!$K$1,FALSE) -> Motorcycles - Fossil Fuels | E196: ⇒ | G196: ⇒ | H196: 111011101211 | I196: =VLOOKUP(H196,'BICS Equity Hierarchy 2024'!$C$5:$Q$1846,'Mapping for Equity'!$K$1,FALSE) -> Motorcycles - Fossil Fuels | K196: =IF(J196="","",VLOOKUP(J196,'BICS Equity Hierarchy 2024'!$C$5:$Q$1783,'Mapping for Equity'!$K$1))
B197: 11101111 | C197: 4 | D197: =VLOOKUP(B197,'Current BICS'!$B$4:$P$1837,'Mapping for Equity'!$K$1,FALSE) -> Auto Parts | E197: ⇒ | G197: ⇒ | H197: 11101111 | I197: =VLOOKUP(H197,'BICS Equity Hierarchy 2024'!$C$5:$Q$1846,'Mapping for Equity'!$K$1,FALSE) -> Auto Parts | K197: =IF(J197="","",VLOOKUP(J197,'BICS Equity Hierarchy 2024'!$C$5:$Q$1783,'Mapping for Equity'!$K$1))
B198: 1110111110 | C198: 5 | D198: =VLOOKUP(B198,'Current BICS'!$B$4:$P$1837,'Mapping for Equity'!$K$1,FALSE) -> Alternative Vehicle Parts | E198: ⇒ | G198: ⇒ | H198: 1110111110 | I198: =VLOOKUP(H198,'BICS Equity Hierarchy 2024'!$C$5:$Q$1846,'Mapping for Equity'!$K$1,FALSE) -> Alternative Vehicle Parts | K198: =IF(J198="","",VLOOKUP(J198,'BICS Equity Hierarchy 2024'!$C$5:$Q$1783,'Mapping for Equity'!$K$1))
B199: 1110111111 | C199: 5 | D199: =VLOOKUP(B199,'Current BICS'!$B$4:$P$1837,'Mapping for Equity'!$K$1,FALSE) -> Auto Electrical & Electronics | E199: ⇒ | G199: ⇒ | H199: 1110111111 | I199: =VLOOKUP(H199,'BICS Equity Hierarchy 2024'!$C$5:$Q$1846,'Mapping for Equity'!$K$1,FALSE) -> Auto Electrical & Electronics | K199: =IF(J199="","",VLOOKUP(J199,'BICS Equity Hierarchy 2024'!$C$5:$Q$1783,'Mapping for Equity'!$K$1))
B200: 111011111110 | C200: 6 | D200: =VLOOKUP(B200,'Current BICS'!$B$4:$P$1837,'Mapping for Equity'!$K$1,FALSE) -> Auto Light Equipment | E200: ⇒ | G200: ⇒ | H200: 111011111110 | I200: =VLOOKUP(H200,'BICS Equity Hierarchy 2024'!$C$5:$Q$1846,'Mapping for Equity'!$K$1,FALSE) -> Auto Light Equipment | K200: =IF(J200="","",VLOOKUP(J200,'BICS Equity Hierarchy 2024'!$C$5:$Q$1783,'Mapping for Equity'!$K$1))
B201: 111011111111 | C201: 6 | D201: =VLOOKUP(B201,'Current BICS'!$B$4:$P$1837,'Mapping for Equity'!$K$1,FALSE) -> Auto Electronics | E201: ⇒ | G201: ⇒ | H201: 111011111111 | I201: =VLOOKUP(H201,'BICS Equity Hierarchy 2024'!$C$5:$Q$1846,'Mapping for Equity'!$K$1,FALSE) -> Auto Electronics | K201: =IF(J201="","",VLOOKUP(J201,'BICS Equity Hierarchy 2024'!$C$5:$Q$1783,'Mapping for Equity'!$K$1))
B202: 1110111112 | C202: 5 | D202: =VLOOKUP(B202,'Current BICS'!$B$4:$P$1837,'Mapping for Equity'!$K$1,FALSE) -> Auto Glass | E202: ⇒ | G202: ⇒ | H202: 1110111112 | I202: =VLOOKUP(H202,'BICS Equity Hierarchy 2024'!$C$5:$Q$1846,'Mapping for Equity'!$K$1,FALSE) -> Auto Glass | K202: =IF(J202="","",VLOOKUP(J202,'BICS Equity Hierarchy 2024'!$C$5:$Q$1783,'Mapping for Equity'!$K$1))
... B254: 11101313 | C254: 4 | D254: =VLOOKUP(B254,'Current BICS'!$B$4:$P$1837,'Mapping for Equity'!$K$1,FALSE) -> Office Supplies | E254: ⇒ | G254: ⇒ | H254: 11101313 | I254: =VLOOKUP(H254,'BICS Equity Hierarchy 2024'!$C$5:$Q$1846,'Mapping for Equity'!$K$1,FALSE) -> Office Supplies | K254: =IF(J254="","",VLOOKUP(J254,'BICS Equity Hierarchy 2024'!$C$5:$Q$1783,'Mapping for Equity'!$K$1))
B255: 1110131310 | C255: 5 | D255: =VLOOKUP(B255,'Current BICS'!$B$4:$P$1837,'Mapping for Equity'!$K$1,FALSE) -> Stationary | E255: ⇒ | F255: Name Changed | G255: ⇒ | H255: 1110131310 | I255: =VLOOKUP(H255,'BICS Equity Hierarchy 2024'!$C$5:$Q$1846,'Mapping for Equity'!$K$1,FALSE) -> Stationery | K255: =IF(J255="","",VLOOKUP(J255,'BICS Equity Hierarchy 2024'!$C$5:$Q$1783,'Mapping for Equity'!$K$1))
B256: 1110131311 | C256: 5 | D256: =VLOOKUP(B256,'Current BICS'!$B$4:$P$1837,'Mapping for Equity'!$K$1,FALSE) -> Writing Instruments | E256: ⇒ | G256: ⇒ | H256: 1110131311 | I256: =VLOOKUP(H256,'BICS Equity Hierarchy 2024'!$C$5:$Q$1846,'Mapping for Equity'!$K$1,FALSE) -> Writing Instruments | K256: =IF(J256="","",VLOOKUP(J256,'BICS Equity Hierarchy 2024'!$C$5:$Q$1783,'Mapping for Equity'!$K$1))
B257: 111014 | C257: 3 | D257: =VLOOKUP(B257,'Current BICS'!$B$4:$P$1837,'Mapping for Equity'!$K$1,FALSE) -> Leisure Products | E257: ⇒ | G257: ⇒ | H257: 111014 | I257: =VLOOKUP(H257,'BICS Equity Hierarchy 2024'!$C$5:$Q$1846,'Mapping for Equity'!$K$1,FALSE) -> Leisure Products | K257: =IF(J257="","",VLOOKUP(J257,'BICS Equity Hierarchy 2024'!$C$5:$Q$1783,'Mapping for Equity'!$K$1))
B258: 11101410 | C258: 4 | D258: =VLOOKUP(B258,'Current BICS'!$B$4:$P$1837,'Mapping for Equity'!$K$1,FALSE) -> Toys & Games | E258: ⇒ | G258: ⇒ | H258: 11101410 | I258: =VLOOKUP(H258,'BICS Equity Hierarchy 2024'!$C$5:$Q$1846,'Mapping for Equity'!$K$1,FALSE) -> Toys & Games | K258: =IF(J258="","",VLOOKUP(J258,'BICS Equity Hierarchy 2024'!$C$5:$Q$1783,'Mapping for Equity'!$K$1))
B259: 11101411 | C259: 4 | D259: =VLOOKUP(B259,'Current BICS'!$B$4:$P$1837,'Mapping for Equity'!$K$1,FALSE) -> Music Instruments | E259: ⇒ | G259: ⇒ | H259: 11101411 | I259: =VLOOKUP(H259,'BICS Equity Hierarchy 2024'!$C$5:$Q$1846,'Mapping for Equity'!$K$1,FALSE) -> Music Instruments | K259: =IF(J259="","",VLOOKUP(J259,'BICS Equity Hierarchy 2024'!$C$5:$Q$1783,'Mapping for Equity'!$K$1))
B260: 11101412 | C260: 4 | D260: =VLOOKUP(B260,'Current BICS'!$B$4:$P$1837,'Mapping for Equity'!$K$1,FALSE) -> Recreational Vehicles | E260: ⇒ | G260: ⇒ | H260: 11101412 | I260: =VLOOKUP(H260,'BICS Equity Hierarchy 2024'!$C$5:$Q$1846,'Mapping for Equity'!$K$1,FALSE) -> Recreational Vehicles | K260: =IF(J260="","",VLOOKUP(J260,'BICS Equity Hierarchy 2024'!$C$5:$Q$1783,'Mapping for Equity'!$K$1))
B261: 1110141210 | C261: 5 | D261: =VLOOKUP(B261,'Current BICS'!$B$4:$P$1837,'Mapping for Equity'!$K$1,FALSE) -> Leisure Boats & Yachts Building | E261: ⇒ | G261: ⇒ | H261: 1110141210 | I261: =VLOOKUP(H261,'BICS Equity Hierarchy 2024'!$C$5:$Q$1846,'Mapping for Equity'!$K$1,FALSE) -> Leisure Boats & Yachts Building | K261: =IF(J261="","",VLOOKUP(J261,'BICS Equity Hierarchy 2024'!$C$5:$Q$1783,'Mapping for Equity'!$K$1))
B262: 1110141211 | C262: 5 | D262: =VLOOKUP(B262,'Current BICS'!$B$4:$P$1837,'Mapping for Equity'!$K$1,FALSE) -> Motorhomes, Trailers & Campers | E262: ⇒ | G262: ⇒ | H262: 1110141211 | I262: =VLOOKUP(H262,'BICS Equity Hierarchy 2024'!$C$5:$Q$1846,'Mapping for Equity'!$K$1,FALSE) -> Motorhomes, Trailers & Campers | K262: =IF(J262="","",VLOOKUP(J262,'BICS Equity Hierarchy 2024'!$C$5:$Q$1783,'Mapping for Equity'!$K$1))
B263: 111014121110 | C263: 6 | D263: =VLOOKUP(B263,'Current BICS'!$B$4:$P$1837,'Mapping for Equity'!$K$1,FALSE) -> Motorhomes | E263: ⇒ | G263: ⇒ | H263: 111014121110 | I263: =VLOOKUP(H263,'BICS Equity Hierarchy 2024'!$C$5:$Q$1846,'Mapping for Equity'!$K$1,FALSE) -> Motorhomes | K263: =IF(J263="","",VLOOKUP(J263,'BICS Equity Hierarchy 2024'!$C$5:$Q$1783,'Mapping for Equity'!$K$1))
B264: 111014121111 | C264: 6 | D264: =VLOOKUP(B264,'Current BICS'!$B$4:$P$1837,'Mapping for Equity'!$K$1,FALSE) -> Travel Trailers & Campers | E264: ⇒ | G264: ⇒ | H264: 111014121111 | I264: =VLOOKUP(H264,'BICS Equity Hierarchy 2024'!$C$5:$Q$1846,'Mapping for Equity'!$K$1,FALSE) -> Travel Trailers & Campers | K264: =IF(J264="","",VLOOKUP(J264,'BICS Equity Hierarchy 2024'!$C$5:$Q$1783,'Mapping for Equity'!$K$1))
B265: 11101413 | C265: 4 | D265: =VLOOKUP(B265,'Current BICS'!$B$4:$P$1837,'Mapping for Equity'!$K$1,FALSE) -> Sporting Goods | E265: ⇒ | G265: ⇒ | H265: 11101413 | I265: =VLOOKUP(H265,'BICS Equity Hierarchy 2024'!$C$5:$Q$1846,'Mapping for Equity'!$K$1,FALSE) -> Sporting Goods | K265: =IF(J265="","",VLOOKUP(J265,'BICS Equity Hierarchy 2024'!$C$5:$Q$1783,'Mapping for Equity'!$K$1))
B266: 1110141310 | C266: 5 | D266: =VLOOKUP(B266,'Current BICS'!$B$4:$P$1837,'Mapping for Equity'!$K$1,FALSE) -> Bicycles & Parts | E266: ⇒ | G266: ⇒ | H266: 1110141310 | I266: =VLOOKUP(H266,'BICS Equity Hierarchy 2024'!$C$5:$Q$1846,'Mapping for Equity'!$K$1,FALSE) -> Bicycles & Parts | K266: =IF(J266="","",VLOOKUP(J266,'BICS Equity Hierarchy 2024'!$C$5:$Q$1783,'Mapping for Equity'!$K$1))
B267: 111014131010 | C267: 6 | D267: =VLOOKUP(B267,'Current BICS'!$B$4:$P$1837,'Mapping for Equity'!$K$1,FALSE) -> Bicycles | E267: ⇒ | G267: ⇒ | H267: 111014131010 | I267: =VLOOKUP(H267,'BICS Equity Hierarchy 2024'!$C$5:$Q$1846,'Mapping for Equity'!$K$1,FALSE) -> Bicycles | K267: =IF(J267="","",VLOOKUP(J267,'BICS Equity Hierarchy 2024'!$C$5:$Q$1783,'Mapping for Equity'!$K$1))
... B517: 121010101318 | C517: 6 | D517: =VLOOKUP(B517,'Current BICS'!$B$4:$P$1837,'Mapping for Equity'!$K$1,FALSE) -> Support Services - Crop Prod | E517: ⇒ | G517: ⇒ | H517: 121010101318 | I517: =VLOOKUP(H517,'BICS Equity Hierarchy 2024'!$C$5:$Q$1846,'Mapping for Equity'!$K$1,FALSE) -> Support Services - Crop Prod | K517: =IF(J517="","",VLOOKUP(J517,'BICS Equity Hierarchy 2024'!$C$5:$Q$1783,'Mapping for Equity'!$K$1))
B518: 1210101014 | C518: 5 | D518: =VLOOKUP(B518,'Current BICS'!$B$4:$P$1837,'Mapping for Equity'!$K$1,FALSE) -> Sugar, Grain & Oilseed Mill | E518: ⇒ | F518: Name Changed | G518: ⇒ | H518: 1210101014 | I518: =VLOOKUP(H518,'BICS Equity Hierarchy 2024'!$C$5:$Q$1846,'Mapping for Equity'!$K$1,FALSE) -> Food Crop Processing | K518: =IF(J518="","",VLOOKUP(J518,'BICS Equity Hierarchy 2024'!$C$5:$Q$1783,'Mapping for Equity'!$K$1))
B519: 121010101410 | C519: 6 | D519: =VLOOKUP(B519,'Current BICS'!$B$4:$P$1837,'Mapping for Equity'!$K$1,FALSE) -> Grain & Oilseed Milling | E519: ⇒ | G519: ⇒ | H519: 121010101410 | I519: =VLOOKUP(H519,'BICS Equity Hierarchy 2024'!$C$5:$Q$1846,'Mapping for Equity'!$K$1,FALSE) -> Grain & Oilseed Milling | K519: =IF(J519="","",VLOOKUP(J519,'BICS Equity Hierarchy 2024'!$C$5:$Q$1783,'Mapping for Equity'!$K$1))
B520: 12101010141010 | C520: 7 | D520: =VLOOKUP(B520,'Current BICS'!$B$4:$P$1837,'Mapping for Equity'!$K$1,FALSE) -> Fats & Oil Refining | E520: ⇒ | G520: ⇒ | H520: 12101010141010 | I520: =VLOOKUP(H520,'BICS Equity Hierarchy 2024'!$C$5:$Q$1846,'Mapping for Equity'!$K$1,FALSE) -> Fats & Oil Refining | K520: =IF(J520="","",VLOOKUP(J520,'BICS Equity Hierarchy 2024'!$C$5:$Q$1783,'Mapping for Equity'!$K$1))
B521: 12101010141011 | C521: 7 | D521: =VLOOKUP(B521,'Current BICS'!$B$4:$P$1837,'Mapping for Equity'!$K$1,FALSE) -> Flour Milling | E521: ⇒ | G521: ⇒ | H521: 12101010141011 | I521: =VLOOKUP(H521,'BICS Equity Hierarchy 2024'!$C$5:$Q$1846,'Mapping for Equity'!$K$1,FALSE) -> Flour Milling | K521: =IF(J521="","",VLOOKUP(J521,'BICS Equity Hierarchy 2024'!$C$5:$Q$1783,'Mapping for Equity'!$K$1))
B522: 12101010141012 | C522: 7 | D522: =VLOOKUP(B522,'Current BICS'!$B$4:$P$1837,'Mapping for Equity'!$K$1,FALSE) -> Malt | E522: ⇒ | G522: ⇒ | H522: 12101010141012 | I522: =VLOOKUP(H522,'BICS Equity Hierarchy 2024'!$C$5:$Q$1846,'Mapping for Equity'!$K$1,FALSE) -> Malt | K522: =IF(J522="","",VLOOKUP(J522,'BICS Equity Hierarchy 2024'!$C$5:$Q$1783,'Mapping for Equity'!$K$1))
B523: 12101010141013 | C523: 7 | D523: =VLOOKUP(B523,'Current BICS'!$B$4:$P$1837,'Mapping for Equity'!$K$1,FALSE) -> Palm Oil Processing | E523: ⇒ | G523: ⇒ | H523: 12101010141013 | I523: =VLOOKUP(H523,'BICS Equity Hierarchy 2024'!$C$5:$Q$1846,'Mapping for Equity'!$K$1,FALSE) -> Palm Oil Processing | K523: =IF(J523="","",VLOOKUP(J523,'BICS Equity Hierarchy 2024'!$C$5:$Q$1783,'Mapping for Equity'!$K$1))
B524: 12101010141014 | C524: 7 | D524: =VLOOKUP(B524,'Current BICS'!$B$4:$P$1837,'Mapping for Equity'!$K$1,FALSE) -> Rice Milling | E524: ⇒ | G524: ⇒ | H524: 12101010141014 | I524: =VLOOKUP(H524,'BICS Equity Hierarchy 2024'!$C$5:$Q$1846,'Mapping for Equity'!$K$1,FALSE) -> Rice Milling | K524: =IF(J524="","",VLOOKUP(J524,'BICS Equity Hierarchy 2024'!$C$5:$Q$1783,'Mapping for Equity'!$K$1))
B525: 12101010141015 | C525: 7 | D525: =VLOOKUP(B525,'Current BICS'!$B$4:$P$1837,'Mapping for Equity'!$K$1,FALSE) -> Soybean Processing | E525: ⇒ | G525: ⇒ | H525: 12101010141015 | I525: =VLOOKUP(H525,'BICS Equity Hierarchy 2024'!$C$5:$Q$1846,'Mapping for Equity'!$K$1,FALSE) -> Soybean Processing | K525: =IF(J525="","",VLOOKUP(J525,'BICS Equity Hierarchy 2024'!$C$5:$Q$1783,'Mapping for Equity'!$K$1))
B526: 12101010141016 | C526: 7 | D526: =VLOOKUP(B526,'Current BICS'!$B$4:$P$1837,'Mapping for Equity'!$K$1,FALSE) -> Wet Corn Milling | E526: ⇒ | G526: ⇒ | H526: 12101010141016 | I526: =VLOOKUP(H526,'BICS Equity Hierarchy 2024'!$C$5:$Q$1846,'Mapping for Equity'!$K$1,FALSE) -> Wet Corn Milling | K526: =IF(J526="","",VLOOKUP(J526,'BICS Equity Hierarchy 2024'!$C$5:$Q$1783,'Mapping for Equity'!$K$1))
B527: 121010101411 | C527: 6 | D527: =VLOOKUP(B527,'Current BICS'!$B$4:$P$1837,'Mapping for Equity'!$K$1,FALSE) -> Sugar | E527: ⇒ | G527: ⇒ | H527: 121010101411 | I527: =VLOOKUP(H527,'BICS Equity Hierarchy 2024'!$C$5:$Q$1846,'Mapping for Equity'!$K$1,FALSE) -> Sugar | K527: =IF(J527="","",VLOOKUP(J527,'BICS Equity Hierarchy 2024'!$C$5:$Q$1783,'Mapping for Equity'!$K$1))
B528: 12101010141110 | C528: 7 | D528: =VLOOKUP(B528,'Current BICS'!$B$4:$P$1837,'Mapping for Equity'!$K$1,FALSE) -> Beet Sugar | E528: ⇒ | G528: ⇒ | H528: 12101010141110 | I528: =VLOOKUP(H528,'BICS Equity Hierarchy 2024'!$C$5:$Q$1846,'Mapping for Equity'!$K$1,FALSE) -> Beet Sugar | K528: =IF(J528="","",VLOOKUP(J528,'BICS Equity Hierarchy 2024'!$C$5:$Q$1783,'Mapping for Equity'!$K$1))
B529: 12101010141111 | C529: 7 | D529: =VLOOKUP(B529,'Current BICS'!$B$4:$P$1837,'Mapping for Equity'!$K$1,FALSE) -> Cane Sugar Refining | E529: ⇒ | G529: ⇒ | H529: 12101010141111 | I529: =VLOOKUP(H529,'BICS Equity Hierarchy 2024'!$C$5:$Q$1846,'Mapping for Equity'!$K$1,FALSE) -> Cane Sugar Refining | K529: =IF(J529="","",VLOOKUP(J529,'BICS Equity Hierarchy 2024'!$C$5:$Q$1783,'Mapping for Equity'!$K$1))
B530: 12101010141112 | C530: 7 | D530: =VLOOKUP(B530,'Current BICS'!$B$4:$P$1837,'Mapping for Equity'!$K$1,FALSE) -> Sugarcane Mills | E530: ⇒ | G530: ⇒ | H530: 12101010141112 | I530: =VLOOKUP(H530,'BICS Equity Hierarchy 2024'!$C$5:$Q$1846,'Mapping for Equity'!$K$1,FALSE) -> Sugarcane Mills | K530: =IF(J530="","",VLOOKUP(J530,'BICS Equity Hierarchy 2024'!$C$5:$Q$1783,'Mapping for Equity'!$K$1))
... B568: 1210101117 | C568: 5 | D568: =VLOOKUP(B568,'Current BICS'!$B$4:$P$1837,'Mapping for Equity'!$K$1,FALSE) -> Pet Food | E568: ⇒ | G568: ⇒ | H568: 1210101117 | I568: =VLOOKUP(H568,'BICS Equity Hierarchy 2024'!$C$5:$Q$1846,'Mapping for Equity'!$K$1,FALSE) -> Pet Food | K568: =IF(J568="","",VLOOKUP(J568,'BICS Equity Hierarchy 2024'!$C$5:$Q$1783,'Mapping for Equity'!$K$1))
B569: 1210101118 | C569: 5 | D569: =VLOOKUP(B569,'Current BICS'!$B$4:$P$1837,'Mapping for Equity'!$K$1,FALSE) -> Snack Food & Confectionary | E569: ⇒ | F569: Name Changed | G569: ⇒ | H569: 1210101118 | I569: =VLOOKUP(H569,'BICS Equity Hierarchy 2024'!$C$5:$Q$1846,'Mapping for Equity'!$K$1,FALSE) -> Snack Food & Confectionery | K569: =IF(J569="","",VLOOKUP(J569,'BICS Equity Hierarchy 2024'!$C$5:$Q$1783,'Mapping for Equity'!$K$1))
B570: 121010111810 | C570: 6 | D570: =VLOOKUP(B570,'Current BICS'!$B$4:$P$1837,'Mapping for Equity'!$K$1,FALSE) -> Confectionery | E570: ⇒ | G570: ⇒ | H570: 121010111810 | I570: =VLOOKUP(H570,'BICS Equity Hierarchy 2024'!$C$5:$Q$1846,'Mapping for Equity'!$K$1,FALSE) -> Confectionery | K570: =IF(J570="","",VLOOKUP(J570,'BICS Equity Hierarchy 2024'!$C$5:$Q$1783,'Mapping for Equity'!$K$1))
B571: 12101011181010 | C571: 7 | D571: =VLOOKUP(B571,'Current BICS'!$B$4:$P$1837,'Mapping for Equity'!$K$1,FALSE) -> Chocolate Confectionery | E571: ⇒ | G571: ⇒ | H571: 12101011181010 | I571: =VLOOKUP(H571,'BICS Equity Hierarchy 2024'!$C$5:$Q$1846,'Mapping for Equity'!$K$1,FALSE) -> Chocolate Confectionery | K571: =IF(J571="","",VLOOKUP(J571,'BICS Equity Hierarchy 2024'!$C$5:$Q$1783,'Mapping for Equity'!$K$1))
B572: 12101011181011 | C572: 7 | D572: =VLOOKUP(B572,'Current BICS'!$B$4:$P$1837,'Mapping for Equity'!$K$1,FALSE) -> Sugar & Other Confectionary | E572: ⇒ | F572: Name Changed | G572: ⇒ | H572: 12101011181011 | I572: =VLOOKUP(H572,'BICS Equity Hierarchy 2024'!$C$5:$Q$1846,'Mapping for Equity'!$K$1,FALSE) -> Sugar & Other Confectionery | K572: =IF(J572="","",VLOOKUP(J572,'BICS Equity Hierarchy 2024'!$C$5:$Q$1783,'Mapping for Equity'!$K$1))
B573: 121010111811 | C573: 6 | D573: =VLOOKUP(B573,'Current BICS'!$B$4:$P$1837,'Mapping for Equity'!$K$1,FALSE) -> Snack Food | E573: ⇒ | G573: ⇒ | H573: 121010111811 | I573: =VLOOKUP(H573,'BICS Equity Hierarchy 2024'!$C$5:$Q$1846,'Mapping for Equity'!$K$1,FALSE) -> Snack Food | K573: =IF(J573="","",VLOOKUP(J573,'BICS Equity Hierarchy 2024'!$C$5:$Q$1783,'Mapping for Equity'!$K$1))
B574: 12101011181110 | C574: 7 | D574: =VLOOKUP(B574,'Current BICS'!$B$4:$P$1837,'Mapping for Equity'!$K$1,FALSE) -> Breakfast Cereal | E574: ⇒ | G574: ⇒ | H574: 12101011181110 | I574: =VLOOKUP(H574,'BICS Equity Hierarchy 2024'!$C$5:$Q$1846,'Mapping for Equity'!$K$1,FALSE) -> Breakfast Cereal | K574: =IF(J574="","",VLOOKUP(J574,'BICS Equity Hierarchy 2024'!$C$5:$Q$1783,'Mapping for Equity'!$K$1))
B575: 12101011181111 | C575: 7 | D575: =VLOOKUP(B575,'Current BICS'!$B$4:$P$1837,'Mapping for Equity'!$K$1,FALSE) -> Cookies & Crackers | E575: ⇒ | G575: ⇒ | H575: 12101011181111 | I575: =VLOOKUP(H575,'BICS Equity Hierarchy 2024'!$C$5:$Q$1846,'Mapping for Equity'!$K$1,FALSE) -> Cookies & Crackers | K575: =IF(J575="","",VLOOKUP(J575,'BICS Equity Hierarchy 2024'!$C$5:$Q$1783,'Mapping for Equity'!$K$1))
B576: 12101011181112 | C576: 7 | D576: =VLOOKUP(B576,'Current BICS'!$B$4:$P$1837,'Mapping for Equity'!$K$1,FALSE) -> Roast Nuts & Peanut Butter | E576: ⇒ | G576: ⇒ | H576: 12101011181112 | I576: =VLOOKUP(H576,'BICS Equity Hierarchy 2024'!$C$5:$Q$1846,'Mapping for Equity'!$K$1,FALSE) -> Roast Nuts & Peanut Butter | K576: =IF(J576="","",VLOOKUP(J576,'BICS Equity Hierarchy 2024'!$C$5:$Q$1783,'Mapping for Equity'!$K$1))
B577: 1210101119 | C577: 5 | D577: =VLOOKUP(B577,'Current BICS'!$B$4:$P$1837,'Mapping for Equity'!$K$1,FALSE) -> Nutritional Supplements | E577: ⇒ | G577: ⇒ | H577: 1210101119 | I577: =VLOOKUP(H577,'BICS Equity Hierarchy 2024'!$C$5:$Q$1846,'Mapping for Equity'!$K$1,FALSE) -> Nutritional Supplements | K577: =IF(J577="","",VLOOKUP(J577,'BICS Equity Hierarchy 2024'!$C$5:$Q$1783,'Mapping for Equity'!$K$1))
B578: 121011 | C578: 3 | D578: =VLOOKUP(B578,'Current BICS'!$B$4:$P$1837,'Mapping for Equity'!$K$1,FALSE) -> Beverages | E578: ⇒ | G578: ⇒ | H578: 121011 | I578: =VLOOKUP(H578,'BICS Equity Hierarchy 2024'!$C$5:$Q$1846,'Mapping for Equity'!$K$1,FALSE) -> Beverages | K578: =IF(J578="","",VLOOKUP(J578,'BICS Equity Hierarchy 2024'!$C$5:$Q$1783,'Mapping for Equity'!$K$1))
B579: 12101110 | C579: 4 | D579: =VLOOKUP(B579,'Current BICS'!$B$4:$P$1837,'Mapping for Equity'!$K$1,FALSE) -> Alcoholic Beverages | E579: ⇒ | G579: ⇒ | H579: 12101110 | I579: =VLOOKUP(H579,'BICS Equity Hierarchy 2024'!$C$5:$Q$1846,'Mapping for Equity'!$K$1,FALSE) -> Alcoholic Beverages | K579: =IF(J579="","",VLOOKUP(J579,'BICS Equity Hierarchy 2024'!$C$5:$Q$1783,'Mapping for Equity'!$K$1))
B580: 1210111010 | C580: 5 | D580: =VLOOKUP(B580,'Current BICS'!$B$4:$P$1837,'Mapping for Equity'!$K$1,FALSE) -> Brewers | E580: ⇒ | G580: ⇒ | H580: 1210111010 | I580: =VLOOKUP(H580,'BICS Equity Hierarchy 2024'!$C$5:$Q$1846,'Mapping for Equity'!$K$1,FALSE) -> Brewers | K580: =IF(J580="","",VLOOKUP(J580,'BICS Equity Hierarchy 2024'!$C$5:$Q$1783,'Mapping for Equity'!$K$1))
B581: 1210111011 | C581: 5 | D581: =VLOOKUP(B581,'Current BICS'!$B$4:$P$1837,'Mapping for Equity'!$K$1,FALSE) -> Distillers | E581: ⇒ | G581: ⇒ | H581: 1210111011 | I581: =VLOOKUP(H581,'BICS Equity Hierarchy 2024'!$C$5:$Q$1846,'Mapping for Equity'!$K$1,FALSE) -> Distillers | K581: =IF(J581="","",VLOOKUP(J581,'BICS Equity Hierarchy 2024'!$C$5:$Q$1783,'Mapping for Equity'!$K$1))
B582: 1210111012 | C582: 5 | D582: =VLOOKUP(B582,'Current BICS'!$B$4:$P$1837,'Mapping for Equity'!$K$1,FALSE) -> Vintners | E582: ⇒ | G582: ⇒ | H582: 1210111012 | I582: =VLOOKUP(H582,'BICS Equity Hierarchy 2024'!$C$5:$Q$1846,'Mapping for Equity'!$K$1,FALSE) -> Vintners | K582: =IF(J582="","",VLOOKUP(J582,'BICS Equity Hierarchy 2024'!$C$5:$Q$1783,'Mapping for Equity'!$K$1))
B583: 12101111 | C583: 4 | D583: =VLOOKUP(B583,'Current BICS'!$B$4:$P$1837,'Mapping for Equity'!$K$1,FALSE) -> Non-Alcoholic Beverages | E583: ⇒ | G583: ⇒ | H583: 12101111 | I583: =VLOOKUP(H583,'BICS Equity Hierarchy 2024'!$C$5:$Q$1846,'Mapping for Equity'!$K$1,FALSE) -> Non-Alcoholic Beverages | K583: =IF(J583="","",VLOOKUP(J583,'BICS Equity Hierarchy 2024'!$C$5:$Q$1783,'Mapping for Equity'!$K$1))
B584: 1210111110 | C584: 5 | D584: =VLOOKUP(B584,'Current BICS'!$B$4:$P$1837,'Mapping for Equity'!$K$1,FALSE) -> Coffee | E584: ⇒ | G584: ⇒ | H584: 1210111110 | I584: =VLOOKUP(H584,'BICS Equity Hierarchy 2024'!$C$5:$Q$1846,'Mapping for Equity'!$K$1,FALSE) -> Coffee | K584: =IF(J584="","",VLOOKUP(J584,'BICS Equity Hierarchy 2024'!$C$5:$Q$1783,'Mapping for Equity'!$K$1))
... B649: 1310 | C649: 2 | D649: =VLOOKUP(B649,'Current BICS'!$B$4:$P$1837,'Mapping for Equity'!$K$1,FALSE) -> Oil & Gas | E649: ⇒ | G649: ⇒ | H649: 1310 | I649: =VLOOKUP(H649,'BICS Equity Hierarchy 2024'!$C$5:$Q$1846,'Mapping for Equity'!$K$1,FALSE) -> Oil & Gas | K649: =IF(J649="","",VLOOKUP(J649,'BICS Equity Hierarchy 2024'!$C$5:$Q$1783,'Mapping for Equity'!$K$1))
B650: 131010 | C650: 3 | D650: =VLOOKUP(B650,'Current BICS'!$B$4:$P$1837,'Mapping for Equity'!$K$1,FALSE) -> Oil & Gas Producers | E650: ⇒ | F650: Name Changed | G650: ⇒ | H650: 131010 | I650: =VLOOKUP(H650,'BICS Equity Hierarchy 2024'!$C$5:$Q$1846,'Mapping for Equity'!$K$1,FALSE) -> Oil & Gas Supply Chain | K650: =IF(J650="","",VLOOKUP(J650,'BICS Equity Hierarchy 2024'!$C$5:$Q$1783,'Mapping for Equity'!$K$1))
B651: 13101010 | C651: 4 | D651: =VLOOKUP(B651,'Current BICS'!$B$4:$P$1837,'Mapping for Equity'!$K$1,FALSE) -> Integrated Oils | E651: ⇒ | G651: ⇒ | H651: 13101010 | I651: =VLOOKUP(H651,'BICS Equity Hierarchy 2024'!$C$5:$Q$1846,'Mapping for Equity'!$K$1,FALSE) -> Integrated Oils | K651: =IF(J651="","",VLOOKUP(J651,'BICS Equity Hierarchy 2024'!$C$5:$Q$1783,'Mapping for Equity'!$K$1))
B652: 13101011 | C652: 4 | D652: =VLOOKUP(B652,'Current BICS'!$B$4:$P$1837,'Mapping for Equity'!$K$1,FALSE) -> Exploration & Production | E652: ⇒ | G652: ⇒ | H652: 13101011 | I652: =VLOOKUP(H652,'BICS Equity Hierarchy 2024'!$C$5:$Q$1846,'Mapping for Equity'!$K$1,FALSE) -> Exploration & Production | K652: =IF(J652="","",VLOOKUP(J652,'BICS Equity Hierarchy 2024'!$C$5:$Q$1783,'Mapping for Equity'!$K$1))
B653: 1310101110 | C653: 5 | D653: =VLOOKUP(B653,'Current BICS'!$B$4:$P$1837,'Mapping for Equity'!$K$1,FALSE) -> Crude Oil & Natural Gas E&P | E653: ⇒ | G653: ⇒ | H653: 1310101110 | I653: =VLOOKUP(H653,'BICS Equity Hierarchy 2024'!$C$5:$Q$1846,'Mapping for Equity'!$K$1,FALSE) -> Crude Oil & Natural Gas E&P | K653: =IF(J653="","",VLOOKUP(J653,'BICS Equity Hierarchy 2024'!$C$5:$Q$1783,'Mapping for Equity'!$K$1))
B654: 131010111010 | C654: 6 | D654: =VLOOKUP(B654,'Current BICS'!$B$4:$P$1837,'Mapping for Equity'!$K$1,FALSE) -> Crude Oil Production | E654: ⇒ | G654: ⇒ | H654: 131010111010 | I654: =VLOOKUP(H654,'BICS Equity Hierarchy 2024'!$C$5:$Q$1846,'Mapping for Equity'!$K$1,FALSE) -> Crude Oil Production | K654: =IF(J654="","",VLOOKUP(J654,'BICS Equity Hierarchy 2024'!$C$5:$Q$1783,'Mapping for Equity'!$K$1))
B655: 131010111011 | C655: 6 | D655: =VLOOKUP(B655,'Current BICS'!$B$4:$P$1837,'Mapping for Equity'!$K$1,FALSE) -> Oil Sands Production | E655: ⇒ | G655: ⇒ | H655: 131010111011 | I655: =VLOOKUP(H655,'BICS Equity Hierarchy 2024'!$C$5:$Q$1846,'Mapping for Equity'!$K$1,FALSE) -> Oil Sands Production | K655: =IF(J655="","",VLOOKUP(J655,'BICS Equity Hierarchy 2024'!$C$5:$Q$1783,'Mapping for Equity'!$K$1))
B656: 131010111012 | C656: 6 | D656: =VLOOKUP(B656,'Current BICS'!$B$4:$P$1837,'Mapping for Equity'!$K$1,FALSE) -> Natural Gas Liquids Production | E656: ⇒ | G656: ⇒ | H656: 131010111012 | I656: =VLOOKUP(H656,'BICS Equity Hierarchy 2024'!$C$5:$Q$1846,'Mapping for Equity'!$K$1,FALSE) -> Natural Gas Liquids Production | K656: =IF(J656="","",VLOOKUP(J656,'BICS Equity Hierarchy 2024'!$C$5:$Q$1783,'Mapping for Equity'!$K$1))
B657: 131010111013 | C657: 6 | D657: =VLOOKUP(B657,'Current BICS'!$B$4:$P$1837,'Mapping for Equity'!$K$1,FALSE) -> Natural Gas Production | E657: ⇒ | G657: ⇒ | H657: 131010111013 | I657: =VLOOKUP(H657,'BICS Equity Hierarchy 2024'!$C$5:$Q$1846,'Mapping for Equity'!$K$1,FALSE) -> Natural Gas Production | K657: =IF(J657="","",VLOOKUP(J657,'BICS Equity Hierarchy 2024'!$C$5:$Q$1783,'Mapping for Equity'!$K$1))
B658: 131010111014 | C658: 6 | D658: =VLOOKUP(B658,'Current BICS'!$B$4:$P$1837,'Mapping for Equity'!$K$1,FALSE) -> Negative Royalties | E658: ⇒ | G658: ⇒ | H658: 131010111014 | I658: =VLOOKUP(H658,'BICS Equity Hierarchy 2024'!$C$5:$Q$1846,'Mapping for Equity'!$K$1,FALSE) -> Negative Royalties | K658: =IF(J658="","",VLOOKUP(J658,'BICS Equity Hierarchy 2024'!$C$5:$Q$1783,'Mapping for Equity'!$K$1))
B659: 1310101111 | C659: 5 | D659: =VLOOKUP(B659,'Current BICS'!$B$4:$P$1837,'Mapping for Equity'!$K$1,FALSE) -> Oil & Natural Gas Mkt & Trading | E659: ⇒ | G659: ⇒ | H659: 1310101111 | I659: =VLOOKUP(H659,'BICS Equity Hierarchy 2024'!$C$5:$Q$1846,'Mapping for Equity'!$K$1,FALSE) -> Oil & Natural Gas Mkt & Trading | K659: =IF(J659="","",VLOOKUP(J659,'BICS Equity Hierarchy 2024'!$C$5:$Q$1783,'Mapping for Equity'!$K$1))
B660: 1310101112 | C660: 5 | D660: =VLOOKUP(B660,'Current BICS'!$B$4:$P$1837,'Mapping for Equity'!$K$1,FALSE) -> Royalty Income - Oil & Gas | E660: ⇒ | G660: ⇒ | H660: 1310101112 | I660: =VLOOKUP(H660,'BICS Equity Hierarchy 2024'!$C$5:$Q$1846,'Mapping for Equity'!$K$1,FALSE) -> Royalty Income - Oil & Gas | K660: =IF(J660="","",VLOOKUP(J660,'BICS Equity Hierarchy 2024'!$C$5:$Q$1783,'Mapping for Equity'!$K$1))
B661: 13101012 | C661: 4 | D661: =VLOOKUP(B661,'Current BICS'!$B$4:$P$1837,'Mapping for Equity'!$K$1,FALSE) -> Midstream - Oil & Gas | E661: ⇒ | G661: ⇒ | H661: 13101012 | I661: =VLOOKUP(H661,'BICS Equity Hierarchy 2024'!$C$5:$Q$1846,'Mapping for Equity'!$K$1,FALSE) -> Midstream - Oil & Gas | K661: =IF(J661="","",VLOOKUP(J661,'BICS Equity Hierarchy 2024'!$C$5:$Q$1783,'Mapping for Equity'!$K$1))
B662: 1310101210 | C662: 5 | D662: =VLOOKUP(B662,'Current BICS'!$B$4:$P$1837,'Mapping for Equity'!$K$1,FALSE) -> Oil & Liquid Rich Gas Pipelines | E662: ⇒ | G662: ⇒ | H662: 1310101210 | I662: =VLOOKUP(H662,'BICS Equity Hierarchy 2024'!$C$5:$Q$1846,'Mapping for Equity'!$K$1,FALSE) -> Oil & Liquid Rich Gas Pipelines | K662: =IF(J662="","",VLOOKUP(J662,'BICS Equity Hierarchy 2024'!$C$5:$Q$1783,'Mapping for Equity'!$K$1))
... B733: 1411101011 | C733: 5 | D733: =VLOOKUP(B733,'Current BICS'!$B$4:$P$1837,'Mapping for Equity'!$K$1,FALSE) -> BDCs | E733: ⇒ | G733: ⇒ | H733: 1411101011 | I733: =VLOOKUP(H733,'BICS Equity Hierarchy 2024'!$C$5:$Q$1846,'Mapping for Equity'!$K$1,FALSE) -> BDCs | K733: =IF(J733="","",VLOOKUP(J733,'BICS Equity Hierarchy 2024'!$C$5:$Q$1783,'Mapping for Equity'!$K$1))
B734: 1411101012 | C734: 5 | D734: =VLOOKUP(B734,'Current BICS'!$B$4:$P$1837,'Mapping for Equity'!$K$1,FALSE) -> SPAC | E734: ⇒ | F734: Name Changed | G734: ⇒ | H734: 1411101012 | I734: =VLOOKUP(H734,'BICS Equity Hierarchy 2024'!$C$5:$Q$1846,'Mapping for Equity'!$K$1,FALSE) -> Blank Check | K734: =IF(J734="","",VLOOKUP(J734,'BICS Equity Hierarchy 2024'!$C$5:$Q$1783,'Mapping for Equity'!$K$1))
B735: 14111011 | C735: 4 | D735: =VLOOKUP(B735,'Current BICS'!$B$4:$P$1837,'Mapping for Equity'!$K$1,FALSE) -> Investment Management | E735: ⇒ | G735: ⇒ | H735: 14111011 | I735: =VLOOKUP(H735,'BICS Equity Hierarchy 2024'!$C$5:$Q$1846,'Mapping for Equity'!$K$1,FALSE) -> Investment Management | K735: =IF(J735="","",VLOOKUP(J735,'BICS Equity Hierarchy 2024'!$C$5:$Q$1783,'Mapping for Equity'!$K$1))
B736: 1411101110 | C736: 5 | D736: =VLOOKUP(B736,'Current BICS'!$B$4:$P$1837,'Mapping for Equity'!$K$1,FALSE) -> Equities | E736: ⇒ | G736: ⇒ | H736: 1411101110 | I736: =VLOOKUP(H736,'BICS Equity Hierarchy 2024'!$C$5:$Q$1846,'Mapping for Equity'!$K$1,FALSE) -> Equities | K736: =IF(J736="","",VLOOKUP(J736,'BICS Equity Hierarchy 2024'!$C$5:$Q$1783,'Mapping for Equity'!$K$1))
B737: 1411101111 | C737: 5 | D737: =VLOOKUP(B737,'Current BICS'!$B$4:$P$1837,'Mapping for Equity'!$K$1,FALSE) -> Fixed Income | E737: ⇒ | G737: ⇒ | H737: 1411101111 | I737: =VLOOKUP(H737,'BICS Equity Hierarchy 2024'!$C$5:$Q$1846,'Mapping for Equity'!$K$1,FALSE) -> Fixed Income | K737: =IF(J737="","",VLOOKUP(J737,'BICS Equity Hierarchy 2024'!$C$5:$Q$1783,'Mapping for Equity'!$K$1))
B738: 1411101112 | C738: 5 | D738: =VLOOKUP(B738,'Current BICS'!$B$4:$P$1837,'Mapping for Equity'!$K$1,FALSE) -> Hedge Fund Investments | E738: ⇒ | G738: ⇒ | H738: 1411101112 | I738: =VLOOKUP(H738,'BICS Equity Hierarchy 2024'!$C$5:$Q$1846,'Mapping for Equity'!$K$1,FALSE) -> Hedge Fund Investments | K738: =IF(J738="","",VLOOKUP(J738,'BICS Equity Hierarchy 2024'!$C$5:$Q$1783,'Mapping for Equity'!$K$1))
B739: 1411101113 | C739: 5 | D739: =VLOOKUP(B739,'Current BICS'!$B$4:$P$1837,'Mapping for Equity'!$K$1,FALSE) -> Mixed Asset | E739: ⇒ | G739: ⇒ | H739: 1411101113 | I739: =VLOOKUP(H739,'BICS Equity Hierarchy 2024'!$C$5:$Q$1846,'Mapping for Equity'!$K$1,FALSE) -> Mixed Asset | K739: =IF(J739="","",VLOOKUP(J739,'BICS Equity Hierarchy 2024'!$C$5:$Q$1783,'Mapping for Equity'!$K$1))
B740: 14111012 | C740: 4 | D740: =VLOOKUP(B740,'Current BICS'!$B$4:$P$1837,'Mapping for Equity'!$K$1,FALSE) -> Private Equity | E740: ⇒ | G740: ⇒ | H740: 14111012 | I740: =VLOOKUP(H740,'BICS Equity Hierarchy 2024'!$C$5:$Q$1846,'Mapping for Equity'!$K$1,FALSE) -> Private Equity | K740: =IF(J740="","",VLOOKUP(J740,'BICS Equity Hierarchy 2024'!$C$5:$Q$1783,'Mapping for Equity'!$K$1))
B741: 1411101210 | C741: 5 | D741: =VLOOKUP(B741,'Current BICS'!$B$4:$P$1837,'Mapping for Equity'!$K$1,FALSE) -> Co-Investments | E741: ⇒ | G741: ⇒ | H741: 1411101210 | I741: =VLOOKUP(H741,'BICS Equity Hierarchy 2024'!$C$5:$Q$1846,'Mapping for Equity'!$K$1,FALSE) -> Co-Investments | K741: =IF(J741="","",VLOOKUP(J741,'BICS Equity Hierarchy 2024'!$C$5:$Q$1783,'Mapping for Equity'!$K$1))
...

Sheet Mapping for Fixed Income
B1: LANGUAGE:
B2: English
B3: BICS Equity 2024 | F3: BICS Fixed Income | H3: Back to Table of Contents
B4: BICS Code | C4: Level | D4: BICS Name | F4: BICS Code | G4: BICS Name
B5: 10 | C5: 1 | D5: Communications | E5: ⇒
B6: 1010 | C6: 2 | D6: Media | E6: ⇒
B7: 101010 | C7: 3 | D7: Advertising & Marketing | E7: ⇒
B8: 10101010 | C8: 4 | D8: Advertising & Marketing | E8: ⇒ | F8: 3116 | G8: Advertising & Marketing
B9: 1010101010 | C9: 5 | D9: Advertising Agencies & Svcs | E9: ⇒ | F9: 3116 | G9: Advertising & Marketing
B10: 101010101010 | C10: 6 | D10: Advertising Agencies | E10: ⇒ | F10: 3116 | G10: Advertising & Marketing
B11: 101010101011 | C11: 6 | D11: E-Marketing | E11: ⇒ | F11: 3116 | G11: Advertising & Marketing
B12: 101010101012 | C12: 6 | D12: Market Research & Consulting | E12: ⇒ | F12: 3116 | G12: Advertising & Marketing
B13: 10101010101210 | C13: 7 | D13: Marketing Consulting Services | E13: ⇒ | F13: 3116 | G13: Advertising & Marketing
B14: 10101010101211 | C14: 7 | D14: Market Research | E14: ⇒ | F14: 3116 | G14: Advertising & Marketing
B15: 101010101013 | C15: 6 | D15: Media Representatives | E15: ⇒ | F15: 3116 | G15: Advertising & Marketing
B16: 101010101014 | C16: 6 | D16: Public Relations Agencies | E16: ⇒ | F16: 3116 | G16: Advertising & Marketing
B17: 1010101011 | C17: 5 | D17: Direct Marketing | E17: ⇒ | F17: 3116 | G17: Advertising & Marketing
B18: 101010101110 | C18: 6 | D18: Advertising Material Distr Svcs | E18: ⇒ | F18: 3116 | G18: Advertising & Marketing
B19: 101010101111 | C19: 6 | D19: Direct Mail Advertising | E19: ⇒ | F19: 3116 | G19: Advertising & Marketing
B20: 101011 | C20: 3 | D20: Cable & Satellite | E20: ⇒
B21: 10101110 | C21: 4 | D21: Cable & Satellite | E21: ⇒ | F21: 3110 | G21: Cable & Satellite
B22: 1010111010 | C22: 5 | D22: Cable & Satellite Video Svcs | E22: ⇒ | F22: 3110 | G22: Cable & Satellite
B23: 1010111011 | C23: 5 | D23: Cable & Satellite Internet Svcs | E23: ⇒ | F23: 3110 | G23: Cable & Satellite
B24: 1010111012 | C24: 5 | D24: Cable & Satellite Phone Svcs | E24: ⇒ | F24: 3110 | G24: Cable & Satellite
B25: 101012 | C25: 3 | D25: Entertainment Content | E25: ⇒
B26: 10101210 | C26: 4 | D26: Film & TV | E26: ⇒ | F26: 3114 | G26: Entertainment Content
B27: 1010121010 | C27: 5 | D27: Film & TV Production & Distr | E27: ⇒ | F27: 3114 | G27: Entertainment Content
B28: 101012101010 | C28: 6 | D28: Film & TV Production | E28: ⇒ | F28: 3114 | G28: Entertainment Content
B29: 10101210101010 | C29: 7 | D29: Film Production | E29: ⇒ | F29: 3114 | G29: Entertainment Content
B30: 10101210101011 | C30: 7 | D30: TV & Video Production | E30: ⇒ | F30: 3114 | G30: Entertainment Content
B31: 101012101011 | C31: 6 | D31: Film & Video Distribution | E31: ⇒ | F31: 3114 | G31: Entertainment Content
B32: 10101210101110 | C32: 7 | D32: Film Distribution | E32: ⇒ | F32: 3114 | G32: Entertainment Content
B33: 10101210101111 | C33: 7 | D33: TV Show Syndication | E33: ⇒ | F33: 3114 | G33: Entertainment Content
B34: 101012101012 | C34: 6 | D34: Teleprod & Postprod Services | E34: ⇒ | F34: 3114 | G34: Entertainment Content
B35: 101012101013 | C35: 6 | D35: Online Film & TV Streaming | E35: ⇒ | F35: 3114 | G35: Entertainment Content
B36: 1010121011 | C36: 5 | D36: TV Media Networks | E36: ⇒ | F36: 3114 | G36: Entertainment Content
B37: 101012101110 | C37: 6 | D37: Cable Networks | E37: ⇒ | F37: 3114 | G37: Entertainment Content
... B50: 1010121211 | C50: 5 | D50: Console & PC Games | E50: ⇒ | F50: 3812 | G50: Software & Services
B51: 101013 | C51: 3 | D51: Publishing & Broadcasting | E51: ⇒
B52: 10101310 | C52: 4 | D52: Publishing | E52: ⇒ | F52: 3115 | G52: Publishing & Broadcasting
B53: 1010131010 | C53: 5 | D53: Book Publishers | E53: ⇒ | F53: 3115 | G53: Publishing & Broadcasting
B54: 101013101010 | C54: 6 | D54: Professional Book Publishers | E54: ⇒ | F54: 3115 | G54: Publishing & Broadcasting
B55: 101013101011 | C55: 6 | D55: School Textbook Publishers | E55: ⇒ | F55: 3115 | G55: Publishing & Broadcasting
B56: 1010131011 | C56: 5 | D56: Newspaper Publishers | E56: ⇒ | F56: 3115 | G56: Publishing & Broadcasting
B57: 101013101110 | C57: 6 | D57: Advertising Rev - Newspaper | E57: ⇒ | F57: 3115 | G57: Publishing & Broadcasting
B58: 101013101111 | C58: 6 | D58: Circulation Rev - Newspaper | E58: ⇒ | F58: 3115 | G58: Publishing & Broadcasting
B59: 101013101112 | C59: 6 | D59: Other Revenue - Newspaper | E59: ⇒ | F59: 3115 | G59: Publishing & Broadcasting
B60: 1010131012 | C60: 5 | D60: Periodical Publishers | E60: ⇒ | F60: 3115 | G60: Publishing & Broadcasting
B61: 101013101210 | C61: 6 | D61: Advertising Rev - Periodical | E61: ⇒ | F61: 3115 | G61: Publishing & Broadcasting
B62: 101013101211 | C62: 6 | D62: Circulation Rev - Periodical | E62: ⇒ | F62: 3115 | G62: Publishing & Broadcasting
B63: 101013101212 | C63: 6 | D63: Other Revenue - Periodical | E63: ⇒ | F63: 3115 | G63: Publishing & Broadcasting
... B71: 10101312 | C71: 4 | D71: Out-of-Home Display Advertising | E71: ⇒ | F71: 3115 | G71: Publishing & Broadcasting
B72: 101014 | C72: 3 | D72: Internet Media & Services | E72: ⇒
B73: 10101410 | C73: 4 | D73: Internet Media & Services | E73: ⇒ | F73: 3112 | G73: Internet Media
B74: 1010141010 | C74: 5 | D74: Automotive Web | E74: ⇒ | F74: 3112 | G74: Internet Media
B75: 101014101010 | C75: 6 | D75: Adv Rev - Automotive Web | E75: ⇒ | F75: 3112 | G75: Internet Media
B76: 101014101011 | C76: 6 | D76: Other Rev - Automotive Web | E76: ⇒ | F76: 3112 | G76: Internet Media
B77: 1010141011 | C77: 5 | D77: Dating Services Web | E77: ⇒ | F77: 3112 | G77: Internet Media
B78: 101014101110 | C78: 6 | D78: Adv Rev - Dating Services Web | E78: ⇒ | F78: 3112 | G78: Internet Media
B79: 101014101111 | C79: 6 | D79: Other Rev - Dating Svcs Web | E79: ⇒ | F79: 3112 | G79: Internet Media
B80: 1010141012 | C80: 5 | D80: Domain Registrar | E80: ⇒ | F80: 3112 | G80: Internet Media
B81: 101014101210 | C81: 6 | D81: Adv Rev - Domain Registrar | E81: ⇒ | F81: 3112 | G81: Internet Media
B82: 101014101211 | C82: 6 | D82: Other Rev - Domain Registrar | E82: ⇒ | F82: 3112 | G82: Internet Media
B83: 1010141013 | C83: 5 | D83: Entmt Event Ticket Online | E83: ⇒ | F83: 3112 | G83: Internet Media
B84: 101014101310 | C84: 6 | D84: Adv Rev-Entmt Evt Ticket Online | E84: ⇒ | F84: 3112 | G84: Internet Media
... B120: 101014102411 | C120: 6 | D120: Ridesharing Svcs | E120: ⇒ | F120: 3112 | G120: Internet Media
B121: 1011 | C121: 2 | D121: Telecommunications | E121: ⇒
B122: 101110 | C122: 3 | D122: Telecommunications | E122: ⇒
B123: 10111010 | C123: 4 | D123: Wireless Telecommunications | E123: ⇒ | F123: 3113 | G123: Wireless Telecommunications Services
B124: 1011101010 | C124: 5 | D124: Wireless Service Providers | E124: ⇒ | F124: 3113 | G124: Wireless Telecommunications Services
B125: 101110101010 | C125: 6 | D125: Mobile Phone Services | E125: ⇒ | F125: 3113 | G125: Wireless Telecommunications Services
B126: 101110101011 | C126: 6 | D126: Mobile Data Services | E126: ⇒ | F126: 3113 | G126: Wireless Telecommunications Services
B127: 101110101012 | C127: 6 | D127: Mobile Text Messaging (SMS) | E127: ⇒ | F127: 3113 | G127: Wireless Telecommunications Services
B128: 101110101013 | C128: 6 | D128: Mobile Roaming Services | E128: ⇒ | F128: 3113 | G128: Wireless Telecommunications Services
B129: 101110101014 | C129: 6 | D129: Wireless Infra Access Revenue | E129: ⇒ | F129: 3113 | G129: Wireless Telecommunications Services
B130: 1011101011 | C130: 5 | D130: Satellite Operators | E130: ⇒ | F130: 3113 | G130: Wireless Telecommunications Services
B131: 1011101012 | C131: 5 | D131: Mobile Comm Device Revenue | E131: ⇒ | F131: 3113 | G131: Wireless Telecommunications Services
B132: 10111011 | C132: 4 | D132: Wireline Telecommunications | E132: ⇒ | F132: 3111 | G132: Wireline Telecommunications Services
B133: 1011101110 | C133: 5 | D133: Wireline Phone Services | E133: ⇒ | F133: 3111 | G133: Wireline Telecommunications Services
B134: 101110111010 | C134: 6 | D134: VOIP Services | E134: ⇒ | F134: 3111 | G134: Wireline Telecommunications Services
... B141: 1011101114 | C141: 5 | D141: Data Centers | E141: ⇒ | F141: 3111 | G141: Wireline Telecommunications Services
B142: 11 | C142: 1 | D142: Consumer Discretionary | E142: ⇒
B143: 1110 | C143: 2 | D143: Consumer Discretionary Products | E143: ⇒
B144: 111010 | C144: 3 | D144: Apparel & Textile Products | E144: ⇒
B145: 11101010 | C145: 4 | D145: Apparel, Footwear & Acc Design | E145: ⇒ | F145: 3219 | G145: Apparel & Textile Products
B146: 1110101010 | C146: 5 | D146: Apparel Design | E146: ⇒ | F146: 3219 | G146: Apparel & Textile Products
B147: 111010101010 | C147: 6 | D147: Children's Apparel | E147: ⇒ | F147: 3219 | G147: Apparel & Textile Products
B148: 111010101011 | C148: 6 | D148: Men's Apparel | E148: ⇒ | F148: 3219 | G148: Apparel & Textile Products
B149: 111010101012 | C149: 6 | D149: Women's Apparel | E149: ⇒ | F149: 3219 | G149: Apparel & Textile Products
B150: 111010101013 | C150: 6 | D150: Lingerie | E150: ⇒ | F150: 3219 | G150: Apparel & Textile Products
B151: 111010101014 | C151: 6 | D151: Sports Apparel | E151: ⇒ | F151: 3219 | G151: Apparel & Textile Products
B152: 111010101015 | C152: 6 | D152: Fur & Leather Apparel | E152: ⇒ | F152: 3219 | G152: Apparel & Textile Products
B153: 111010101016 | C153: 6 | D153: Outerwear Apparel | E153: ⇒ | F153: 3219 | G153: Apparel & Textile Products
B154: 111010101017 | C154: 6 | D154: Professional Uniforms | E154: ⇒ | F154: 3219 | G154: Apparel & Textile Products
B155: 1110101011 | C155: 5 | D155: Apparel Brand Licensing | E155: ⇒ | F155: 3219 | G155: Apparel & Textile Products
B156: 1110101012 | C156: 5 | D156: Bags, Leather Goods & Acc Design | E156: ⇒ | F156: 3219 | G156: Apparel & Textile Products
... B189: 111010111214 | C189: 6 | D189: Tire Cord & Tire Fabrics Mills | E189: ⇒ | F189: 3219 | G189: Apparel & Textile Products
B190: 111011 | C190: 3 | D190: Automotive | E190: ⇒
B191: 11101110 | C191: 4 | D191: Automobiles | E191: ⇒ | F191: 3211 | G191: Automobiles Manufacturing
B192: 1110111010 | C192: 5 | D192: Cars | E192: ⇒ | F192: 3211 | G192: Automobiles Manufacturing
...

Sheet Comparison Template
B1: LANGUAGE: | F1: Back to Table of Contents
B2: English | C2: DX616= | D2: =INDEX('How To Download'!$E$70:$E$80,MATCH('Comparison Template'!B2,'How To Download'!$D$70:$D$80,FALSE)) -> 1 | E2: BICS 2024
B3: Enter Identifier | C3: ID_BB_COMPANY | D3: SECURITY_NAME | E3: Level 1 - Sector | G3: Level 2 - Industry Group | I3: Level 3 - Industry | K3: Level 4 - Sub-Industry | M3: Level 5 - Segment | O3: Level 6 - Segment | Q3: Level 7 - Segment
E4: CLASSIFICATION_LEVEL_1_CODE | F4: CLASSIFICATION_LEVEL_1_NAME | G4: CLASSIFICATION_LEVEL_2_CODE | H4: CLASSIFICATION_LEVEL_2_NAME | I4: CLASSIFICATION_LEVEL_3_CODE | J4: CLASSIFICATION_LEVEL_3_NAME | K4: CLASSIFICATION_LEVEL_4_CODE | L4: CLASSIFICATION_LEVEL_4_NAME | M4: CLASSIFICATION_LEVEL_5_CODE | N4: CLASSIFICATION_LEVEL_5_NAME | O4: CLASSIFICATION_LEVEL_6_CODE | P4: CLASSIFICATION_LEVEL_6_NAME | Q4: CLASSIFICATION_LEVEL_7_CODE | R4: CLASSIFICATION_LEVEL_7_NAME
B5: GS UN Equity | C5: {=IF($B5="","",_xll.BDP($B5,C$3))} -> 348768 | D5: {=IF($B5="","",_xll.BDP($B5,D$3,"SECURITY_NAME_LANG",$D$2))} -> Goldman Sachs Group Inc/The | E5: {=IF($B5="","",IF(LEFT(_xlfn.SINGLE(_xll.BDP($B5,"CLASSIFICATION_LEVEL_1_CODE","CLASSIFICATION_SCHEME=BICS")),1)="#","",_xll.BDP($B5,"CLASSIFICATION_LEVEL_1_CODE","CLASSIFICATION_SCHEME=BICS")))} -> 14 | F5: {=IF($B5="","",IF(LEFT(_xlfn.SINGLE(_xll.BDP($B5,"CLASSIFICATION_LEVEL_1_NAME","CLASSIFICATION_SCHEME=BICS")),1)="#","",_xll.BDP($B5,"CLASSIFICATION_LEVEL_1_NAME","CLASSIFICATION_SCHEME=BICS","SECURITY_NAME_LANG",$D$2)))} -> Financials | G5: {=IF($B5="","",IF(LEFT(_xlfn.SINGLE(_xll.BDP($B5,"CLASSIFICATION_LEVEL_2_CODE","CLASSIFICATION_SCHEME=BICS")),1)="#","",_xll.BDP($B5,"CLASSIFICATION_LEVEL_2_CODE","CLASSIFICATION_SCHEME=BICS")))} -> 1411 | H5: {=IF($B5="","",IF(LEFT(_xlfn.SINGLE(_xll.BDP($B5,"CLASSIFICATION_LEVEL_2_NAME","CLASSIFICATION_SCHEME=BICS")),1)="#","",_xll.BDP($B5,"CLASSIFICATION_LEVEL_2_NAME","CLASSIFICATION_SCHEME=BICS","SECURITY_NAME_LANG",$D$2)))} -> Financial Services | I5: {=IF($B5="","",IF(LEFT(_xlfn.SINGLE(_xll.BDP($B5,"CLASSIFICATION_LEVEL_3_CODE","CLASSIFICATION_SCHEME=BICS")),1)="#","",_xll.BDP($B5,"CLASSIFICATION_LEVEL_3_CODE","CLASSIFICATION_SCHEME=BICS")))} -> 141112 | J5: {=IF($B5="","",IF(LEFT(_xlfn.SINGLE(_xll.BDP($B5,"CLASSIFICATION_LEVEL_3_NAME","CLASSIFICATION_SCHEME=BICS")),1)="#","",_xll.BDP($B5,"CLASSIFICATION_LEVEL_3_NAME","CLASSIFICATION_SCHEME=BICS","SECURITY_NAME_LANG",$D$2)))} -> Institutional Financial Svcs | K5: {=IF($B5="","",IF(LEFT(_xlfn.SINGLE(_xll.BDP($B5,"CLASSIFICATION_LEVEL_4_CODE","CLASSIFICATION_SCHEME=BICS")),1)="#","",_xll.BDP($B5,"CLASSIFICATION_LEVEL_4_CODE","CLASSIFICATION_SCHEME=BICS")))} -> 14111210 | L5: {=IF($B5="","",IF(LEFT(_xlfn.SINGLE(_xll.BDP($B5,"CLASSIFICATION_LEVEL_4_NAME","CLASSIFICATION_SCHEME=BICS")),1)="#","",_xll.BDP($B5,"CLASSIFICATION_LEVEL_4_NAME","CLASSIFICATION_SCHEME=BICS","SECURITY_NAME_LANG",$D$2)))} -> Institutional Brokerage | M5: {=IF($B5="","",IF(LEFT(_xlfn.SINGLE(_xll.BDP($B5,"CLASSIFICATION_LEVEL_5_CODE","CLASSIFICATION_SCHEME=BICS")),1)="#","",_xll.BDP($B5,"CLASSIFICATION_LEVEL_5_CODE","CLASSIFICATION_SCHEME=BICS")))} -> 1411121012 | N5: {=IF($B5="","",IF(LEFT(_xlfn.SINGLE(_xll.BDP($B5,"CLASSIFICATION_LEVEL_5_NAME","CLASSIFICATION_SCHEME=BICS")),1)="#","",_xll.BDP($B5,"CLASSIFICATION_LEVEL_5_NAME","CLASSIFICATION_SCHEME=BICS","SECURITY_NAME_LANG",$D$2)))} -> Trading & Principal Investment | O5: {=IF($B5="","",IF(LEFT(_xlfn.SINGLE(_xll.BDP($B5,"CLASSIFICATION_LEVEL_6_CODE","CLASSIFICATION_SCHEME=BICS")),1)="#","",_xll.BDP($B5,"CLASSIFICATION_LEVEL_6_CODE","CLASSIFICATION_SCHEME=BICS")))} | P5: {=IF($B5="","",IF(LEFT(_xlfn.SINGLE(_xll.BDP($B5,"CLASSIFICATION_LEVEL_6_NAME","CLASSIFICATION_SCHEME=BICS")),1)="#","",_xll.BDP($B5,"CLASSIFICATION_LEVEL_6_NAME","CLASSIFICATION_SCHEME=BICS","SECURITY_NAME_LANG",$D$2)))} | Q5: {=IF($B5="","",IF(LEFT(_xlfn.SINGLE(_xll.BDP($B5,"CLASSIFICATION_LEVEL_7_CODE","CLASSIFICATION_SCHEME=BICS")),1)="#","",_xll.BDP($B5,"CLASSIFICATION_LEVEL_7_CODE","CLASSIFICATION_SCHEME=BICS")))} | R5: {=IF($B5="","",IF(LEFT(_xlfn.SINGLE(_xll.BDP($B5,"CLASSIFICATION_LEVEL_7_NAME","CLASSIFICATION_SCHEME=BICS")),1)="#","",_xll.BDP($B5,"CLASSIFICATION_LEVEL_7_NAME","CLASSIFICATION_SCHEME=BICS","SECURITY_NAME_LANG",$D$2)))}
B6: BA UN Equity | C6: {=IF($B6="","",_xll.BDP($B6,C$3))} -> 100211 | D6: {=IF($B6="","",_xll.BDP($B6,D$3,"SECURITY_NAME_LANG",$D$2))} -> Boeing Co/The | E6: {=IF($B6="","",IF(LEFT(_xlfn.SINGLE(_xll.BDP($B6,"CLASSIFICATION_LEVEL_1_CODE","CLASSIFICATION_SCHEME=BICS")),1)="#","",_xll.BDP($B6,"CLASSIFICATION_LEVEL_1_CODE","CLASSIFICATION_SCHEME=BICS")))} -> 17 | F6: {=IF($B6="","",IF(LEFT(_xlfn.SINGLE(_xll.BDP($B6,"CLASSIFICATION_LEVEL_1_NAME","CLASSIFICATION_SCHEME=BICS")),1)="#","",_xll.BDP($B6,"CLASSIFICATION_LEVEL_1_NAME","CLASSIFICATION_SCHEME=BICS","SECURITY_NAME_LANG",$D$2)))} -> Industrials | G6: {=IF($B6="","",IF(LEFT(_xlfn.SINGLE(_xll.BDP($B6,"CLASSIFICATION_LEVEL_2_CODE","CLASSIFICATION_SCHEME=BICS")),1)="#","",_xll.BDP($B6,"CLASSIFICATION_LEVEL_2_CODE","CLASSIFICATION_SCHEME=BICS")))} -> 1710 | H6: {=IF($B6="","",IF(LEFT(_xlfn.SINGLE(_xll.BDP($B6,"CLASSIFICATION_LEVEL_2_NAME","CLASSIFICATION_SCHEME=BICS")),1)="#","",_xll.BDP($B6,"CLASSIFICATION_LEVEL_2_NAME","CLASSIFICATION_SCHEME=BICS","SECURITY_NAME_LANG",$D$2)))} -> Industrial Products | I6: {=IF($B6="","",IF(LEFT(_xlfn.SINGLE(_xll.BDP($B6,"CLASSIFICATION_LEVEL_3_CODE","CLASSIFICATION_SCHEME=BICS")),1)="#","",_xll.BDP($B6,"CLASSIFICATION_LEVEL_3_CODE","CLASSIFICATION_SCHEME=BICS")))} -> 171011 | J6: {=IF($B6="","",IF(LEFT(_xlfn.SINGLE(_xll.BDP($B6,"CLASSIFICATION_LEVEL_3_NAME","CLASSIFICATION_SCHEME=BICS")),1)="#","",_xll.BDP($B6,"CLASSIFICATION_LEVEL_3_NAME","CLASSIFICATION_SCHEME=BICS","SECURITY_NAME_LANG",$D$2)))} -> Aerospace & Defense | K6: {=IF($B6="","",IF(LEFT(_xlfn.SINGLE(_xll.BDP($B6,"CLASSIFICATION_LEVEL_4_CODE","CLASSIFICATION_SCHEME=BICS")),1)="#","",_xll.BDP($B6,"CLASSIFICATION_LEVEL_4_CODE","CLASSIFICATION_SCHEME=BICS")))} -> 17101110 | L6: {=IF($B6="","",IF(LEFT(_xlfn.SINGLE(_xll.BDP($B6,"CLASSIFICATION_LEVEL_4_NAME","CLASSIFICATION_SCHEME=BICS")),1)="#","",_xll.BDP($B6,"CLASSIFICATION_LEVEL_4_NAME","CLASSIFICATION_SCHEME=BICS","SECURITY_NAME_LANG",$D$2)))} -> Aircraft & Parts | M6: {=IF($B6="","",IF(LEFT(_xlfn.SINGLE(_xll.BDP($B6,"CLASSIFICATION_LEVEL_5_CODE","CLASSIFICATION_SCHEME=BICS")),1)="#","",_xll.BDP($B6,"CLASSIFICATION_LEVEL_5_CODE","CLASSIFICATION_SCHEME=BICS")))} -> 1710111010 | N6: {=IF($B6="","",IF(LEFT(_xlfn.SINGLE(_xll.BDP($B6,"CLASSIFICATION_LEVEL_5_NAME","CLASSIFICATION_SCHEME=BICS")),1)="#","",_xll.BDP($B6,"CLASSIFICATION_LEVEL_5_NAME","CLASSIFICATION_SCHEME=BICS","SECURITY_NAME_LANG",$D$2)))} -> Aircraft | O6: {=IF($B6="","",IF(LEFT(_xlfn.SINGLE(_xll.BDP($B6,"CLASSIFICATION_LEVEL_6_CODE","CLASSIFICATION_SCHEME=BICS")),1)="#","",_xll.BDP($B6,"CLASSIFICATION_LEVEL_6_CODE","CLASSIFICATION_SCHEME=BICS")))} | P6: {=IF($B6="","",IF(LEFT(_xlfn.SINGLE(_xll.BDP($B6,"CLASSIFICATION_LEVEL_6_NAME","CLASSIFICATION_SCHEME=BICS")),1)="#","",_xll.BDP($B6,"CLASSIFICATION_LEVEL_6_NAME","CLASSIFICATION_SCHEME=BICS","SECURITY_NAME_LANG",$D$2)))} | Q6: {=IF($B6="","",IF(LEFT(_xlfn.SINGLE(_xll.BDP($B6,"CLASSIFICATION_LEVEL_7_CODE","CLASSIFICATION_SCHEME=BICS")),1)="#","",_xll.BDP($B6,"CLASSIFICATION_LEVEL_7_CODE","CLASSIFICATION_SCHEME=BICS")))} | R6: {=IF($B6="","",IF(LEFT(_xlfn.SINGLE(_xll.BDP($B6,"CLASSIFICATION_LEVEL_7_NAME","CLASSIFICATION_SCHEME=BICS")),1)="#","",_xll.BDP($B6,"CLASSIFICATION_LEVEL_7_NAME","CLASSIFICATION_SCHEME=BICS","SECURITY_NAME_LANG",$D$2)))}
B7: MMM UN Equity | C7: {=IF($B7="","",_xll.BDP($B7,C$3))} -> 101001 | D7: {=IF($B7="","",_xll.BDP($B7,D$3,"SECURITY_NAME_LANG",$D$2))} -> 3M Co | E7: {=IF($B7="","",IF(LEFT(_xlfn.SINGLE(_xll.BDP($B7,"CLASSIFICATION_LEVEL_1_CODE","CLASSIFICATION_SCHEME=BICS")),1)="#","",_xll.BDP($B7,"CLASSIFICATION_LEVEL_1_CODE","CLASSIFICATION_SCHEME=BICS")))} -> 17 | F7: {=IF($B7="","",IF(LEFT(_xlfn.SINGLE(_xll.BDP($B7,"CLASSIFICATION_LEVEL_1_NAME","CLASSIFICATION_SCHEME=BICS")),1)="#","",_xll.BDP($B7,"CLASSIFICATION_LEVEL_1_NAME","CLASSIFICATION_SCHEME=BICS","SECURITY_NAME_LANG",$D$2)))} -> Industrials | G7: {=IF($B7="","",IF(LEFT(_xlfn.SINGLE(_xll.BDP($B7,"CLASSIFICATION_LEVEL_2_CODE","CLASSIFICATION_SCHEME=BICS")),1)="#","",_xll.BDP($B7,"CLASSIFICATION_LEVEL_2_CODE","CLASSIFICATION_SCHEME=BICS")))} -> 1710 | H7: {=IF($B7="","",IF(LEFT(_xlfn.SINGLE(_xll.BDP($B7,"CLASSIFICATION_LEVEL_2_NAME","CLASSIFICATION_SCHEME=BICS")),1)="#","",_xll.BDP($B7,"CLASSIFICATION_LEVEL_2_NAME","CLASSIFICATION_SCHEME=BICS","SECURITY_NAME_LANG",$D$2)))} -> Industrial Products | I7: {=IF($B7="","",IF(LEFT(_xlfn.SINGLE(_xll.BDP($B7,"CLASSIFICATION_LEVEL_3_CODE","CLASSIFICATION_SCHEME=BICS")),1)="#","",_xll.BDP($B7,"CLASSIFICATION_LEVEL_3_CODE","CLASSIFICATION_SCHEME=BICS")))} -> 171010 | J7: {=IF($B7="","",IF(LEFT(_xlfn.SINGLE(_xll.BDP($B7,"CLASSIFICATION_LEVEL_3_NAME","CLASSIFICATION_SCHEME=BICS")),1)="#","",_xll.BDP($B7,"CLASSIFICATION_LEVEL_3_NAME","CLASSIFICATION_SCHEME=BICS","SECURITY_NAME_LANG",$D$2)))} -> Diversified Industrials | K7: {=IF($B7="","",IF(LEFT(_xlfn.SINGLE(_xll.BDP($B7,"CLASSIFICATION_LEVEL_4_CODE","CLASSIFICATION_SCHEME=BICS")),1)="#","",_xll.BDP($B7,"CLASSIFICATION_LEVEL_4_CODE","CLASSIFICATION_SCHEME=BICS")))} -> 17101010 | L7: {=IF($B7="","",IF(LEFT(_xlfn.SINGLE(_xll.BDP($B7,"CLASSIFICATION_LEVEL_4_NAME","CLASSIFICATION_SCHEME=BICS")),1)="#","",_xll.BDP($B7,"CLASSIFICATION_LEVEL_4_NAME","CLASSIFICATION_SCHEME=BICS","SECURITY_NAME_LANG",$D$2)))} -> Diversified Industrials | M7: {=IF($B7="","",IF(LEFT(_xlfn.SINGLE(_xll.BDP($B7,"CLASSIFICATION_LEVEL_5_CODE","CLASSIFICATION_SCHEME=BICS")),1)="#","",_xll.BDP($B7,"CLASSIFICATION_LEVEL_5_CODE","CLASSIFICATION_SCHEME=BICS")))} | N7: {=IF($B7="","",IF(LEFT(_xlfn.SINGLE(_xll.BDP($B7,"CLASSIFICATION_LEVEL_5_NAME","CLASSIFICATION_SCHEME=BICS")),1)="#","",_xll.BDP($B7,"CLASSIFICATION_LEVEL_5_NAME","CLASSIFICATION_SCHEME=BICS","SECURITY_NAME_LANG",$D$2)))} | O7: {=IF($B7="","",IF(LEFT(_xlfn.SINGLE(_xll.BDP($B7,"CLASSIFICATION_LEVEL_6_CODE","CLASSIFICATION_SCHEME=BICS")),1)="#","",_xll.BDP($B7,"CLASSIFICATION_LEVEL_6_CODE","CLASSIFICATION_SCHEME=BICS")))} | P7: {=IF($B7="","",IF(LEFT(_xlfn.SINGLE(_xll.BDP($B7,"CLASSIFICATION_LEVEL_6_NAME","CLASSIFICATION_SCHEME=BICS")),1)="#","",_xll.BDP($B7,"CLASSIFICATION_LEVEL_6_NAME","CLASSIFICATION_SCHEME=BICS","SECURITY_NAME_LANG",$D$2)))} | Q7: {=IF($B7="","",IF(LEFT(_xlfn.SINGLE(_xll.BDP($B7,"CLASSIFICATION_LEVEL_7_CODE","CLASSIFICATION_SCHEME=BICS")),1)="#","",_xll.BDP($B7,"CLASSIFICATION_LEVEL_7_CODE","CLASSIFICATION_SCHEME=BICS")))} | R7: {=IF($B7="","",IF(LEFT(_xlfn.SINGLE(_xll.BDP($B7,"CLASSIFICATION_LEVEL_7_NAME","CLASSIFICATION_SCHEME=BICS")),1)="#","",_xll.BDP($B7,"CLASSIFICATION_LEVEL_7_NAME","CLASSIFICATION_SCHEME=BICS","SECURITY_NAME_LANG",$D$2)))}
B8: UNH UN Equity | C8: {=IF($B8="","",_xll.BDP($B8,C$3))} -> 101548 | D8: {=IF($B8="","",_xll.BDP($B8,D$3,"SECURITY_NAME_LANG",$D$2))} -> UnitedHealth Group Inc | E8: {=IF($B8="","",IF(LEFT(_xlfn.SINGLE(_xll.BDP($B8,"CLASSIFICATION_LEVEL_1_CODE","CLASSIFICATION_SCHEME=BICS")),1)="#","",_xll.BDP($B8,"CLASSIFICATION_LEVEL_1_CODE","CLASSIFICATION_SCHEME=BICS")))} -> 16 | F8: {=IF($B8="","",IF(LEFT(_xlfn.SINGLE(_xll.BDP($B8,"CLASSIFICATION_LEVEL_1_NAME","CLASSIFICATION_SCHEME=BICS")),1)="#","",_xll.BDP($B8,"CLASSIFICATION_LEVEL_1_NAME","CLASSIFICATION_SCHEME=BICS","SECURITY_NAME_LANG",$D$2)))} -> Health Care | G8: {=IF($B8="","",IF(LEFT(_xlfn.SINGLE(_xll.BDP($B8,"CLASSIFICATION_LEVEL_2_CODE","CLASSIFICATION_SCHEME=BICS")),1)="#","",_xll.BDP($B8,"CLASSIFICATION_LEVEL_2_CODE","CLASSIFICATION_SCHEME=BICS")))} -> 1610 | H8: {=IF($B8="","",IF(LEFT(_xlfn.SINGLE(_xll.BDP($B8,"CLASSIFICATION_LEVEL_2_NAME","CLASSIFICATION_SCHEME=BICS")),1)="#","",_xll.BDP($B8,"CLASSIFICATION_LEVEL_2_NAME","CLASSIFICATION_SCHEME=BICS","SECURITY_NAME_LANG",$D$2)))} -> Health Care | I8: {=IF($B8="","",IF(LEFT(_xlfn.SINGLE(_xll.BDP($B8,"CLASSIFICATION_LEVEL_3_CODE","CLASSIFICATION_SCHEME=BICS")),1)="#","",_xll.BDP($B8,"CLASSIFICATION_LEVEL_3_CODE","CLASSIFICATION_SCHEME=BICS")))} -> 161011 | J8: {=IF($B8="","",IF(LEFT(_xlfn.SINGLE(_xll.BDP($B8,"CLASSIFICATION_LEVEL_3_NAME","CLASSIFICATION_SCHEME=BICS")),1)="#","",_xll.BDP($B8,"CLASSIFICATION_LEVEL_3_NAME","CLASSIFICATION_SCHEME=BICS","SECURITY_NAME_LANG",$D$2)))} -> Health Care Facilities & Svcs | K8: {=IF($B8="","",IF(LEFT(_xlfn.SINGLE(_xll.BDP($B8,"CLASSIFICATION_LEVEL_4_CODE","CLASSIFICATION_SCHEME=BICS")),1)="#","",_xll.BDP($B8,"CLASSIFICATION_LEVEL_4_CODE","CLASSIFICATION_SCHEME=BICS")))} -> 16101113 | L8: {=IF($B8="","",IF(LEFT(_xlfn.SINGLE(_xll.BDP($B8,"CLASSIFICATION_LEVEL_4_NAME","CLASSIFICATION_SCHEME=BICS")),1)="#","",_xll.BDP($B8,"CLASSIFICATION_LEVEL_4_NAME","CLASSIFICATION_SCHEME=BICS","SECURITY_NAME_LANG",$D$2)))} -> Managed Care | M8: {=IF($B8="","",IF(LEFT(_xlfn.SINGLE(_xll.BDP($B8,"CLASSIFICATION_LEVEL_5_CODE","CLASSIFICATION_SCHEME=BICS")),1)="#","",_xll.BDP($B8,"CLASSIFICATION_LEVEL_5_CODE","CLASSIFICATION_SCHEME=BICS")))} | N8: {=IF($B8="","",IF(LEFT(_xlfn.SINGLE(_xll.BDP($B8,"CLASSIFICATION_LEVEL_5_NAME","CLASSIFICATION_SCHEME=BICS")),1)="#","",_xll.BDP($B8,"CLASSIFICATION_LEVEL_5_NAME","CLASSIFICATION_SCHEME=BICS","SECURITY_NAME_LANG",$D$2)))} | O8: {=IF($B8="","",IF(LEFT(_xlfn.SINGLE(_xll.BDP($B8,"CLASSIFICATION_LEVEL_6_CODE","CLASSIFICATION_SCHEME=BICS")),1)="#","",_xll.BDP($B8,"CLASSIFICATION_LEVEL_6_CODE","CLASSIFICATION_SCHEME=BICS")))} | P8: {=IF($B8="","",IF(LEFT(_xlfn.SINGLE(_xll.BDP($B8,"CLASSIFICATION_LEVEL_6_NAME","CLASSIFICATION_SCHEME=BICS")),1)="#","",_xll.BDP($B8,"CLASSIFICATION_LEVEL_6_NAME","CLASSIFICATION_SCHEME=BICS","SECURITY_NAME_LANG",$D$2)))} | Q8: {=IF($B8="","",IF(LEFT(_xlfn.SINGLE(_xll.BDP($B8,"CLASSIFICATION_LEVEL_7_CODE","CLASSIFICATION_SCHEME=BICS")),1)="#","",_xll.BDP($B8,"CLASSIFICATION_LEVEL_7_CODE","CLASSIFICATION_SCHEME=BICS")))} | R8: {=IF($B8="","",IF(LEFT(_xlfn.SINGLE(_xll.BDP($B8,"CLASSIFICATION_LEVEL_7_NAME","CLASSIFICATION_SCHEME=BICS")),1)="#","",_xll.BDP($B8,"CLASSIFICATION_LEVEL_7_NAME","CLASSIFICATION_SCHEME=BICS","SECURITY_NAME_LANG",$D$2)))}
B9: MCD UN Equity | C9: {=IF($B9="","",_xll.BDP($B9,C$3))} -> 100960 | D9: {=IF($B9="","",_xll.BDP($B9,D$3,"SECURITY_NAME_LANG",$D$2))} -> McDonald's Corp | E9: {=IF($B9="","",IF(LEFT(_xlfn.SINGLE(_xll.BDP($B9,"CLASSIFICATION_LEVEL_1_CODE","CLASSIFICATION_SCHEME=BICS")),1)="#","",_xll.BDP($B9,"CLASSIFICATION_LEVEL_1_CODE","CLASSIFICATION_SCHEME=BICS")))} -> 11 | F9: {=IF($B9="","",IF(LEFT(_xlfn.SINGLE(_xll.BDP($B9,"CLASSIFICATION_LEVEL_1_NAME","CLASSIFICATION_SCHEME=BICS")),1)="#","",_xll.BDP($B9,"CLASSIFICATION_LEVEL_1_NAME","CLASSIFICATION_SCHEME=BICS","SECURITY_NAME_LANG",$D$2)))} -> Consumer Discretionary | G9: {=IF($B9="","",IF(LEFT(_xlfn.SINGLE(_xll.BDP($B9,"CLASSIFICATION_LEVEL_2_CODE","CLASSIFICATION_SCHEME=BICS")),1)="#","",_xll.BDP($B9,"CLASSIFICATION_LEVEL_2_CODE","CLASSIFICATION_SCHEME=BICS")))} -> 1111 | H9: {=IF($B9="","",IF(LEFT(_xlfn.SINGLE(_xll.BDP($B9,"CLASSIFICATION_LEVEL_2_NAME","CLASSIFICATION_SCHEME=BICS")),1)="#","",_xll.BDP($B9,"CLASSIFICATION_LEVEL_2_NAME","CLASSIFICATION_SCHEME=BICS","SECURITY_NAME_LANG",$D$2)))} -> Consumer Discretionary Services | I9: {=IF($B9="","",IF(LEFT(_xlfn.SINGLE(_xll.BDP($B9,"CLASSIFICATION_LEVEL_3_CODE","CLASSIFICATION_SCHEME=BICS")),1)="#","",_xll.BDP($B9,"CLASSIFICATION_LEVEL_3_CODE","CLASSIFICATION_SCHEME=BICS")))} -> 111111 | J9: {=IF($B9="","",IF(LEFT(_xlfn.SINGLE(_xll.BDP($B9,"CLASSIFICATION_LEVEL_3_NAME","CLASSIFICATION_SCHEME=BICS")),1)="#","",_xll.BDP($B9,"CLASSIFICATION_LEVEL_3_NAME","CLASSIFICATION_SCHEME=BICS","SECURITY_NAME_LANG",$D$2)))} -> Leisure Facilities & Services | K9: {=IF($B9="","",IF(LEFT(_xlfn.SINGLE(_xll.BDP($B9,"CLASSIFICATION_LEVEL_4_CODE","CLASSIFICATION_SCHEME=BICS")),1)="#","",_xll.BDP($B9,"CLASSIFICATION_LEVEL_4_CODE","CLASSIFICATION_SCHEME=BICS")))} -> 11111113 | L9: {=IF($B9="","",IF(LEFT(_xlfn.SINGLE(_xll.BDP($B9,"CLASSIFICATION_LEVEL_4_NAME","CLASSIFICATION_SCHEME=BICS")),1)="#","",_xll.BDP($B9,"CLASSIFICATION_LEVEL_4_NAME","CLASSIFICATION_SCHEME=BICS","SECURITY_NAME_LANG",$D$2)))} -> Restaurants | M9: {=IF($B9="","",IF(LEFT(_xlfn.SINGLE(_xll.BDP($B9,"CLASSIFICATION_LEVEL_5_CODE","CLASSIFICATION_SCHEME=BICS")),1)="#","",_xll.BDP($B9,"CLASSIFICATION_LEVEL_5_CODE","CLASSIFICATION_SCHEME=BICS")))} -> 1111111310 | N9: {=IF($B9="","",IF(LEFT(_xlfn.SINGLE(_xll.BDP($B9,"CLASSIFICATION_LEVEL_5_NAME","CLASSIFICATION_SCHEME=BICS")),1)="#","",_xll.BDP($B9,"CLASSIFICATION_LEVEL_5_NAME","CLASSIFICATION_SCHEME=BICS","SECURITY_NAME_LANG",$D$2)))} -> Limited Service Restaurants | O9: {=IF($B9="","",IF(LEFT(_xlfn.SINGLE(_xll.BDP($B9,"CLASSIFICATION_LEVEL_6_CODE","CLASSIFICATION_SCHEME=BICS")),1)="#","",_xll.BDP($B9,"CLASSIFICATION_LEVEL_6_CODE","CLASSIFICATION_SCHEME=BICS")))} -> 111111131011 | P9: {=IF($B9="","",IF(LEFT(_xlfn.SINGLE(_xll.BDP($B9,"CLASSIFICATION_LEVEL_6_NAME","CLASSIFICATION_SCHEME=BICS")),1)="#","",_xll.BDP($B9,"CLASSIFICATION_LEVEL_6_NAME","CLASSIFICATION_SCHEME=BICS","SECURITY_NAME_LANG",$D$2)))} -> Fast Food Restaurants | Q9: {=IF($B9="","",IF(LEFT(_xlfn.SINGLE(_xll.BDP($B9,"CLASSIFICATION_LEVEL_7_CODE","CLASSIFICATION_SCHEME=BICS")),1)="#","",_xll.BDP($B9,"CLASSIFICATION_LEVEL_7_CODE","CLASSIFICATION_SCHEME=BICS")))} | R9: {=IF($B9="","",IF(LEFT(_xlfn.SINGLE(_xll.BDP($B9,"CLASSIFICATION_LEVEL_7_NAME","CLASSIFICATION_SCHEME=BICS")),1)="#","",_xll.BDP($B9,"CLASSIFICATION_LEVEL_7_NAME","CLASSIFICATION_SCHEME=BICS","SECURITY_NAME_LANG",$D$2)))}
B10: AAPL UW Equity | C10: {=IF($B10="","",_xll.BDP($B10,C$3))} -> 101695 | D10: {=IF($B10="","",_xll.BDP($B10,D$3,"SECURITY_NAME_LANG",$D$2))} -> Apple Inc | E10: {=IF($B10="","",IF(LEFT(_xlfn.SINGLE(_xll.BDP($B10,"CLASSIFICATION_LEVEL_1_CODE","CLASSIFICATION_SCHEME=BICS")),1)="#","",_xll.BDP($B10,"CLASSIFICATION_LEVEL_1_CODE","CLASSIFICATION_SCHEME=BICS")))} -> 19 | F10: {=IF($B10="","",IF(LEFT(_xlfn.SINGLE(_xll.BDP($B10,"CLASSIFICATION_LEVEL_1_NAME","CLASSIFICATION_SCHEME=BICS")),1)="#","",_xll.BDP($B10,"CLASSIFICATION_LEVEL_1_NAME","CLASSIFICATION_SCHEME=BICS","SECURITY_NAME_LANG",$D$2)))} -> Technology | G10: {=IF($B10="","",IF(LEFT(_xlfn.SINGLE(_xll.BDP($B10,"CLASSIFICATION_LEVEL_2_CODE","CLASSIFICATION_SCHEME=BICS")),1)="#","",_xll.BDP($B10,"CLASSIFICATION_LEVEL_2_CODE","CLASSIFICATION_SCHEME=BICS")))} -> 1910 | H10: {=IF($B10="","",IF(LEFT(_xlfn.SINGLE(_xll.BDP($B10,"CLASSIFICATION_LEVEL_2_NAME","CLASSIFICATION_SCHEME=BICS")),1)="#","",_xll.BDP($B10,"CLASSIFICATION_LEVEL_2_NAME","CLASSIFICATION_SCHEME=BICS","SECURITY_NAME_LANG",$D$2)))} -> Tech Hardware & Semiconductors | I10: {=IF($B10="","",IF(LEFT(_xlfn.SINGLE(_xll.BDP($B10,"CLASSIFICATION_LEVEL_3_CODE","CLASSIFICATION_SCHEME=BICS")),1)="#","",_xll.BDP($B10,"CLASSIFICATION_LEVEL_3_CODE","CLASSIFICATION_SCHEME=BICS")))} -> 191010 | J10: {=IF($B10="","",IF(LEFT(_xlfn.SINGLE(_xll.BDP($B10,"CLASSIFICATION_LEVEL_3_NAME","CLASSIFICATION_SCHEME=BICS")),1)="#","",_xll.BDP($B10,"CLASSIFICATION_LEVEL_3_NAME","CLASSIFICATION_SCHEME=BICS","SECURITY_NAME_LANG",$D$2)))} -> Technology Hardware | K10: {=IF($B10="","",IF(LEFT(_xlfn.SINGLE(_xll.BDP($B10,"CLASSIFICATION_LEVEL_4_CODE","CLASSIFICATION_SCHEME=BICS")),1)="#","",_xll.BDP($B10,"CLASSIFICATION_LEVEL_4_CODE","CLASSIFICATION_SCHEME=BICS")))} -> 19101010 | L10: {=IF($B10="","",IF(LEFT(_xlfn.SINGLE(_xll.BDP($B10,"CLASSIFICATION_LEVEL_4_NAME","CLASSIFICATION_SCHEME=BICS")),1)="#","",_xll.BDP($B10,"CLASSIFICATION_LEVEL_4_NAME","CLASSIFICATION_SCHEME=BICS","SECURITY_NAME_LANG",$D$2)))} -> Communications Equipment | M10: {=IF($B10="","",IF(LEFT(_xlfn.SINGLE(_xll.BDP($B10,"CLASSIFICATION_LEVEL_5_CODE","CLASSIFICATION_SCHEME=BICS")),1)="#","",_xll.BDP($B10,"CLASSIFICATION_LEVEL_5_CODE","CLASSIFICATION_SCHEME=BICS")))} -> 1910101012 | N10: {=IF($B10="","",IF(LEFT(_xlfn.SINGLE(_xll.BDP($B10,"CLASSIFICATION_LEVEL_5_NAME","CLASSIFICATION_SCHEME=BICS")),1)="#","",_xll.BDP($B10,"CLASSIFICATION_LEVEL_5_NAME","CLASSIFICATION_SCHEME=BICS","SECURITY_NAME_LANG",$D$2)))} -> Mobile Phones | O10: {=IF($B10="","",IF(LEFT(_xlfn.SINGLE(_xll.BDP($B10,"CLASSIFICATION_LEVEL_6_CODE","CLASSIFICATION_SCHEME=BICS")),1)="#","",_xll.BDP($B10,"CLASSIFICATION_LEVEL_6_CODE","CLASSIFICATION_SCHEME=BICS")))} | P10: {=IF($B10="","",IF(LEFT(_xlfn.SINGLE(_xll.BDP($B10,"CLASSIFICATION_LEVEL_6_NAME","CLASSIFICATION_SCHEME=BICS")),1)="#","",_xll.BDP($B10,"CLASSIFICATION_LEVEL_6_NAME","CLASSIFICATION_SCHEME=BICS","SECURITY_NAME_LANG",$D$2)))} | Q10: {=IF($B10="","",IF(LEFT(_xlfn.SINGLE(_xll.BDP($B10,"CLASSIFICATION_LEVEL_7_CODE","CLASSIFICATION_SCHEME=BICS")),1)="#","",_xll.BDP($B10,"CLASSIFICATION_LEVEL_7_CODE","CLASSIFICATION_SCHEME=BICS")))} | R10: {=IF($B10="","",IF(LEFT(_xlfn.SINGLE(_xll.BDP($B10,"CLASSIFICATION_LEVEL_7_NAME","CLASSIFICATION_SCHEME=BICS")),1)="#","",_xll.BDP($B10,"CLASSIFICATION_LEVEL_7_NAME","CLASSIFICATION_SCHEME=BICS","SECURITY_NAME_LANG",$D$2)))}
B11: HD UN Equity | C11: {=IF($B11="","",_xll.BDP($B11,C$3))} -> 100743 | D11: {=IF($B11="","",_xll.BDP($B11,D$3,"SECURITY_NAME_LANG",$D$2))} -> Home Depot Inc/The | E11: {=IF($B11="","",IF(LEFT(_xlfn.SINGLE(_xll.BDP($B11,"CLASSIFICATION_LEVEL_1_CODE","CLASSIFICATION_SCHEME=BICS")),1)="#","",_xll.BDP($B11,"CLASSIFICATION_LEVEL_1_CODE","CLASSIFICATION_SCHEME=BICS")))} -> 11 | F11: {=IF($B11="","",IF(LEFT(_xlfn.SINGLE(_xll.BDP($B11,"CLASSIFICATION_LEVEL_1_NAME","CLASSIFICATION_SCHEME=BICS")),1)="#","",_xll.BDP($B11,"CLASSIFICATION_LEVEL_1_NAME","CLASSIFICATION_SCHEME=BICS","SECURITY_NAME_LANG",$D$2)))} -> Consumer Discretionary | G11: {=IF($B11="","",IF(LEFT(_xlfn.SINGLE(_xll.BDP($B11,"CLASSIFICATION_LEVEL_2_CODE","CLASSIFICATION_SCHEME=BICS")),1)="#","",_xll.BDP($B11,"CLASSIFICATION_LEVEL_2_CODE","CLASSIFICATION_SCHEME=BICS")))} -> 1112 | H11: {=IF($B11="","",IF(LEFT(_xlfn.SINGLE(_xll.BDP($B11,"CLASSIFICATION_LEVEL_2_NAME","CLASSIFICATION_SCHEME=BICS")),1)="#","",_xll.BDP($B11,"CLASSIFICATION_LEVEL_2_NAME","CLASSIFICATION_SCHEME=BICS","SECURITY_NAME_LANG",$D$2)))} -> Retail & Whsle - Discretionary | I11: {=IF($B11="","",IF(LEFT(_xlfn.SINGLE(_xll.BDP($B11,"CLASSIFICATION_LEVEL_3_CODE","CLASSIFICATION_SCHEME=BICS")),1)="#","",_xll.BDP($B11,"CLASSIFICATION_LEVEL_3_CODE","CLASSIFICATION_SCHEME=BICS")))} -> 111211 | J11: {=IF($B11="","",IF(LEFT(_xlfn.SINGLE(_xll.BDP($B11,"CLASSIFICATION_LEVEL_3_NAME","CLASSIFICATION_SCHEME=BICS")),1)="#","",_xll.BDP($B11,"CLASSIFICATION_LEVEL_3_NAME","CLASSIFICATION_SCHEME=BICS","SECURITY_NAME_LANG",$D$2)))} -> Retail - Discretionary | K11: {=IF($B11="","",IF(LEFT(_xlfn.SINGLE(_xll.BDP($B11,"CLASSIFICATION_LEVEL_4_CODE","CLASSIFICATION_SCHEME=BICS")),1)="#","",_xll.BDP($B11,"CLASSIFICATION_LEVEL_4_CODE","CLASSIFICATION_SCHEME=BICS")))} -> 11121114 | L11: {=IF($B11="","",IF(LEFT(_xlfn.SINGLE(_xll.BDP($B11,"CLASSIFICATION_LEVEL_4_NAME","CLASSIFICATION_SCHEME=BICS")),1)="#","",_xll.BDP($B11,"CLASSIFICATION_LEVEL_4_NAME","CLASSIFICATION_SCHEME=BICS","SECURITY_NAME_LANG",$D$2)))} -> Home Products Stores | M11: {=IF($B11="","",IF(LEFT(_xlfn.SINGLE(_xll.BDP($B11,"CLASSIFICATION_LEVEL_5_CODE","CLASSIFICATION_SCHEME=BICS")),1)="#","",_xll.BDP($B11,"CLASSIFICATION_LEVEL_5_CODE","CLASSIFICATION_SCHEME=BICS")))} -> 1112111411 | N11: {=IF($B11="","",IF(LEFT(_xlfn.SINGLE(_xll.BDP($B11,"CLASSIFICATION_LEVEL_5_NAME","CLASSIFICATION_SCHEME=BICS")),1)="#","",_xll.BDP($B11,"CLASSIFICATION_LEVEL_5_NAME","CLASSIFICATION_SCHEME=BICS","SECURITY_NAME_LANG",$D$2)))} -> Home Improvement Stores | O11: {=IF($B11="","",IF(LEFT(_xlfn.SINGLE(_xll.BDP($B11,"CLASSIFICATION_LEVEL_6_CODE","CLASSIFICATION_SCHEME=BICS")),1)="#","",_xll.BDP($B11,"CLASSIFICATION_LEVEL_6_CODE","CLASSIFICATION_SCHEME=BICS")))} -> 111211141111 | P11: {=IF($B11="","",IF(LEFT(_xlfn.SINGLE(_xll.BDP($B11,"CLASSIFICATION_LEVEL_6_NAME","CLASSIFICATION_SCHEME=BICS")),1)="#","",_xll.BDP($B11,"CLASSIFICATION_LEVEL_6_NAME","CLASSIFICATION_SCHEME=BICS","SECURITY_NAME_LANG",$D$2)))} -> Home Centers | Q11: {=IF($B11="","",IF(LEFT(_xlfn.SINGLE(_xll.BDP($B11,"CLASSIFICATION_LEVEL_7_CODE","CLASSIFICATION_SCHEME=BICS")),1)="#","",_xll.BDP($B11,"CLASSIFICATION_LEVEL_7_CODE","CLASSIFICATION_SCHEME=BICS")))} | R11: {=IF($B11="","",IF(LEFT(_xlfn.SINGLE(_xll.BDP($B11,"CLASSIFICATION_LEVEL_7_NAME","CLASSIFICATION_SCHEME=BICS")),1)="#","",_xll.BDP($B11,"CLASSIFICATION_LEVEL_7_NAME","CLASSIFICATION_SCHEME=BICS","SECURITY_NAME_LANG",$D$2)))}
B12: IBM UN Equity | C12: {=IF($B12="","",_xll.BDP($B12,C$3))} -> 100801 | D12: {=IF($B12="","",_xll.BDP($B12,D$3,"SECURITY_NAME_LANG",$D$2))} -> International Business Machine | E12: {=IF($B12="","",IF(LEFT(_xlfn.SINGLE(_xll.BDP($B12,"CLASSIFICATION_LEVEL_1_CODE","CLASSIFICATION_SCHEME=BICS")),1)="#","",_xll.BDP($B12,"CLASSIFICATION_LEVEL_1_CODE","CLASSIFICATION_SCHEME=BICS")))} -> 19 | F12: {=IF($B12="","",IF(LEFT(_xlfn.SINGLE(_xll.BDP($B12,"CLASSIFICATION_LEVEL_1_NAME","CLASSIFICATION_SCHEME=BICS")),1)="#","",_xll.BDP($B12,"CLASSIFICATION_LEVEL_1_NAME","CLASSIFICATION_SCHEME=BICS","SECURITY_NAME_LANG",$D$2)))} -> Technology | G12: {=IF($B12="","",IF(LEFT(_xlfn.SINGLE(_xll.BDP($B12,"CLASSIFICATION_LEVEL_2_CODE","CLASSIFICATION_SCHEME=BICS")),1)="#","",_xll.BDP($B12,"CLASSIFICATION_LEVEL_2_CODE","CLASSIFICATION_SCHEME=BICS")))} -> 1911 | H12: {=IF($B12="","",IF(LEFT(_xlfn.SINGLE(_xll.BDP($B12,"CLASSIFICATION_LEVEL_2_NAME","CLASSIFICATION_SCHEME=BICS")),1)="#","",_xll.BDP($B12,"CLASSIFICATION_LEVEL_2_NAME","CLASSIFICATION_SCHEME=BICS","SECURITY_NAME_LANG",$D$2)))} -> Software & Tech Services | I12: {=IF($B12="","",IF(LEFT(_xlfn.SINGLE(_xll.BDP($B12,"CLASSIFICATION_LEVEL_3_CODE","CLASSIFICATION_SCHEME=BICS")),1)="#","",_xll.BDP($B12,"CLASSIFICATION_LEVEL_3_CODE","CLASSIFICATION_SCHEME=BICS")))} -> 191111 | J12: {=IF($B12="","",IF(LEFT(_xlfn.SINGLE(_xll.BDP($B12,"CLASSIFICATION_LEVEL_3_NAME","CLASSIFICATION_SCHEME=BICS")),1)="#","",_xll.BDP($B12,"CLASSIFICATION_LEVEL_3_NAME","CLASSIFICATION_SCHEME=BICS","SECURITY_NAME_LANG",$D$2)))} -> IT Services | K12: {=IF($B12="","",IF(LEFT(_xlfn.SINGLE(_xll.BDP($B12,"CLASSIFICATION_LEVEL_4_CODE","CLASSIFICATION_SCHEME=BICS")),1)="#","",_xll.BDP($B12,"CLASSIFICATION_LEVEL_4_CODE","CLASSIFICATION_SCHEME=BICS")))} -> 19111110 | L12: {=IF($B12="","",IF(LEFT(_xlfn.SINGLE(_xll.BDP($B12,"CLASSIFICATION_LEVEL_4_NAME","CLASSIFICATION_SCHEME=BICS")),1)="#","",_xll.BDP($B12,"CLASSIFICATION_LEVEL_4_NAME","CLASSIFICATION_SCHEME=BICS","SECURITY_NAME_LANG",$D$2)))} -> IT Services | M12: {=IF($B12="","",IF(LEFT(_xlfn.SINGLE(_xll.BDP($B12,"CLASSIFICATION_LEVEL_5_CODE","CLASSIFICATION_SCHEME=BICS")),1)="#","",_xll.BDP($B12,"CLASSIFICATION_LEVEL_5_CODE","CLASSIFICATION_SCHEME=BICS")))} -> 1911111010 | N12: {=IF($B12="","",IF(LEFT(_xlfn.SINGLE(_xll.BDP($B12,"CLASSIFICATION_LEVEL_5_NAME","CLASSIFICATION_SCHEME=BICS")),1)="#","",_xll.BDP($B12,"CLASSIFICATION_LEVEL_5_NAME","CLASSIFICATION_SCHEME=BICS","SECURITY_NAME_LANG",$D$2)))} -> IT Services - Commercial | O12: {=IF($B12="","",IF(LEFT(_xlfn.SINGLE(_xll.BDP($B12,"CLASSIFICATION_LEVEL_6_CODE","CLASSIFICATION_SCHEME=BICS")),1)="#","",_xll.BDP($B12,"CLASSIFICATION_LEVEL_6_CODE","CLASSIFICATION_SCHEME=BICS")))} | P12: {=IF($B12="","",IF(LEFT(_xlfn.SINGLE(_xll.BDP($B12,"CLASSIFICATION_LEVEL_6_NAME","CLASSIFICATION_SCHEME=BICS")),1)="#","",_xll.BDP($B12,"CLASSIFICATION_LEVEL_6_NAME","CLASSIFICATION_SCHEME=BICS","SECURITY_NAME_LANG",$D$2)))} | Q12: {=IF($B12="","",IF(LEFT(_xlfn.SINGLE(_xll.BDP($B12,"CLASSIFICATION_LEVEL_7_CODE","CLASSIFICATION_SCHEME=BICS")),1)="#","",_xll.BDP($B12,"CLASSIFICATION_LEVEL_7_CODE","CLASSIFICATION_SCHEME=BICS")))} | R12: {=IF($B12="","",IF(LEFT(_xlfn.SINGLE(_xll.BDP($B12,"CLASSIFICATION_LEVEL_7_NAME","CLASSIFICATION_SCHEME=BICS")),1)="#","",_xll.BDP($B12,"CLASSIFICATION_LEVEL_7_NAME","CLASSIFICATION_SCHEME=BICS","SECURITY_NAME_LANG",$D$2)))}
B13: JNJ UN Equity | C13: {=IF($B13="","",_xll.BDP($B13,C$3))} -> 100828 | D13: {=IF($B13="","",_xll.BDP($B13,D$3,"SECURITY_NAME_LANG",$D$2))} -> Johnson & Johnson | E13: {=IF($B13="","",IF(LEFT(_xlfn.SINGLE(_xll.BDP($B13,"CLASSIFICATION_LEVEL_1_CODE","CLASSIFICATION_SCHEME=BICS")),1)="#","",_xll.BDP($B13,"CLASSIFICATION_LEVEL_1_CODE","CLASSIFICATION_SCHEME=BICS")))} -> 16 | F13: {=IF($B13="","",IF(LEFT(_xlfn.SINGLE(_xll.BDP($B13,"CLASSIFICATION_LEVEL_1_NAME","CLASSIFICATION_SCHEME=BICS")),1)="#","",_xll.BDP($B13,"CLASSIFICATION_LEVEL_1_NAME","CLASSIFICATION_SCHEME=BICS","SECURITY_NAME_LANG",$D$2)))} -> Health Care | G13: {=IF($B13="","",IF(LEFT(_xlfn.SINGLE(_xll.BDP($B13,"CLASSIFICATION_LEVEL_2_CODE","CLASSIFICATION_SCHEME=BICS")),1)="#","",_xll.BDP($B13,"CLASSIFICATION_LEVEL_2_CODE","CLASSIFICATION_SCHEME=BICS")))} -> 1610 | H13: {=IF($B13="","",IF(LEFT(_xlfn.SINGLE(_xll.BDP($B13,"CLASSIFICATION_LEVEL_2_NAME","CLASSIFICATION_SCHEME=BICS")),1)="#","",_xll.BDP($B13,"CLASSIFICATION_LEVEL_2_NAME","CLASSIFICATION_SCHEME=BICS","SECURITY_NAME_LANG",$D$2)))} -> Health Care | I13: {=IF($B13="","",IF(LEFT(_xlfn.SINGLE(_xll.BDP($B13,"CLASSIFICATION_LEVEL_3_CODE","CLASSIFICATION_SCHEME=BICS")),1)="#","",_xll.BDP($B13,"CLASSIFICATION_LEVEL_3_CODE","CLASSIFICATION_SCHEME=BICS")))} -> 161010 | J13: {=IF($B13="","",IF(LEFT(_xlfn.SINGLE(_xll.BDP($B13,"CLASSIFICATION_LEVEL_3_NAME","CLASSIFICATION_SCHEME=BICS")),1)="#","",_xll.BDP($B13,"CLASSIFICATION_LEVEL_3_NAME","CLASSIFICATION_SCHEME=BICS","SECURITY_NAME_LANG",$D$2)))} -> Biotech & Pharma | K13: {=IF($B13="","",IF(LEFT(_xlfn.SINGLE(_xll.BDP($B13,"CLASSIFICATION_LEVEL_4_CODE","CLASSIFICATION_SCHEME=BICS")),1)="#","",_xll.BDP($B13,"CLASSIFICATION_LEVEL_4_CODE","CLASSIFICATION_SCHEME=BICS")))} -> 16101010 | L13: {=IF($B13="","",IF(LEFT(_xlfn.SINGLE(_xll.BDP($B13,"CLASSIFICATION_LEVEL_4_NAME","CLASSIFICATION_SCHEME=BICS")),1)="#","",_xll.BDP($B13,"CLASSIFICATION_LEVEL_4_NAME","CLASSIFICATION_SCHEME=BICS","SECURITY_NAME_LANG",$D$2)))} -> Large Pharma | M13: {=IF($B13="","",IF(LEFT(_xlfn.SINGLE(_xll.BDP($B13,"CLASSIFICATION_LEVEL_5_CODE","CLASSIFICATION_SCHEME=BICS")),1)="#","",_xll.BDP($B13,"CLASSIFICATION_LEVEL_5_CODE","CLASSIFICATION_SCHEME=BICS")))} | N13: {=IF($B13="","",IF(LEFT(_xlfn.SINGLE(_xll.BDP($B13,"CLASSIFICATION_LEVEL_5_NAME","CLASSIFICATION_SCHEME=BICS")),1)="#","",_xll.BDP($B13,"CLASSIFICATION_LEVEL_5_NAME","CLASSIFICATION_SCHEME=BICS","SECURITY_NAME_LANG",$D$2)))} | O13: {=IF($B13="","",IF(LEFT(_xlfn.SINGLE(_xll.BDP($B13,"CLASSIFICATION_LEVEL_6_CODE","CLASSIFICATION_SCHEME=BICS")),1)="#","",_xll.BDP($B13,"CLASSIFICATION_LEVEL_6_CODE","CLASSIFICATION_SCHEME=BICS")))} | P13: {=IF($B13="","",IF(LEFT(_xlfn.SINGLE(_xll.BDP($B13,"CLASSIFICATION_LEVEL_6_NAME","CLASSIFICATION_SCHEME=BICS")),1)="#","",_xll.BDP($B13,"CLASSIFICATION_LEVEL_6_NAME","CLASSIFICATION_SCHEME=BICS","SECURITY_NAME_LANG",$D$2)))} | Q13: {=IF($B13="","",IF(LEFT(_xlfn.SINGLE(_xll.BDP($B13,"CLASSIFICATION_LEVEL_7_CODE","CLASSIFICATION_SCHEME=BICS")),1)="#","",_xll.BDP($B13,"CLASSIFICATION_LEVEL_7_CODE","CLASSIFICATION_SCHEME=BICS")))} | R13: {=IF($B13="","",IF(LEFT(_xlfn.SINGLE(_xll.BDP($B13,"CLASSIFICATION_LEVEL_7_NAME","CLASSIFICATION_SCHEME=BICS")),1)="#","",_xll.BDP($B13,"CLASSIFICATION_LEVEL_7_NAME","CLASSIFICATION_SCHEME=BICS","SECURITY_NAME_LANG",$D$2)))}
B14: TRV UN Equity | C14: {=IF($B14="","",_xll.BDP($B14,C$3))} -> 101388 | D14: {=IF($B14="","",_xll.BDP($B14,D$3,"SECURITY_NAME_LANG",$D$2))} -> Travelers Cos Inc/The | E14: {=IF($B14="","",IF(LEFT(_xlfn.SINGLE(_xll.BDP($B14,"CLASSIFICATION_LEVEL_1_CODE","CLASSIFICATION_SCHEME=BICS")),1)="#","",_xll.BDP($B14,"CLASSIFICATION_LEVEL_1_CODE","CLASSIFICATION_SCHEME=BICS")))} -> 14 | F14: {=IF($B14="","",IF(LEFT(_xlfn.SINGLE(_xll.BDP($B14,"CLASSIFICATION_LEVEL_1_NAME","CLASSIFICATION_SCHEME=BICS")),1)="#","",_xll.BDP($B14,"CLASSIFICATION_LEVEL_1_NAME","CLASSIFICATION_SCHEME=BICS","SECURITY_NAME_LANG",$D$2)))} -> Financials | G14: {=IF($B14="","",IF(LEFT(_xlfn.SINGLE(_xll.BDP($B14,"CLASSIFICATION_LEVEL_2_CODE","CLASSIFICATION_SCHEME=BICS")),1)="#","",_xll.BDP($B14,"CLASSIFICATION_LEVEL_2_CODE","CLASSIFICATION_SCHEME=BICS")))} -> 1412 | H14: {=IF($B14="","",IF(LEFT(_xlfn.SINGLE(_xll.BDP($B14,"CLASSIFICATION_LEVEL_2_NAME","CLASSIFICATION_SCHEME=BICS")),1)="#","",_xll.BDP($B14,"CLASSIFICATION_LEVEL_2_NAME","CLASSIFICATION_SCHEME=BICS","SECURITY_NAME_LANG",$D$2)))} -> Insurance | I14: {=IF($B14="","",IF(LEFT(_xlfn.SINGLE(_xll.BDP($B14,"CLASSIFICATION_LEVEL_3_CODE","CLASSIFICATION_SCHEME=BICS")),1)="#","",_xll.BDP($B14,"CLASSIFICATION_LEVEL_3_CODE","CLASSIFICATION_SCHEME=BICS")))} -> 141210 | J14: {=IF($B14="","",IF(LEFT(_xlfn.SINGLE(_xll.BDP($B14,"CLASSIFICATION_LEVEL_3_NAME","CLASSIFICATION_SCHEME=BICS")),1)="#","",_xll.BDP($B14,"CLASSIFICATION_LEVEL_3_NAME","CLASSIFICATION_SCHEME=BICS","SECURITY_NAME_LANG",$D$2)))} -> Insurance | K14: {=IF($B14="","",IF(LEFT(_xlfn.SINGLE(_xll.BDP($B14,"CLASSIFICATION_LEVEL_4_CODE","CLASSIFICATION_SCHEME=BICS")),1)="#","",_xll.BDP($B14,"CLASSIFICATION_LEVEL_4_CODE","CLASSIFICATION_SCHEME=BICS")))} -> 14121011 | L14: {=IF($B14="","",IF(LEFT(_xlfn.SINGLE(_xll.BDP($B14,"CLASSIFICATION_LEVEL_4_NAME","CLASSIFICATION_SCHEME=BICS")),1)="#","",_xll.BDP($B14,"CLASSIFICATION_LEVEL_4_NAME","CLASSIFICATION_SCHEME=BICS","SECURITY_NAME_LANG",$D$2)))} -> P&C Insurance | M14: {=IF($B14="","",IF(LEFT(_xlfn.SINGLE(_xll.BDP($B14,"CLASSIFICATION_LEVEL_5_CODE","CLASSIFICATION_SCHEME=BICS")),1)="#","",_xll.BDP($B14,"CLASSIFICATION_LEVEL_5_CODE","CLASSIFICATION_SCHEME=BICS")))} -> 1412101110 | N14: {=IF($B14="","",IF(LEFT(_xlfn.SINGLE(_xll.BDP($B14,"CLASSIFICATION_LEVEL_5_NAME","CLASSIFICATION_SCHEME=BICS")),1)="#","",_xll.BDP($B14,"CLASSIFICATION_LEVEL_5_NAME","CLASSIFICATION_SCHEME=BICS","SECURITY_NAME_LANG",$D$2)))} -> P&C Insurance Premiums | O14: {=IF($B14="","",IF(LEFT(_xlfn.SINGLE(_xll.BDP($B14,"CLASSIFICATION_LEVEL_6_CODE","CLASSIFICATION_SCHEME=BICS")),1)="#","",_xll.BDP($B14,"CLASSIFICATION_LEVEL_6_CODE","CLASSIFICATION_SCHEME=BICS")))} | P14: {=IF($B14="","",IF(LEFT(_xlfn.SINGLE(_xll.BDP($B14,"CLASSIFICATION_LEVEL_6_NAME","CLASSIFICATION_SCHEME=BICS")),1)="#","",_xll.BDP($B14,"CLASSIFICATION_LEVEL_6_NAME","CLASSIFICATION_SCHEME=BICS","SECURITY_NAME_LANG",$D$2)))} | Q14: {=IF($B14="","",IF(LEFT(_xlfn.SINGLE(_xll.BDP($B14,"CLASSIFICATION_LEVEL_7_CODE","CLASSIFICATION_SCHEME=BICS")),1)="#","",_xll.BDP($B14,"CLASSIFICATION_LEVEL_7_CODE","CLASSIFICATION_SCHEME=BICS")))} | R14: {=IF($B14="","",IF(LEFT(_xlfn.SINGLE(_xll.BDP($B14,"CLASSIFICATION_LEVEL_7_NAME","CLASSIFICATION_SCHEME=BICS")),1)="#","",_xll.BDP($B14,"CLASSIFICATION_LEVEL_7_NAME","CLASSIFICATION_SCHEME=BICS","SECURITY_NAME_LANG",$D$2)))}
B15: UTX UN Equity | C15: {=IF($B15="","",_xll.BDP($B15,C$3))} -> 72600253 | D15: {=IF($B15="","",_xll.BDP($B15,D$3,"SECURITY_NAME_LANG",$D$2))} -> Ultratrex Inc | E15: {=IF($B15="","",IF(LEFT(_xlfn.SINGLE(_xll.BDP($B15,"CLASSIFICATION_LEVEL_1_CODE","CLASSIFICATION_SCHEME=BICS")),1)="#","",_xll.BDP($B15,"CLASSIFICATION_LEVEL_1_CODE","CLASSIFICATION_SCHEME=BICS")))} -> 17 | F15: {=IF($B15="","",IF(LEFT(_xlfn.SINGLE(_xll.BDP($B15,"CLASSIFICATION_LEVEL_1_NAME","CLASSIFICATION_SCHEME=BICS")),1)="#","",_xll.BDP($B15,"CLASSIFICATION_LEVEL_1_NAME","CLASSIFICATION_SCHEME=BICS","SECURITY_NAME_LANG",$D$2)))} -> Industrials | G15: {=IF($B15="","",IF(LEFT(_xlfn.SINGLE(_xll.BDP($B15,"CLASSIFICATION_LEVEL_2_CODE","CLASSIFICATION_SCHEME=BICS")),1)="#","",_xll.BDP($B15,"CLASSIFICATION_LEVEL_2_CODE","CLASSIFICATION_SCHEME=BICS")))} -> 1710 | H15: {=IF($B15="","",IF(LEFT(_xlfn.SINGLE(_xll.BDP($B15,"CLASSIFICATION_LEVEL_2_NAME","CLASSIFICATION_SCHEME=BICS")),1)="#","",_xll.BDP($B15,"CLASSIFICATION_LEVEL_2_NAME","CLASSIFICATION_SCHEME=BICS","SECURITY_NAME_LANG",$D$2)))} -> Industrial Products | I15: {=IF($B15="","",IF(LEFT(_xlfn.SINGLE(_xll.BDP($B15,"CLASSIFICATION_LEVEL_3_CODE","CLASSIFICATION_SCHEME=BICS")),1)="#","",_xll.BDP($B15,"CLASSIFICATION_LEVEL_3_CODE","CLASSIFICATION_SCHEME=BICS")))} -> 171013 | J15: {=IF($B15="","",IF(LEFT(_xlfn.SINGLE(_xll.BDP($B15,"CLASSIFICATION_LEVEL_3_NAME","CLASSIFICATION_SCHEME=BICS")),1)="#","",_xll.BDP($B15,"CLASSIFICATION_LEVEL_3_NAME","CLASSIFICATION_SCHEME=BICS","SECURITY_NAME_LANG",$D$2)))} -> Machinery | K15: {=IF($B15="","",IF(LEFT(_xlfn.SINGLE(_xll.BDP($B15,"CLASSIFICATION_LEVEL_4_CODE","CLASSIFICATION_SCHEME=BICS")),1)="#","",_xll.BDP($B15,"CLASSIFICATION_LEVEL_4_CODE","CLASSIFICATION_SCHEME=BICS")))} -> 17101311 | L15: {=IF($B15="","",IF(LEFT(_xlfn.SINGLE(_xll.BDP($B15,"CLASSIFICATION_LEVEL_4_NAME","CLASSIFICATION_SCHEME=BICS")),1)="#","",_xll.BDP($B15,"CLASSIFICATION_LEVEL_4_NAME","CLASSIFICATION_SCHEME=BICS","SECURITY_NAME_LANG",$D$2)))} -> Construction & Mining Machinery | M15: {=IF($B15="","",IF(LEFT(_xlfn.SINGLE(_xll.BDP($B15,"CLASSIFICATION_LEVEL_5_CODE","CLASSIFICATION_SCHEME=BICS")),1)="#","",_xll.BDP($B15,"CLASSIFICATION_LEVEL_5_CODE","CLASSIFICATION_SCHEME=BICS")))} -> 1710131110 | N15: {=IF($B15="","",IF(LEFT(_xlfn.SINGLE(_xll.BDP($B15,"CLASSIFICATION_LEVEL_5_NAME","CLASSIFICATION_SCHEME=BICS")),1)="#","",_xll.BDP($B15,"CLASSIFICATION_LEVEL_5_NAME","CLASSIFICATION_SCHEME=BICS","SECURITY_NAME_LANG",$D$2)))} -> Construction Machinery | O15: {=IF($B15="","",IF(LEFT(_xlfn.SINGLE(_xll.BDP($B15,"CLASSIFICATION_LEVEL_6_CODE","CLASSIFICATION_SCHEME=BICS")),1)="#","",_xll.BDP($B15,"CLASSIFICATION_LEVEL_6_CODE","CLASSIFICATION_SCHEME=BICS")))} | P15: {=IF($B15="","",IF(LEFT(_xlfn.SINGLE(_xll.BDP($B15,"CLASSIFICATION_LEVEL_6_NAME","CLASSIFICATION_SCHEME=BICS")),1)="#","",_xll.BDP($B15,"CLASSIFICATION_LEVEL_6_NAME","CLASSIFICATION_SCHEME=BICS","SECURITY_NAME_LANG",$D$2)))} | Q15: {=IF($B15="","",IF(LEFT(_xlfn.SINGLE(_xll.BDP($B15,"CLASSIFICATION_LEVEL_7_CODE","CLASSIFICATION_SCHEME=BICS")),1)="#","",_xll.BDP($B15,"CLASSIFICATION_LEVEL_7_CODE","CLASSIFICATION_SCHEME=BICS")))} | R15: {=IF($B15="","",IF(LEFT(_xlfn.SINGLE(_xll.BDP($B15,"CLASSIFICATION_LEVEL_7_NAME","CLASSIFICATION_SCHEME=BICS")),1)="#","",_xll.BDP($B15,"CLASSIFICATION_LEVEL_7_NAME","CLASSIFICATION_SCHEME=BICS","SECURITY_NAME_LANG",$D$2)))}
B16: DIS UN Equity | C16: {=IF($B16="","",_xll.BDP($B16,C$3))} -> 60854400 | D16: {=IF($B16="","",_xll.BDP($B16,D$3,"SECURITY_NAME_LANG",$D$2))} -> Walt Disney Co/The | E16: {=IF($B16="","",IF(LEFT(_xlfn.SINGLE(_xll.BDP($B16,"CLASSIFICATION_LEVEL_1_CODE","CLASSIFICATION_SCHEME=BICS")),1)="#","",_xll.BDP($B16,"CLASSIFICATION_LEVEL_1_CODE","CLASSIFICATION_SCHEME=BICS")))} -> 10 | F16: {=IF($B16="","",IF(LEFT(_xlfn.SINGLE(_xll.BDP($B16,"CLASSIFICATION_LEVEL_1_NAME","CLASSIFICATION_SCHEME=BICS")),1)="#","",_xll.BDP($B16,"CLASSIFICATION_LEVEL_1_NAME","CLASSIFICATION_SCHEME=BICS","SECURITY_NAME_LANG",$D$2)))} -> Communications | G16: {=IF($B16="","",IF(LEFT(_xlfn.SINGLE(_xll.BDP($B16,"CLASSIFICATION_LEVEL_2_CODE","CLASSIFICATION_SCHEME=BICS")),1)="#","",_xll.BDP($B16,"CLASSIFICATION_LEVEL_2_CODE","CLASSIFICATION_SCHEME=BICS")))} -> 1010 | H16: {=IF($B16="","",IF(LEFT(_xlfn.SINGLE(_xll.BDP($B16,"CLASSIFICATION_LEVEL_2_NAME","CLASSIFICATION_SCHEME=BICS")),1)="#","",_xll.BDP($B16,"CLASSIFICATION_LEVEL_2_NAME","CLASSIFICATION_SCHEME=BICS","SECURITY_NAME_LANG",$D$2)))} -> Media | I16: {=IF($B16="","",IF(LEFT(_xlfn.SINGLE(_xll.BDP($B16,"CLASSIFICATION_LEVEL_3_CODE","CLASSIFICATION_SCHEME=BICS")),1)="#","",_xll.BDP($B16,"CLASSIFICATION_LEVEL_3_CODE","CLASSIFICATION_SCHEME=BICS")))} -> 101012 | J16: {=IF($B16="","",IF(LEFT(_xlfn.SINGLE(_xll.BDP($B16,"CLASSIFICATION_LEVEL_3_NAME","CLASSIFICATION_SCHEME=BICS")),1)="#","",_xll.BDP($B16,"CLASSIFICATION_LEVEL_3_NAME","CLASSIFICATION_SCHEME=BICS","SECURITY_NAME_LANG",$D$2)))} -> Entertainment Content | K16: {=IF($B16="","",IF(LEFT(_xlfn.SINGLE(_xll.BDP($B16,"CLASSIFICATION_LEVEL_4_CODE","CLASSIFICATION_SCHEME=BICS")),1)="#","",_xll.BDP($B16,"CLASSIFICATION_LEVEL_4_CODE","CLASSIFICATION_SCHEME=BICS")))} -> 10101210 | L16: {=IF($B16="","",IF(LEFT(_xlfn.SINGLE(_xll.BDP($B16,"CLASSIFICATION_LEVEL_4_NAME","CLASSIFICATION_SCHEME=BICS")),1)="#","",_xll.BDP($B16,"CLASSIFICATION_LEVEL_4_NAME","CLASSIFICATION_SCHEME=BICS","SECURITY_NAME_LANG",$D$2)))} -> Film & TV | M16: {=IF($B16="","",IF(LEFT(_xlfn.SINGLE(_xll.BDP($B16,"CLASSIFICATION_LEVEL_5_CODE","CLASSIFICATION_SCHEME=BICS")),1)="#","",_xll.BDP($B16,"CLASSIFICATION_LEVEL_5_CODE","CLASSIFICATION_SCHEME=BICS")))} -> 1010121011 | N16: {=IF($B16="","",IF(LEFT(_xlfn.SINGLE(_xll.BDP($B16,"CLASSIFICATION_LEVEL_5_NAME","CLASSIFICATION_SCHEME=BICS")),1)="#","",_xll.BDP($B16,"CLASSIFICATION_LEVEL_5_NAME","CLASSIFICATION_SCHEME=BICS","SECURITY_NAME_LANG",$D$2)))} -> TV Media Networks | O16: {=IF($B16="","",IF(LEFT(_xlfn.SINGLE(_xll.BDP($B16,"CLASSIFICATION_LEVEL_6_CODE","CLASSIFICATION_SCHEME=BICS")),1)="#","",_xll.BDP($B16,"CLASSIFICATION_LEVEL_6_CODE","CLASSIFICATION_SCHEME=BICS")))} | P16: {=IF($B16="","",IF(LEFT(_xlfn.SINGLE(_xll.BDP($B16,"CLASSIFICATION_LEVEL_6_NAME","CLASSIFICATION_SCHEME=BICS")),1)="#","",_xll.BDP($B16,"CLASSIFICATION_LEVEL_6_NAME","CLASSIFICATION_SCHEME=BICS","SECURITY_NAME_LANG",$D$2)))} | Q16: {=IF($B16="","",IF(LEFT(_xlfn.SINGLE(_xll.BDP($B16,"CLASSIFICATION_LEVEL_7_CODE","CLASSIFICATION_SCHEME=BICS")),1)="#","",_xll.BDP($B16,"CLASSIFICATION_LEVEL_7_CODE","CLASSIFICATION_SCHEME=BICS")))} | R16: {=IF($B16="","",IF(LEFT(_xlfn.SINGLE(_xll.BDP($B16,"CLASSIFICATION_LEVEL_7_NAME","CLASSIFICATION_SCHEME=BICS")),1)="#","",_xll.BDP($B16,"CLASSIFICATION_LEVEL_7_NAME","CLASSIFICATION_SCHEME=BICS","SECURITY_NAME_LANG",$D$2)))}
... B34: IBM US Equity | C34: {=IF($B34="","",_xll.BDP($B34,C$3))} -> 100801 | D34: {=IF($B34="","",_xll.BDP($B34,D$3,"SECURITY_NAME_LANG",$D$2))} -> International Business Machine | E34: {=IF($B34="","",IF(LEFT(_xlfn.SINGLE(_xll.BDP($B34,"CLASSIFICATION_LEVEL_1_CODE","CLASSIFICATION_SCHEME=BICS")),1)="#","",_xll.BDP($B34,"CLASSIFICATION_LEVEL_1_CODE","CLASSIFICATION_SCHEME=BICS")))} -> 19 | F34: {=IF($B34="","",IF(LEFT(_xlfn.SINGLE(_xll.BDP($B34,"CLASSIFICATION_LEVEL_1_NAME","CLASSIFICATION_SCHEME=BICS")),1)="#","",_xll.BDP($B34,"CLASSIFICATION_LEVEL_1_NAME","CLASSIFICATION_SCHEME=BICS","SECURITY_NAME_LANG",$D$2)))} -> Technology | G34: {=IF($B34="","",IF(LEFT(_xlfn.SINGLE(_xll.BDP($B34,"CLASSIFICATION_LEVEL_2_CODE","CLASSIFICATION_SCHEME=BICS")),1)="#","",_xll.BDP($B34,"CLASSIFICATION_LEVEL_2_CODE","CLASSIFICATION_SCHEME=BICS")))} -> 1911 | H34: {=IF($B34="","",IF(LEFT(_xlfn.SINGLE(_xll.BDP($B34,"CLASSIFICATION_LEVEL_2_NAME","CLASSIFICATION_SCHEME=BICS")),1)="#","",_xll.BDP($B34,"CLASSIFICATION_LEVEL_2_NAME","CLASSIFICATION_SCHEME=BICS","SECURITY_NAME_LANG",$D$2)))} -> Software & Tech Services | I34: {=IF($B34="","",IF(LEFT(_xlfn.SINGLE(_xll.BDP($B34,"CLASSIFICATION_LEVEL_3_CODE","CLASSIFICATION_SCHEME=BICS")),1)="#","",_xll.BDP($B34,"CLASSIFICATION_LEVEL_3_CODE","CLASSIFICATION_SCHEME=BICS")))} -> 191111 | J34: {=IF($B34="","",IF(LEFT(_xlfn.SINGLE(_xll.BDP($B34,"CLASSIFICATION_LEVEL_3_NAME","CLASSIFICATION_SCHEME=BICS")),1)="#","",_xll.BDP($B34,"CLASSIFICATION_LEVEL_3_NAME","CLASSIFICATION_SCHEME=BICS","SECURITY_NAME_LANG",$D$2)))} -> IT Services | K34: {=IF($B34="","",IF(LEFT(_xlfn.SINGLE(_xll.BDP($B34,"CLASSIFICATION_LEVEL_4_CODE","CLASSIFICATION_SCHEME=BICS")),1)="#","",_xll.BDP($B34,"CLASSIFICATION_LEVEL_4_CODE","CLASSIFICATION_SCHEME=BICS")))} -> 19111110 | L34: {=IF($B34="","",IF(LEFT(_xlfn.SINGLE(_xll.BDP($B34,"CLASSIFICATION_LEVEL_4_NAME","CLASSIFICATION_SCHEME=BICS")),1)="#","",_xll.BDP($B34,"CLASSIFICATION_LEVEL_4_NAME","CLASSIFICATION_SCHEME=BICS","SECURITY_NAME_LANG",$D$2)))} -> IT Services | M34: {=IF($B34="","",IF(LEFT(_xlfn.SINGLE(_xll.BDP($B34,"CLASSIFICATION_LEVEL_5_CODE","CLASSIFICATION_SCHEME=BICS")),1)="#","",_xll.BDP($B34,"CLASSIFICATION_LEVEL_5_CODE","CLASSIFICATION_SCHEME=BICS")))} -> 1911111010 | N34: {=IF($B34="","",IF(LEFT(_xlfn.SINGLE(_xll.BDP($B34,"CLASSIFICATION_LEVEL_5_NAME","CLASSIFICATION_SCHEME=BICS")),1)="#","",_xll.BDP($B34,"CLASSIFICATION_LEVEL_5_NAME","CLASSIFICATION_SCHEME=BICS","SECURITY_NAME_LANG",$D$2)))} -> IT Services - Commercial | O34: {=IF($B34="","",IF(LEFT(_xlfn.SINGLE(_xll.BDP($B34,"CLASSIFICATION_LEVEL_6_CODE","CLASSIFICATION_SCHEME=BICS")),1)="#","",_xll.BDP($B34,"CLASSIFICATION_LEVEL_6_CODE","CLASSIFICATION_SCHEME=BICS")))} | P34: {=IF($B34="","",IF(LEFT(_xlfn.SINGLE(_xll.BDP($B34,"CLASSIFICATION_LEVEL_6_NAME","CLASSIFICATION_SCHEME=BICS")),1)="#","",_xll.BDP($B34,"CLASSIFICATION_LEVEL_6_NAME","CLASSIFICATION_SCHEME=BICS","SECURITY_NAME_LANG",$D$2)))} | Q34: {=IF($B34="","",IF(LEFT(_xlfn.SINGLE(_xll.BDP($B34,"CLASSIFICATION_LEVEL_7_CODE","CLASSIFICATION_SCHEME=BICS")),1)="#","",_xll.BDP($B34,"CLASSIFICATION_LEVEL_7_CODE","CLASSIFICATION_SCHEME=BICS")))} | R34: {=IF($B34="","",IF(LEFT(_xlfn.SINGLE(_xll.BDP($B34,"CLASSIFICATION_LEVEL_7_NAME","CLASSIFICATION_SCHEME=BICS")),1)="#","",_xll.BDP($B34,"CLASSIFICATION_LEVEL_7_NAME","CLASSIFICATION_SCHEME=BICS","SECURITY_NAME_LANG",$D$2)))}
C35: =IF($B35="","",_xll.BDP($B35,C$3)) | D35: =IF($B35="","",_xll.BDP($B35,D$3,"SECURITY_NAME_LANG",$D$2)) | E35: =IF($B35="","",IF(LEFT(_xll.BDP($B35,"CLASSIFICATION_LEVEL_1_CODE","CLASSIFICATION_SCHEME=BICS"),1)="#","",_xll.BDP($B35,"CLASSIFICATION_LEVEL_1_CODE","CLASSIFICATION_SCHEME=BICS"))) | F35: =IF($B35="","",IF(LEFT(_xll.BDP($B35,"CLASSIFICATION_LEVEL_1_NAME","CLASSIFICATION_SCHEME=BICS"),1)="#","",_xll.BDP($B35,"CLASSIFICATION_LEVEL_1_NAME","CLASSIFICATION_SCHEME=BICS","SECURITY_NAME_LANG",$D$2))) | G35: =IF($B35="","",IF(LEFT(_xll.BDP($B35,"CLASSIFICATION_LEVEL_2_CODE","CLASSIFICATION_SCHEME=BICS"),1)="#","",_xll.BDP($B35,"CLASSIFICATION_LEVEL_2_CODE","CLASSIFICATION_SCHEME=BICS"))) | H35: =IF($B35="","",IF(LEFT(_xll.BDP($B35,"CLASSIFICATION_LEVEL_2_NAME","CLASSIFICATION_SCHEME=BICS"),1)="#","",_xll.BDP($B35,"CLASSIFICATION_LEVEL_2_NAME","CLASSIFICATION_SCHEME=BICS","SECURITY_NAME_LANG",$D$2))) | I35: =IF($B35="","",IF(LEFT(_xll.BDP($B35,"CLASSIFICATION_LEVEL_3_CODE","CLASSIFICATION_SCHEME=BICS"),1)="#","",_xll.BDP($B35,"CLASSIFICATION_LEVEL_3_CODE","CLASSIFICATION_SCHEME=BICS"))) | J35: =IF($B35="","",IF(LEFT(_xll.BDP($B35,"CLASSIFICATION_LEVEL_3_NAME","CLASSIFICATION_SCHEME=BICS"),1)="#","",_xll.BDP($B35,"CLASSIFICATION_LEVEL_3_NAME","CLASSIFICATION_SCHEME=BICS","SECURITY_NAME_LANG",$D$2))) | K35: =IF($B35="","",IF(LEFT(_xll.BDP($B35,"CLASSIFICATION_LEVEL_4_CODE","CLASSIFICATION_SCHEME=BICS"),1)="#","",_xll.BDP($B35,"CLASSIFICATION_LEVEL_4_CODE","CLASSIFICATION_SCHEME=BICS"))) | L35: =IF($B35="","",IF(LEFT(_xll.BDP($B35,"CLASSIFICATION_LEVEL_4_NAME","CLASSIFICATION_SCHEME=BICS"),1)="#","",_xll.BDP($B35,"CLASSIFICATION_LEVEL_4_NAME","CLASSIFICATION_SCHEME=BICS","SECURITY_NAME_LANG",$D$2))) | M35: =IF($B35="","",IF(LEFT(_xll.BDP($B35,"CLASSIFICATION_LEVEL_5_CODE","CLASSIFICATION_SCHEME=BICS"),1)="#","",_xll.BDP($B35,"CLASSIFICATION_LEVEL_5_CODE","CLASSIFICATION_SCHEME=BICS"))) | N35: =IF($B35="","",IF(LEFT(_xll.BDP($B35,"CLASSIFICATION_LEVEL_5_NAME","CLASSIFICATION_SCHEME=BICS"),1)="#","",_xll.BDP($B35,"CLASSIFICATION_LEVEL_5_NAME","CLASSIFICATION_SCHEME=BICS","SECURITY_NAME_LANG",$D$2))) | O35: =IF($B35="","",IF(LEFT(_xll.BDP($B35,"CLASSIFICATION_LEVEL_6_CODE","CLASSIFICATION_SCHEME=BICS"),1)="#","",_xll.BDP($B35,"CLASSIFICATION_LEVEL_6_CODE","CLASSIFICATION_SCHEME=BICS"))) | P35: =IF($B35="","",IF(LEFT(_xll.BDP($B35,"CLASSIFICATION_LEVEL_6_NAME","CLASSIFICATION_SCHEME=BICS"),1)="#","",_xll.BDP($B35,"CLASSIFICATION_LEVEL_6_NAME","CLASSIFICATION_SCHEME=BICS","SECURITY_NAME_LANG",$D$2))) | Q35: =IF($B35="","",IF(LEFT(_xll.BDP($B35,"CLASSIFICATION_LEVEL_7_CODE","CLASSIFICATION_SCHEME=BICS"),1)="#","",_xll.BDP($B35,"CLASSIFICATION_LEVEL_7_CODE","CLASSIFICATION_SCHEME=BICS"))) | R35: =IF($B35="","",IF(LEFT(_xll.BDP($B35,"CLASSIFICATION_LEVEL_7_NAME","CLASSIFICATION_SCHEME=BICS"),1)="#","",_xll.BDP($B35,"CLASSIFICATION_LEVEL_7_NAME","CLASSIFICATION_SCHEME=BICS","SECURITY_NAME_LANG",$D$2)))
C36: =IF($B36="","",_xll.BDP($B36,C$3)) | D36: =IF($B36="","",_xll.BDP($B36,D$3,"SECURITY_NAME_LANG",$D$2)) | E36: =IF($B36="","",IF(LEFT(_xll.BDP($B36,"CLASSIFICATION_LEVEL_1_CODE","CLASSIFICATION_SCHEME=BICS"),1)="#","",_xll.BDP($B36,"CLASSIFICATION_LEVEL_1_CODE","CLASSIFICATION_SCHEME=BICS"))) | F36: =IF($B36="","",IF(LEFT(_xll.BDP($B36,"CLASSIFICATION_LEVEL_1_NAME","CLASSIFICATION_SCHEME=BICS"),1)="#","",_xll.BDP($B36,"CLASSIFICATION_LEVEL_1_NAME","CLASSIFICATION_SCHEME=BICS","SECURITY_NAME_LANG",$D$2))) | G36: =IF($B36="","",IF(LEFT(_xll.BDP($B36,"CLASSIFICATION_LEVEL_2_CODE","CLASSIFICATION_SCHEME=BICS"),1)="#","",_xll.BDP($B36,"CLASSIFICATION_LEVEL_2_CODE","CLASSIFICATION_SCHEME=BICS"))) | H36: =IF($B36="","",IF(LEFT(_xll.BDP($B36,"CLASSIFICATION_LEVEL_2_NAME","CLASSIFICATION_SCHEME=BICS"),1)="#","",_xll.BDP($B36,"CLASSIFICATION_LEVEL_2_NAME","CLASSIFICATION_SCHEME=BICS","SECURITY_NAME_LANG",$D$2))) | I36: =IF($B36="","",IF(LEFT(_xll.BDP($B36,"CLASSIFICATION_LEVEL_3_CODE","CLASSIFICATION_SCHEME=BICS"),1)="#","",_xll.BDP($B36,"CLASSIFICATION_LEVEL_3_CODE","CLASSIFICATION_SCHEME=BICS"))) | J36: =IF($B36="","",IF(LEFT(_xll.BDP($B36,"CLASSIFICATION_LEVEL_3_NAME","CLASSIFICATION_SCHEME=BICS"),1)="#","",_xll.BDP($B36,"CLASSIFICATION_LEVEL_3_NAME","CLASSIFICATION_SCHEME=BICS","SECURITY_NAME_LANG",$D$2))) | K36: =IF($B36="","",IF(LEFT(_xll.BDP($B36,"CLASSIFICATION_LEVEL_4_CODE","CLASSIFICATION_SCHEME=BICS"),1)="#","",_xll.BDP($B36,"CLASSIFICATION_LEVEL_4_CODE","CLASSIFICATION_SCHEME=BICS"))) | L36: =IF($B36="","",IF(LEFT(_xll.BDP($B36,"CLASSIFICATION_LEVEL_4_NAME","CLASSIFICATION_SCHEME=BICS"),1)="#","",_xll.BDP($B36,"CLASSIFICATION_LEVEL_4_NAME","CLASSIFICATION_SCHEME=BICS","SECURITY_NAME_LANG",$D$2))) | M36: =IF($B36="","",IF(LEFT(_xll.BDP($B36,"CLASSIFICATION_LEVEL_5_CODE","CLASSIFICATION_SCHEME=BICS"),1)="#","",_xll.BDP($B36,"CLASSIFICATION_LEVEL_5_CODE","CLASSIFICATION_SCHEME=BICS"))) | N36: =IF($B36="","",IF(LEFT(_xll.BDP($B36,"CLASSIFICATION_LEVEL_5_NAME","CLASSIFICATION_SCHEME=BICS"),1)="#","",_xll.BDP($B36,"CLASSIFICATION_LEVEL_5_NAME","CLASSIFICATION_SCHEME=BICS","SECURITY_NAME_LANG",$D$2))) | O36: =IF($B36="","",IF(LEFT(_xll.BDP($B36,"CLASSIFICATION_LEVEL_6_CODE","CLASSIFICATION_SCHEME=BICS"),1)="#","",_xll.BDP($B36,"CLASSIFICATION_LEVEL_6_CODE","CLASSIFICATION_SCHEME=BICS"))) | P36: =IF($B36="","",IF(LEFT(_xll.BDP($B36,"CLASSIFICATION_LEVEL_6_NAME","CLASSIFICATION_SCHEME=BICS"),1)="#","",_xll.BDP($B36,"CLASSIFICATION_LEVEL_6_NAME","CLASSIFICATION_SCHEME=BICS","SECURITY_NAME_LANG",$D$2))) | Q36: =IF($B36="","",IF(LEFT(_xll.BDP($B36,"CLASSIFICATION_LEVEL_7_CODE","CLASSIFICATION_SCHEME=BICS"),1)="#","",_xll.BDP($B36,"CLASSIFICATION_LEVEL_7_CODE","CLASSIFICATION_SCHEME=BICS"))) | R36: =IF($B36="","",IF(LEFT(_xll.BDP($B36,"CLASSIFICATION_LEVEL_7_NAME","CLASSIFICATION_SCHEME=BICS"),1)="#","",_xll.BDP($B36,"CLASSIFICATION_LEVEL_7_NAME","CLASSIFICATION_SCHEME=BICS","SECURITY_NAME_LANG",$D$2)))
C37: =IF($B37="","",_xll.BDP($B37,C$3)) | D37: =IF($B37="","",_xll.BDP($B37,D$3,"SECURITY_NAME_LANG",$D$2)) | E37: =IF($B37="","",IF(LEFT(_xll.BDP($B37,"CLASSIFICATION_LEVEL_1_CODE","CLASSIFICATION_SCHEME=BICS"),1)="#","",_xll.BDP($B37,"CLASSIFICATION_LEVEL_1_CODE","CLASSIFICATION_SCHEME=BICS"))) | F37: =IF($B37="","",IF(LEFT(_xll.BDP($B37,"CLASSIFICATION_LEVEL_1_NAME","CLASSIFICATION_SCHEME=BICS"),1)="#","",_xll.BDP($B37,"CLASSIFICATION_LEVEL_1_NAME","CLASSIFICATION_SCHEME=BICS","SECURITY_NAME_LANG",$D$2))) | G37: =IF($B37="","",IF(LEFT(_xll.BDP($B37,"CLASSIFICATION_LEVEL_2_CODE","CLASSIFICATION_SCHEME=BICS"),1)="#","",_xll.BDP($B37,"CLASSIFICATION_LEVEL_2_CODE","CLASSIFICATION_SCHEME=BICS"))) | H37: =IF($B37="","",IF(LEFT(_xll.BDP($B37,"CLASSIFICATION_LEVEL_2_NAME","CLASSIFICATION_SCHEME=BICS"),1)="#","",_xll.BDP($B37,"CLASSIFICATION_LEVEL_2_NAME","CLASSIFICATION_SCHEME=BICS","SECURITY_NAME_LANG",$D$2))) | I37: =IF($B37="","",IF(LEFT(_xll.BDP($B37,"CLASSIFICATION_LEVEL_3_CODE","CLASSIFICATION_SCHEME=BICS"),1)="#","",_xll.BDP($B37,"CLASSIFICATION_LEVEL_3_CODE","CLASSIFICATION_SCHEME=BICS"))) | J37: =IF($B37="","",IF(LEFT(_xll.BDP($B37,"CLASSIFICATION_LEVEL_3_NAME","CLASSIFICATION_SCHEME=BICS"),1)="#","",_xll.BDP($B37,"CLASSIFICATION_LEVEL_3_NAME","CLASSIFICATION_SCHEME=BICS","SECURITY_NAME_LANG",$D$2))) | K37: =IF($B37="","",IF(LEFT(_xll.BDP($B37,"CLASSIFICATION_LEVEL_4_CODE","CLASSIFICATION_SCHEME=BICS"),1)="#","",_xll.BDP($B37,"CLASSIFICATION_LEVEL_4_CODE","CLASSIFICATION_SCHEME=BICS"))) | L37: =IF($B37="","",IF(LEFT(_xll.BDP($B37,"CLASSIFICATION_LEVEL_4_NAME","CLASSIFICATION_SCHEME=BICS"),1)="#","",_xll.BDP($B37,"CLASSIFICATION_LEVEL_4_NAME","CLASSIFICATION_SCHEME=BICS","SECURITY_NAME_LANG",$D$2))) | M37: =IF($B37="","",IF(LEFT(_xll.BDP($B37,"CLASSIFICATION_LEVEL_5_CODE","CLASSIFICATION_SCHEME=BICS"),1)="#","",_xll.BDP($B37,"CLASSIFICATION_LEVEL_5_CODE","CLASSIFICATION_SCHEME=BICS"))) | N37: =IF($B37="","",IF(LEFT(_xll.BDP($B37,"CLASSIFICATION_LEVEL_5_NAME","CLASSIFICATION_SCHEME=BICS"),1)="#","",_xll.BDP($B37,"CLASSIFICATION_LEVEL_5_NAME","CLASSIFICATION_SCHEME=BICS","SECURITY_NAME_LANG",$D$2))) | O37: =IF($B37="","",IF(LEFT(_xll.BDP($B37,"CLASSIFICATION_LEVEL_6_CODE","CLASSIFICATION_SCHEME=BICS"),1)="#","",_xll.BDP($B37,"CLASSIFICATION_LEVEL_6_CODE","CLASSIFICATION_SCHEME=BICS"))) | P37: =IF($B37="","",IF(LEFT(_xll.BDP($B37,"CLASSIFICATION_LEVEL_6_NAME","CLASSIFICATION_SCHEME=BICS"),1)="#","",_xll.BDP($B37,"CLASSIFICATION_LEVEL_6_NAME","CLASSIFICATION_SCHEME=BICS","SECURITY_NAME_LANG",$D$2))) | Q37: =IF($B37="","",IF(LEFT(_xll.BDP($B37,"CLASSIFICATION_LEVEL_7_CODE","CLASSIFICATION_SCHEME=BICS"),1)="#","",_xll.BDP($B37,"CLASSIFICATION_LEVEL_7_CODE","CLASSIFICATION_SCHEME=BICS"))) | R37: =IF($B37="","",IF(LEFT(_xll.BDP($B37,"CLASSIFICATION_LEVEL_7_NAME","CLASSIFICATION_SCHEME=BICS"),1)="#","",_xll.BDP($B37,"CLASSIFICATION_LEVEL_7_NAME","CLASSIFICATION_SCHEME=BICS","SECURITY_NAME_LANG",$D$2)))
C38: =IF($B38="","",_xll.BDP($B38,C$3)) | D38: =IF($B38="","",_xll.BDP($B38,D$3,"SECURITY_NAME_LANG",$D$2)) | E38: =IF($B38="","",IF(LEFT(_xll.BDP($B38,"CLASSIFICATION_LEVEL_1_CODE","CLASSIFICATION_SCHEME=BICS"),1)="#","",_xll.BDP($B38,"CLASSIFICATION_LEVEL_1_CODE","CLASSIFICATION_SCHEME=BICS"))) | F38: =IF($B38="","",IF(LEFT(_xll.BDP($B38,"CLASSIFICATION_LEVEL_1_NAME","CLASSIFICATION_SCHEME=BICS"),1)="#","",_xll.BDP($B38,"CLASSIFICATION_LEVEL_1_NAME","CLASSIFICATION_SCHEME=BICS","SECURITY_NAME_LANG",$D$2))) | G38: =IF($B38="","",IF(LEFT(_xll.BDP($B38,"CLASSIFICATION_LEVEL_2_CODE","CLASSIFICATION_SCHEME=BICS"),1)="#","",_xll.BDP($B38,"CLASSIFICATION_LEVEL_2_CODE","CLASSIFICATION_SCHEME=BICS"))) | H38: =IF($B38="","",IF(LEFT(_xll.BDP($B38,"CLASSIFICATION_LEVEL_2_NAME","CLASSIFICATION_SCHEME=BICS"),1)="#","",_xll.BDP($B38,"CLASSIFICATION_LEVEL_2_NAME","CLASSIFICATION_SCHEME=BICS","SECURITY_NAME_LANG",$D$2))) | I38: =IF($B38="","",IF(LEFT(_xll.BDP($B38,"CLASSIFICATION_LEVEL_3_CODE","CLASSIFICATION_SCHEME=BICS"),1)="#","",_xll.BDP($B38,"CLASSIFICATION_LEVEL_3_CODE","CLASSIFICATION_SCHEME=BICS"))) | J38: =IF($B38="","",IF(LEFT(_xll.BDP($B38,"CLASSIFICATION_LEVEL_3_NAME","CLASSIFICATION_SCHEME=BICS"),1)="#","",_xll.BDP($B38,"CLASSIFICATION_LEVEL_3_NAME","CLASSIFICATION_SCHEME=BICS","SECURITY_NAME_LANG",$D$2))) | K38: =IF($B38="","",IF(LEFT(_xll.BDP($B38,"CLASSIFICATION_LEVEL_4_CODE","CLASSIFICATION_SCHEME=BICS"),1)="#","",_xll.BDP($B38,"CLASSIFICATION_LEVEL_4_CODE","CLASSIFICATION_SCHEME=BICS"))) | L38: =IF($B38="","",IF(LEFT(_xll.BDP($B38,"CLASSIFICATION_LEVEL_4_NAME","CLASSIFICATION_SCHEME=BICS"),1)="#","",_xll.BDP($B38,"CLASSIFICATION_LEVEL_4_NAME","CLASSIFICATION_SCHEME=BICS","SECURITY_NAME_LANG",$D$2))) | M38: =IF($B38="","",IF(LEFT(_xll.BDP($B38,"CLASSIFICATION_LEVEL_5_CODE","CLASSIFICATION_SCHEME=BICS"),1)="#","",_xll.BDP($B38,"CLASSIFICATION_LEVEL_5_CODE","CLASSIFICATION_SCHEME=BICS"))) | N38: =IF($B38="","",IF(LEFT(_xll.BDP($B38,"CLASSIFICATION_LEVEL_5_NAME","CLASSIFICATION_SCHEME=BICS"),1)="#","",_xll.BDP($B38,"CLASSIFICATION_LEVEL_5_NAME","CLASSIFICATION_SCHEME=BICS","SECURITY_NAME_LANG",$D$2))) | O38: =IF($B38="","",IF(LEFT(_xll.BDP($B38,"CLASSIFICATION_LEVEL_6_CODE","CLASSIFICATION_SCHEME=BICS"),1)="#","",_xll.BDP($B38,"CLASSIFICATION_LEVEL_6_CODE","CLASSIFICATION_SCHEME=BICS"))) | P38: =IF($B38="","",IF(LEFT(_xll.BDP($B38,"CLASSIFICATION_LEVEL_6_NAME","CLASSIFICATION_SCHEME=BICS"),1)="#","",_xll.BDP($B38,"CLASSIFICATION_LEVEL_6_NAME","CLASSIFICATION_SCHEME=BICS","SECURITY_NAME_LANG",$D$2))) | Q38: =IF($B38="","",IF(LEFT(_xll.BDP($B38,"CLASSIFICATION_LEVEL_7_CODE","CLASSIFICATION_SCHEME=BICS"),1)="#","",_xll.BDP($B38,"CLASSIFICATION_LEVEL_7_CODE","CLASSIFICATION_SCHEME=BICS"))) | R38: =IF($B38="","",IF(LEFT(_xll.BDP($B38,"CLASSIFICATION_LEVEL_7_NAME","CLASSIFICATION_SCHEME=BICS"),1)="#","",_xll.BDP($B38,"CLASSIFICATION_LEVEL_7_NAME","CLASSIFICATION_SCHEME=BICS","SECURITY_NAME_LANG",$D$2)))
C39: =IF($B39="","",_xll.BDP($B39,C$3)) | D39: =IF($B39="","",_xll.BDP($B39,D$3,"SECURITY_NAME_LANG",$D$2)) | E39: =IF($B39="","",IF(LEFT(_xll.BDP($B39,"CLASSIFICATION_LEVEL_1_CODE","CLASSIFICATION_SCHEME=BICS"),1)="#","",_xll.BDP($B39,"CLASSIFICATION_LEVEL_1_CODE","CLASSIFICATION_SCHEME=BICS"))) | F39: =IF($B39="","",IF(LEFT(_xll.BDP($B39,"CLASSIFICATION_LEVEL_1_NAME","CLASSIFICATION_SCHEME=BICS"),1)="#","",_xll.BDP($B39,"CLASSIFICATION_LEVEL_1_NAME","CLASSIFICATION_SCHEME=BICS","SECURITY_NAME_LANG",$D$2))) | G39: =IF($B39="","",IF(LEFT(_xll.BDP($B39,"CLASSIFICATION_LEVEL_2_CODE","CLASSIFICATION_SCHEME=BICS"),1)="#","",_xll.BDP($B39,"CLASSIFICATION_LEVEL_2_CODE","CLASSIFICATION_SCHEME=BICS"))) | H39: =IF($B39="","",IF(LEFT(_xll.BDP($B39,"CLASSIFICATION_LEVEL_2_NAME","CLASSIFICATION_SCHEME=BICS"),1)="#","",_xll.BDP($B39,"CLASSIFICATION_LEVEL_2_NAME","CLASSIFICATION_SCHEME=BICS","SECURITY_NAME_LANG",$D$2))) | I39: =IF($B39="","",IF(LEFT(_xll.BDP($B39,"CLASSIFICATION_LEVEL_3_CODE","CLASSIFICATION_SCHEME=BICS"),1)="#","",_xll.BDP($B39,"CLASSIFICATION_LEVEL_3_CODE","CLASSIFICATION_SCHEME=BICS"))) | J39: =IF($B39="","",IF(LEFT(_xll.BDP($B39,"CLASSIFICATION_LEVEL_3_NAME","CLASSIFICATION_SCHEME=BICS"),1)="#","",_xll.BDP($B39,"CLASSIFICATION_LEVEL_3_NAME","CLASSIFICATION_SCHEME=BICS","SECURITY_NAME_LANG",$D$2))) | K39: =IF($B39="","",IF(LEFT(_xll.BDP($B39,"CLASSIFICATION_LEVEL_4_CODE","CLASSIFICATION_SCHEME=BICS"),1)="#","",_xll.BDP($B39,"CLASSIFICATION_LEVEL_4_CODE","CLASSIFICATION_SCHEME=BICS"))) | L39: =IF($B39="","",IF(LEFT(_xll.BDP($B39,"CLASSIFICATION_LEVEL_4_NAME","CLASSIFICATION_SCHEME=BICS"),1)="#","",_xll.BDP($B39,"CLASSIFICATION_LEVEL_4_NAME","CLASSIFICATION_SCHEME=BICS","SECURITY_NAME_LANG",$D$2))) | M39: =IF($B39="","",IF(LEFT(_xll.BDP($B39,"CLASSIFICATION_LEVEL_5_CODE","CLASSIFICATION_SCHEME=BICS"),1)="#","",_xll.BDP($B39,"CLASSIFICATION_LEVEL_5_CODE","CLASSIFICATION_SCHEME=BICS"))) | N39: =IF($B39="","",IF(LEFT(_xll.BDP($B39,"CLASSIFICATION_LEVEL_5_NAME","CLASSIFICATION_SCHEME=BICS"),1)="#","",_xll.BDP($B39,"CLASSIFICATION_LEVEL_5_NAME","CLASSIFICATION_SCHEME=BICS","SECURITY_NAME_LANG",$D$2))) | O39: =IF($B39="","",IF(LEFT(_xll.BDP($B39,"CLASSIFICATION_LEVEL_6_CODE","CLASSIFICATION_SCHEME=BICS"),1)="#","",_xll.BDP($B39,"CLASSIFICATION_LEVEL_6_CODE","CLASSIFICATION_SCHEME=BICS"))) | P39: =IF($B39="","",IF(LEFT(_xll.BDP($B39,"CLASSIFICATION_LEVEL_6_NAME","CLASSIFICATION_SCHEME=BICS"),1)="#","",_xll.BDP($B39,"CLASSIFICATION_LEVEL_6_NAME","CLASSIFICATION_SCHEME=BICS","SECURITY_NAME_LANG",$D$2))) | Q39: =IF($B39="","",IF(LEFT(_xll.BDP($B39,"CLASSIFICATION_LEVEL_7_CODE","CLASSIFICATION_SCHEME=BICS"),1)="#","",_xll.BDP($B39,"CLASSIFICATION_LEVEL_7_CODE","CLASSIFICATION_SCHEME=BICS"))) | R39: =IF($B39="","",IF(LEFT(_xll.BDP($B39,"CLASSIFICATION_LEVEL_7_NAME","CLASSIFICATION_SCHEME=BICS"),1)="#","",_xll.BDP($B39,"CLASSIFICATION_LEVEL_7_NAME","CLASSIFICATION_SCHEME=BICS","SECURITY_NAME_LANG",$D$2)))
C40: =IF($B40="","",_xll.BDP($B40,C$3)) | D40: =IF($B40="","",_xll.BDP($B40,D$3,"SECURITY_NAME_LANG",$D$2)) | E40: =IF($B40="","",IF(LEFT(_xll.BDP($B40,"CLASSIFICATION_LEVEL_1_CODE","CLASSIFICATION_SCHEME=BICS"),1)="#","",_xll.BDP($B40,"CLASSIFICATION_LEVEL_1_CODE","CLASSIFICATION_SCHEME=BICS"))) | F40: =IF($B40="","",IF(LEFT(_xll.BDP($B40,"CLASSIFICATION_LEVEL_1_NAME","CLASSIFICATION_SCHEME=BICS"),1)="#","",_xll.BDP($B40,"CLASSIFICATION_LEVEL_1_NAME","CLASSIFICATION_SCHEME=BICS","SECURITY_NAME_LANG",$D$2))) | G40: =IF($B40="","",IF(LEFT(_xll.BDP($B40,"CLASSIFICATION_LEVEL_2_CODE","CLASSIFICATION_SCHEME=BICS"),1)="#","",_xll.BDP($B40,"CLASSIFICATION_LEVEL_2_CODE","CLASSIFICATION_SCHEME=BICS"))) | H40: =IF($B40="","",IF(LEFT(_xll.BDP($B40,"CLASSIFICATION_LEVEL_2_NAME","CLASSIFICATION_SCHEME=BICS"),1)="#","",_xll.BDP($B40,"CLASSIFICATION_LEVEL_2_NAME","CLASSIFICATION_SCHEME=BICS","SECURITY_NAME_LANG",$D$2))) | I40: =IF($B40="","",IF(LEFT(_xll.BDP($B40,"CLASSIFICATION_LEVEL_3_CODE","CLASSIFICATION_SCHEME=BICS"),1)="#","",_xll.BDP($B40,"CLASSIFICATION_LEVEL_3_CODE","CLASSIFICATION_SCHEME=BICS"))) | J40: =IF($B40="","",IF(LEFT(_xll.BDP($B40,"CLASSIFICATION_LEVEL_3_NAME","CLASSIFICATION_SCHEME=BICS"),1)="#","",_xll.BDP($B40,"CLASSIFICATION_LEVEL_3_NAME","CLASSIFICATION_SCHEME=BICS","SECURITY_NAME_LANG",$D$2))) | K40: =IF($B40="","",IF(LEFT(_xll.BDP($B40,"CLASSIFICATION_LEVEL_4_CODE","CLASSIFICATION_SCHEME=BICS"),1)="#","",_xll.BDP($B40,"CLASSIFICATION_LEVEL_4_CODE","CLASSIFICATION_SCHEME=BICS"))) | L40: =IF($B40="","",IF(LEFT(_xll.BDP($B40,"CLASSIFICATION_LEVEL_4_NAME","CLASSIFICATION_SCHEME=BICS"),1)="#","",_xll.BDP($B40,"CLASSIFICATION_LEVEL_4_NAME","CLASSIFICATION_SCHEME=BICS","SECURITY_NAME_LANG",$D$2))) | M40: =IF($B40="","",IF(LEFT(_xll.BDP($B40,"CLASSIFICATION_LEVEL_5_CODE","CLASSIFICATION_SCHEME=BICS"),1)="#","",_xll.BDP($B40,"CLASSIFICATION_LEVEL_5_CODE","CLASSIFICATION_SCHEME=BICS"))) | N40: =IF($B40="","",IF(LEFT(_xll.BDP($B40,"CLASSIFICATION_LEVEL_5_NAME","CLASSIFICATION_SCHEME=BICS"),1)="#","",_xll.BDP($B40,"CLASSIFICATION_LEVEL_5_NAME","CLASSIFICATION_SCHEME=BICS","SECURITY_NAME_LANG",$D$2))) | O40: =IF($B40="","",IF(LEFT(_xll.BDP($B40,"CLASSIFICATION_LEVEL_6_CODE","CLASSIFICATION_SCHEME=BICS"),1)="#","",_xll.BDP($B40,"CLASSIFICATION_LEVEL_6_CODE","CLASSIFICATION_SCHEME=BICS"))) | P40: =IF($B40="","",IF(LEFT(_xll.BDP($B40,"CLASSIFICATION_LEVEL_6_NAME","CLASSIFICATION_SCHEME=BICS"),1)="#","",_xll.BDP($B40,"CLASSIFICATION_LEVEL_6_NAME","CLASSIFICATION_SCHEME=BICS","SECURITY_NAME_LANG",$D$2))) | Q40: =IF($B40="","",IF(LEFT(_xll.BDP($B40,"CLASSIFICATION_LEVEL_7_CODE","CLASSIFICATION_SCHEME=BICS"),1)="#","",_xll.BDP($B40,"CLASSIFICATION_LEVEL_7_CODE","CLASSIFICATION_SCHEME=BICS"))) | R40: =IF($B40="","",IF(LEFT(_xll.BDP($B40,"CLASSIFICATION_LEVEL_7_NAME","CLASSIFICATION_SCHEME=BICS"),1)="#","",_xll.BDP($B40,"CLASSIFICATION_LEVEL_7_NAME","CLASSIFICATION_SCHEME=BICS","SECURITY_NAME_LANG",$D$2)))
C41: =IF($B41="","",_xll.BDP($B41,C$3)) | D41: =IF($B41="","",_xll.BDP($B41,D$3,"SECURITY_NAME_LANG",$D$2)) | E41: =IF($B41="","",IF(LEFT(_xll.BDP($B41,"CLASSIFICATION_LEVEL_1_CODE","CLASSIFICATION_SCHEME=BICS"),1)="#","",_xll.BDP($B41,"CLASSIFICATION_LEVEL_1_CODE","CLASSIFICATION_SCHEME=BICS"))) | F41: =IF($B41="","",IF(LEFT(_xll.BDP($B41,"CLASSIFICATION_LEVEL_1_NAME","CLASSIFICATION_SCHEME=BICS"),1)="#","",_xll.BDP($B41,"CLASSIFICATION_LEVEL_1_NAME","CLASSIFICATION_SCHEME=BICS","SECURITY_NAME_LANG",$D$2))) | G41: =IF($B41="","",IF(LEFT(_xll.BDP($B41,"CLASSIFICATION_LEVEL_2_CODE","CLASSIFICATION_SCHEME=BICS"),1)="#","",_xll.BDP($B41,"CLASSIFICATION_LEVEL_2_CODE","CLASSIFICATION_SCHEME=BICS"))) | H41: =IF($B41="","",IF(LEFT(_xll.BDP($B41,"CLASSIFICATION_LEVEL_2_NAME","CLASSIFICATION_SCHEME=BICS"),1)="#","",_xll.BDP($B41,"CLASSIFICATION_LEVEL_2_NAME","CLASSIFICATION_SCHEME=BICS","SECURITY_NAME_LANG",$D$2))) | I41: =IF($B41="","",IF(LEFT(_xll.BDP($B41,"CLASSIFICATION_LEVEL_3_CODE","CLASSIFICATION_SCHEME=BICS"),1)="#","",_xll.BDP($B41,"CLASSIFICATION_LEVEL_3_CODE","CLASSIFICATION_SCHEME=BICS"))) | J41: =IF($B41="","",IF(LEFT(_xll.BDP($B41,"CLASSIFICATION_LEVEL_3_NAME","CLASSIFICATION_SCHEME=BICS"),1)="#","",_xll.BDP($B41,"CLASSIFICATION_LEVEL_3_NAME","CLASSIFICATION_SCHEME=BICS","SECURITY_NAME_LANG",$D$2))) | K41: =IF($B41="","",IF(LEFT(_xll.BDP($B41,"CLASSIFICATION_LEVEL_4_CODE","CLASSIFICATION_SCHEME=BICS"),1)="#","",_xll.BDP($B41,"CLASSIFICATION_LEVEL_4_CODE","CLASSIFICATION_SCHEME=BICS"))) | L41: =IF($B41="","",IF(LEFT(_xll.BDP($B41,"CLASSIFICATION_LEVEL_4_NAME","CLASSIFICATION_SCHEME=BICS"),1)="#","",_xll.BDP($B41,"CLASSIFICATION_LEVEL_4_NAME","CLASSIFICATION_SCHEME=BICS","SECURITY_NAME_LANG",$D$2))) | M41: =IF($B41="","",IF(LEFT(_xll.BDP($B41,"CLASSIFICATION_LEVEL_5_CODE","CLASSIFICATION_SCHEME=BICS"),1)="#","",_xll.BDP($B41,"CLASSIFICATION_LEVEL_5_CODE","CLASSIFICATION_SCHEME=BICS"))) | N41: =IF($B41="","",IF(LEFT(_xll.BDP($B41,"CLASSIFICATION_LEVEL_5_NAME","CLASSIFICATION_SCHEME=BICS"),1)="#","",_xll.BDP($B41,"CLASSIFICATION_LEVEL_5_NAME","CLASSIFICATION_SCHEME=BICS","SECURITY_NAME_LANG",$D$2))) | O41: =IF($B41="","",IF(LEFT(_xll.BDP($B41,"CLASSIFICATION_LEVEL_6_CODE","CLASSIFICATION_SCHEME=BICS"),1)="#","",_xll.BDP($B41,"CLASSIFICATION_LEVEL_6_CODE","CLASSIFICATION_SCHEME=BICS"))) | P41: =IF($B41="","",IF(LEFT(_xll.BDP($B41,"CLASSIFICATION_LEVEL_6_NAME","CLASSIFICATION_SCHEME=BICS"),1)="#","",_xll.BDP($B41,"CLASSIFICATION_LEVEL_6_NAME","CLASSIFICATION_SCHEME=BICS","SECURITY_NAME_LANG",$D$2))) | Q41: =IF($B41="","",IF(LEFT(_xll.BDP($B41,"CLASSIFICATION_LEVEL_7_CODE","CLASSIFICATION_SCHEME=BICS"),1)="#","",_xll.BDP($B41,"CLASSIFICATION_LEVEL_7_CODE","CLASSIFICATION_SCHEME=BICS"))) | R41: =IF($B41="","",IF(LEFT(_xll.BDP($B41,"CLASSIFICATION_LEVEL_7_NAME","CLASSIFICATION_SCHEME=BICS"),1)="#","",_xll.BDP($B41,"CLASSIFICATION_LEVEL_7_NAME","CLASSIFICATION_SCHEME=BICS","SECURITY_NAME_LANG",$D$2)))
